Workbook

Sheet Dashboard
F1: MONTH
B17: Today | C17: Month | D17: Last Week | E17: Yesterday | H17: Vendors | I17: Bought | J17: Sold | K17: Stock | L17: Revenue | M17: Spent | N17: Profit | O17: % | Q17: Last 20 Sold | R17: Profit | S17: Vendor | T17: Date
A18: RVN | B18: =SUMIFS(Inventory!F2:F7005, Inventory!J2:J7005, "closed", Inventory!D2:D7005, "="&TODAY()) -> 0 | C18: =SUMIFS(Inventory!F2:F7005, Inventory!J2:J7005, "closed", Inventory!D2:D7005, ">="&DATE(YEAR(TODAY()), MONTH(TODAY()), 1), Inventory!D2:D7005, "<="&EOMONTH(TODAY(), 0)) -> 30.89 | D18: =SUMIFS(Inventory!F2:F7005, Inventory!J2:J7005, "closed", Inventory!D2:D7005, ">="&TODAY()-WEEKDAY(TODAY(), 2)-7, Inventory!D2:D7005, "<="&TODAY()-WEEKDAY(TODAY(), 2)-1) -> 138.07 | E18: =SUMIFS(Inventory!F2:F7005, Inventory!J2:J7005, "closed", Inventory!D2:D7005, "="&TODAY()-1) -> 0 | H18: Other | I18: =COUNTIF(Inventory!B:B,H18) -> 66 | J18: =COUNTIFS(Inventory!B:B,H18,Inventory!J:J,"Closed") -> 65 | K18: =(I18-J18) -> 1 | L18: =SUMIF(Inventory!B:B,H18,Inventory!F:F) -> 1371.59 | M18: =SUMIF(Inventory!B:B,H18,Inventory!E:E) -> 1006.89 | N18: =SUMIF(Inventory!B:B,H18,Inventory!G:G) -> 364.7 | O18: =(N18/L18) -> 0.26589579 | Q18: =IFERROR(__xludf.DUMMYFUNCTION("SORTN({Inventory!A2:A7005, Inventory!G2:G7005, Inventory!B2:B7005, Inventory!D2:D7005}, 20, 0, Inventory!D2:D7005, False) "),"Worms Armageddon") -> Worms Armageddon | R18: =IFERROR(__xludf.DUMMYFUNCTION("""COMPUTED_VALUE"""),1.28) -> 1.28 | S18: =IFERROR(__xludf.DUMMYFUNCTION("""COMPUTED_VALUE"""),"G2A") -> G2A | T18: =IFERROR(__xludf.DUMMYFUNCTION("""COMPUTED_VALUE"""),46207.0) -> 46207
H19: Eneba | I19: =COUNTIF(Inventory!B:B,H19) -> 427 | J19: =COUNTIFS(Inventory!B:B,H19,Inventory!J:J,"Closed") -> 409 | K19: =(I19-J19) -> 18 | L19: =SUMIF(Inventory!B:B,H19,Inventory!F:F) -> 8127.36 | M19: =SUMIF(Inventory!B:B,H19,Inventory!E:E) -> 6947.45 | N19: =SUMIF(Inventory!B:B,H19,Inventory!G:G) -> 1179.91 | O19: =(N19/L19) -> 0.14517752 | Q19: =IFERROR(__xludf.DUMMYFUNCTION("""COMPUTED_VALUE"""),"Tempest Rising") -> Tempest Rising | R19: =IFERROR(__xludf.DUMMYFUNCTION("""COMPUTED_VALUE"""),5.16) -> 5.16 | S19: =IFERROR(__xludf.DUMMYFUNCTION("""COMPUTED_VALUE"""),"King") -> King | T19: =IFERROR(__xludf.DUMMYFUNCTION("""COMPUTED_VALUE"""),46205.0) -> 46205
A20: =IF(B20 > C20, "🟢", "🔴") -> 🔴 | B20: =IFERROR(SUMIFS(Inventory!F2:F7005, Inventory!D2:D7005, "="&TODAY(), Inventory!J2:J7005, "Closed") / COUNTIFS(Inventory!D2:D7005, "="&TODAY(), Inventory!J2:J7005, "Closed"), 0) -> 0 | C20: =SUMIFS(Inventory!F2:F7005, Inventory!D2:D7005, ">="&DATE(YEAR(TODAY()), MONTH(TODAY()), 1), Inventory!D2:D7005, "<="&EOMONTH(TODAY(), 0), Inventory!J2:J7005, "Closed") / COUNTIFS(Inventory!D2:D7005, ">="&DATE(YEAR(TODAY()), MONTH(TODAY()), 1), Inventory!D2:D7005, "<="&EOMONTH(TODAY(), 0), Inventory!J2:J7005, "Closed") -> 10.296667 | D20: =SUMIFS(Inventory!F2:F7005, Inventory!D2:D7005, ">="&TODAY()-WEEKDAY(TODAY(), 2)-7, Inventory!D2:D7005, "<="&TODAY()-WEEKDAY(TODAY(), 2)-1, Inventory!J2:J7005, "Closed") / COUNTIFS(Inventory!D2:D7005, ">="&TODAY()-WEEKDAY(TODAY(), 2)-7, Inventory!D2:D7005, "<="&TODAY()-WEEKDAY(TODAY(), 2)-1, Inventory!J2:J7005, "Closed") -> 13.807 | E20: =IFERROR(SUMIFS(Inventory!F2:F7005, Inventory!D2:D7005, "="&TODAY()-1, Inventory!J2:J7005, "Closed") / COUNTIFS(Inventory!D2:D7005, "="&TODAY()-1, Inventory!J2:J7005, "Closed"),0) -> 0 | H20: Fanatical | I20: =COUNTIF(Inventory!B:B,H20) -> 2295 | J20: =COUNTIFS(Inventory!B:B,H20,Inventory!J:J,"Closed") -> 2275 | K20: =(I20-J20) -> 20 | L20: =SUMIF(Inventory!B:B,H20,Inventory!F:F) -> 20919.141 | M20: =SUMIF(Inventory!B:B,H20,Inventory!E:E) -> 16186.38 | N20: =SUMIF(Inventory!B:B,H20,Inventory!G:G) -> 4732.761 | O20: =(N20/L20) -> 0.2262407 | Q20: =IFERROR(__xludf.DUMMYFUNCTION("""COMPUTED_VALUE"""),"Dead by Daylight") -> Dead by Daylight | R20: =IFERROR(__xludf.DUMMYFUNCTION("""COMPUTED_VALUE"""),5.0600000000000005) -> 5.06 | S20: =IFERROR(__xludf.DUMMYFUNCTION("""COMPUTED_VALUE"""),"G2A") -> G2A | T20: =IFERROR(__xludf.DUMMYFUNCTION("""COMPUTED_VALUE"""),46204.0) -> 46204
A21: SPNT | B21: =SUMIFS(Inventory!E2:E7005, Inventory!J2:J7005, "closed", Inventory!D2:D7005, "="&TODAY()) -> 0 | C21: =SUMIFS(Inventory!E2:E7005, Inventory!J2:J7005, "closed", Inventory!D2:D7005, ">="&DATE(YEAR(TODAY()), MONTH(TODAY()), 1), Inventory!D2:D7005, "<="&EOMONTH(TODAY(), 0)) -> 19.39 | D21: =SUMIFS(Inventory!E2:E7005, Inventory!J2:J7005, "closed", Inventory!D2:D7005, ">="&TODAY()-WEEKDAY(TODAY(), 2)-7, Inventory!D2:D7005, "<="&TODAY()-WEEKDAY(TODAY(), 2)-1) -> 95.5 | E21: =SUMIFS(Inventory!E2:E7005, Inventory!J2:J7005, "closed", Inventory!D2:D7005, "="&TODAY()-1) -> 0 | H21: Gamivo | I21: =COUNTIF(Inventory!B:B,H21) -> 802 | J21: =COUNTIFS(Inventory!B:B,H21,Inventory!J:J,"Closed") -> 741 | K21: =(I21-J21) -> 61 | L21: =SUMIF(Inventory!B:B,H21,Inventory!F:F) -> 16077.07 | M21: =SUMIF(Inventory!B:B,H21,Inventory!E:E) -> 14544.94 | N21: =SUMIF(Inventory!B:B,H21,Inventory!G:G) -> 1532.13 | O21: =(N21/L21) -> 0.095299081 | Q21: =IFERROR(__xludf.DUMMYFUNCTION("""COMPUTED_VALUE"""),"SoulQuest") -> SoulQuest | R21: =IFERROR(__xludf.DUMMYFUNCTION("""COMPUTED_VALUE"""),1.1500000000000004) -> 1.15 | S21: =IFERROR(__xludf.DUMMYFUNCTION("""COMPUTED_VALUE"""),"GreenMan") -> GreenMan | T21: =IFERROR(__xludf.DUMMYFUNCTION("""COMPUTED_VALUE"""),46203.0) -> 46203
H22: GreenMan | I22: =COUNTIF(Inventory!B:B,H22) -> 1458 | J22: =COUNTIFS(Inventory!B:B,H22,Inventory!J:J,"Closed") -> 1436 | K22: =(I22-J22) -> 22 | L22: =SUMIF(Inventory!B:B,H22,Inventory!F:F) -> 22532.81 | M22: =SUMIF(Inventory!B:B,H22,Inventory!E:E) -> 17434.526 | N22: =SUMIF(Inventory!B:B,H22,Inventory!G:G) -> 5098.2841 | O22: =(N22/L22) -> 0.22626047 | Q22: =IFERROR(__xludf.DUMMYFUNCTION("""COMPUTED_VALUE"""),"Dead by Daylight") -> Dead by Daylight | R22: =IFERROR(__xludf.DUMMYFUNCTION("""COMPUTED_VALUE"""),5.0600000000000005) -> 5.06 | S22: =IFERROR(__xludf.DUMMYFUNCTION("""COMPUTED_VALUE"""),"G2A") -> G2A | T22: =IFERROR(__xludf.DUMMYFUNCTION("""COMPUTED_VALUE"""),46203.0) -> 46203
A23: =IF(B23 < C23, "🟢", "🔴") -> 🟢 | B23: =IFERROR(SUMIFS(Inventory!E2:E7005, Inventory!D2:D7005, "="&TODAY(), Inventory!J2:J7005, "Closed") / COUNTIFS(Inventory!D2:D7005, "="&TODAY(), Inventory!J2:J7005, "Closed"), 0) -> 0 | C23: =SUMIFS(Inventory!E2:E7005, Inventory!D2:D7005, ">="&DATE(YEAR(TODAY()), MONTH(TODAY()), 1), Inventory!D2:D7005, "<="&EOMONTH(TODAY(), 0), Inventory!J2:J7005, "Closed") / COUNTIFS(Inventory!D2:D7005, ">="&DATE(YEAR(TODAY()), MONTH(TODAY()), 1), Inventory!D2:D7005, "<="&EOMONTH(TODAY(), 0), Inventory!J2:J7005, "Closed") -> 6.4633333 | D23: =SUMIFS(Inventory!E2:E7005, Inventory!D2:D7005, ">="&TODAY()-WEEKDAY(TODAY(), 2)-7, Inventory!D2:D7005, "<="&TODAY()-WEEKDAY(TODAY(), 2)-1, Inventory!J2:J7005, "Closed") / COUNTIFS(Inventory!D2:D7005, ">="&TODAY()-WEEKDAY(TODAY(), 2)-7, Inventory!D2:D7005, "<="&TODAY()-WEEKDAY(TODAY(), 2)-1, Inventory!J2:J7005, "Closed") -> 9.55 | E23: =IFERROR(SUMIFS(Inventory!E2:E7005, Inventory!D2:D7005, "="&TODAY()-1, Inventory!J2:J7005, "Closed") / COUNTIFS(Inventory!D2:D7005, "="&TODAY()-1, Inventory!J2:J7005, "Closed"),0) -> 0 | H23: GamesPlanet | I23: =COUNTIF(Inventory!B:B,H23) -> 597 | J23: =COUNTIFS(Inventory!B:B,H23,Inventory!J:J,"Closed") -> 587 | K23: =(I23-J23) -> 10 | L23: =SUMIF(Inventory!B:B,H23,Inventory!F:F) -> 9352.43 | M23: =SUMIF(Inventory!B:B,H23,Inventory!E:E) -> 7271.89 | N23: =SUMIF(Inventory!B:B,H23,Inventory!G:G) -> 2080.54 | O23: =(N23/L23) -> 0.22245983 | Q23: =IFERROR(__xludf.DUMMYFUNCTION("""COMPUTED_VALUE"""),"Dead by Daylight") -> Dead by Daylight | R23: =IFERROR(__xludf.DUMMYFUNCTION("""COMPUTED_VALUE"""),5.07) -> 5.07 | S23: =IFERROR(__xludf.DUMMYFUNCTION("""COMPUTED_VALUE"""),"G2A") -> G2A | T23: =IFERROR(__xludf.DUMMYFUNCTION("""COMPUTED_VALUE"""),46202.0) -> 46202
A24: PRFT | B24: =SUMIFS(Inventory!G2:G7005, Inventory!J2:J7005, "closed", Inventory!D2:D7005, "="&TODAY()) -> 0 | C24: =SUMIFS(Inventory!G2:G7005, Inventory!J2:J7005, "closed", Inventory!D2:D7005, ">="&DATE(YEAR(TODAY()), MONTH(TODAY()), 1), Inventory!D2:D7005, "<="&EOMONTH(TODAY(), 0)) -> 11.5 | D24: =SUMIFS(Inventory!G2:G7005, Inventory!J2:J7005, "closed", Inventory!D2:D7005, ">="&TODAY()-WEEKDAY(TODAY(), 2)-7, Inventory!D2:D7005, "<="&TODAY()-WEEKDAY(TODAY(), 2)-1) -> 42.57 | E24: =SUMIFS(Inventory!G2:G7005, Inventory!J2:J7005, "closed", Inventory!D2:D7005, "="&TODAY()-1) -> 0 | H24: G2A | I24: =COUNTIF(Inventory!B:B,H24) -> 716 | J24: =COUNTIFS(Inventory!B:B,H24,Inventory!J:J,"Closed") -> 688 | K24: =(I24-J24) -> 28 | L24: =SUMIF(Inventory!B:B,H24,Inventory!F:F) -> 11123.06 | M24: =SUMIF(Inventory!B:B,H24,Inventory!E:E) -> 9522.18 | N24: =SUMIF(Inventory!B:B,H24,Inventory!G:G) -> 1600.88 | O24: =(N24/L24) -> 0.14392442 | Q24: =IFERROR(__xludf.DUMMYFUNCTION("""COMPUTED_VALUE"""),"Sniper Elite 5 Deluxe Edition") -> Sniper Elite 5 Deluxe Edition | R24: =IFERROR(__xludf.DUMMYFUNCTION("""COMPUTED_VALUE"""),0.129999999999999) -> 0.13 | S24: =IFERROR(__xludf.DUMMYFUNCTION("""COMPUTED_VALUE"""),"K4G") -> K4G | T24: =IFERROR(__xludf.DUMMYFUNCTION("""COMPUTED_VALUE"""),46201.0) -> 46201
H25: IndieGala | I25: =COUNTIF(Inventory!B:B,H25) -> 23 | J25: =COUNTIFS(Inventory!B:B,H25,Inventory!J:J,"Closed") -> 22 | K25: =(I25-J25) -> 1 | L25: =SUMIF(Inventory!B:B,H25,Inventory!F:F) -> 131.66 | M25: =SUMIF(Inventory!B:B,H25,Inventory!E:E) -> 135.83 | N25: =SUMIF(Inventory!B:B,H25,Inventory!G:G) -> -4.17 | O25: =(N25/L25) -> -0.03167249 | Q25: =IFERROR(__xludf.DUMMYFUNCTION("""COMPUTED_VALUE"""),"Tempest Rising") -> Tempest Rising | R25: =IFERROR(__xludf.DUMMYFUNCTION("""COMPUTED_VALUE"""),6.16) -> 6.16 | S25: =IFERROR(__xludf.DUMMYFUNCTION("""COMPUTED_VALUE"""),"King") -> King | T25: =IFERROR(__xludf.DUMMYFUNCTION("""COMPUTED_VALUE"""),46201.0) -> 46201
A26: =IF(B26 > C26, "🟢", "🔴") -> 🔴 | B26: =IFERROR((SUMIFS(Inventory!F2:F7005, Inventory!D2:D7005, "="&TODAY(), Inventory!J2:J7005, "Closed") - SUMIFS(Inventory!E2:E7005, Inventory!D2:D7005, "="&TODAY(), Inventory!J2:J7005, "Closed")) / COUNTIFS(Inventory!D2:D7005, "="&TODAY(), Inventory!J2:J7005, "Closed"), 0) -> 0 | C26: =(SUMIFS(Inventory!F2:F7005, Inventory!D2:D7005, ">="&DATE(YEAR(TODAY()), MONTH(TODAY()), 1), Inventory!D2:D7005, "<="&EOMONTH(TODAY(), 0), Inventory!J2:J7005, "Closed") - SUMIFS(Inventory!E2:E7005, Inventory!D2:D7005, ">="&DATE(YEAR(TODAY()), MONTH(TODAY()), 1), Inventory!D2:D7005, "<="&EOMONTH(TODAY(), 0), Inventory!J2:J7005, "Closed")) / COUNTIFS(Inventory!D2:D7005, ">="&DATE(YEAR(TODAY()), MONTH(TODAY()), 1), Inventory!D2:D7005, "<="&EOMONTH(TODAY(), 0), Inventory!J2:J7005, "Closed") -> 3.8333333 | D26: =(SUMIFS(Inventory!F2:F7005, Inventory!D2:D7005, ">="&TODAY()-WEEKDAY(TODAY(), 2)-7, Inventory!D2:D7005, "<="&TODAY()-WEEKDAY(TODAY(), 2)-1, Inventory!J2:J7005, "Closed") - SUMIFS(Inventory!E2:E7005, Inventory!D2:D7005, ">="&TODAY()-WEEKDAY(TODAY(), 2)-7, Inventory!D2:D7005, "<="&TODAY()-WEEKDAY(TODAY(), 2)-1, Inventory!J2:J7005, "Closed")) / COUNTIFS(Inventory!D2:D7005, ">="&TODAY()-WEEKDAY(TODAY(), 2)-7, Inventory!D2:D7005, "<="&TODAY()-WEEKDAY(TODAY(), 2)-1, Inventory!J2:J7005, "Closed") -> 4.257 | E26: =IFERROR((SUMIFS(Inventory!F2:F7005, Inventory!D2:D7005, "="&TODAY()-1, Inventory!J2:J7005, "Closed") - SUMIFS(Inventory!E2:E7005, Inventory!D2:D7005, "="&TODAY()-1, Inventory!J2:J7005, "Closed")) / COUNTIFS(Inventory!D2:D7005, "="&TODAY()-1, Inventory!J2:J7005, "Closed"),0) -> 0 | H26: CDKeys | I26: =COUNTIF(Inventory!B:B,H26) -> 1797 | J26: =COUNTIFS(Inventory!B:B,H26,Inventory!J:J,"Closed") -> 1745 | K26: =(I26-J26) -> 52 | L26: =SUMIF(Inventory!B:B,H26,Inventory!F:F) -> 30579.94 | M26: =SUMIF(Inventory!B:B,H26,Inventory!E:E) -> 25908.24 | N26: =SUMIF(Inventory!B:B,H26,Inventory!G:G) -> 4671.7 | O26: =(N26/L26) -> 0.15277008 | Q26: =IFERROR(__xludf.DUMMYFUNCTION("""COMPUTED_VALUE"""),"Dead by Daylight") -> Dead by Daylight | R26: =IFERROR(__xludf.DUMMYFUNCTION("""COMPUTED_VALUE"""),6.75) -> 6.75 | S26: =IFERROR(__xludf.DUMMYFUNCTION("""COMPUTED_VALUE"""),"G2A") -> G2A | T26: =IFERROR(__xludf.DUMMYFUNCTION("""COMPUTED_VALUE"""),46201.0) -> 46201
A27: SOLD | B27: =COUNTIFS(Inventory!D2:D7005, "="&TODAY(), Inventory!J2:J7005, "Closed") -> 0 | C27: =COUNTIFS(Inventory!D2:D7005, ">="&DATE(YEAR(TODAY()), MONTH(TODAY()), 1), Inventory!D2:D7005, "<="&EOMONTH(TODAY(), 0), Inventory!J2:J7005, "Closed") -> 3 | D27: =COUNTIFS(Inventory!D2:D7005, ">="&TODAY()-WEEKDAY(TODAY(), 2)-7, Inventory!D2:D7005, "<="&TODAY()-WEEKDAY(TODAY(), 2)-1, Inventory!J2:J7005, "Closed") -> 10 | E27: =COUNTIFS(Inventory!D2:D7005, "="&TODAY()-1, Inventory!J2:J7005, "Closed") -> 0 | H27: King | I27: =COUNTIF(Inventory!B:B,H27) -> 173 | J27: =COUNTIFS(Inventory!B:B,H27,Inventory!J:J,"Closed") -> 147 | K27: =(I27-J27) -> 26 | L27: =SUMIF(Inventory!B:B,H27,Inventory!F:F) -> 2262.62 | M27: =SUMIF(Inventory!B:B,H27,Inventory!E:E) -> 1895.65 | N27: =SUMIF(Inventory!B:B,H27,Inventory!G:G) -> 366.97 | O27: =(N27/L27) -> 0.16218808 | Q27: =IFERROR(__xludf.DUMMYFUNCTION("""COMPUTED_VALUE"""),"Dead by Daylight") -> Dead by Daylight | R27: =IFERROR(__xludf.DUMMYFUNCTION("""COMPUTED_VALUE"""),6.75) -> 6.75 | S27: =IFERROR(__xludf.DUMMYFUNCTION("""COMPUTED_VALUE"""),"G2A") -> G2A | T27: =IFERROR(__xludf.DUMMYFUNCTION("""COMPUTED_VALUE"""),46201.0) -> 46201
H28: WinGame | I28: =COUNTIF(Inventory!B:B,H28) -> 117 | J28: =COUNTIFS(Inventory!B:B,H28,Inventory!J:J,"Closed") -> 116 | K28: =(I28-J28) -> 1 | L28: =SUMIF(Inventory!B:B,H28,Inventory!F:F) -> 1272.7 | M28: =SUMIF(Inventory!B:B,H28,Inventory!E:E) -> 1022.1 | N28: =SUMIF(Inventory!B:B,H28,Inventory!G:G) -> 250.6 | O28: =(N28/L28) -> 0.19690422 | Q28: =IFERROR(__xludf.DUMMYFUNCTION("""COMPUTED_VALUE"""),"Tempest Rising") -> Tempest Rising | R28: =IFERROR(__xludf.DUMMYFUNCTION("""COMPUTED_VALUE"""),6.16) -> 6.16 | S28: =IFERROR(__xludf.DUMMYFUNCTION("""COMPUTED_VALUE"""),"King") -> King | T28: =IFERROR(__xludf.DUMMYFUNCTION("""COMPUTED_VALUE"""),46200.0) -> 46200
A29: MRGN | B29: =IFERROR((B24/B18), 0) -> 0 | C29: =C24/C18 -> 0.37228877 | D29: =(D24/D18) -> 0.30832187 | E29: =(E24/E18) -> #DIV/0! | H29: K4G | I29: =COUNTIF(Inventory!B:B,H29) -> 174 | J29: =COUNTIFS(Inventory!B:B,H29,Inventory!J:J,"Closed") -> 152 | K29: =(I29-J29) -> 22 | L29: =SUMIF(Inventory!B:B,H29,Inventory!F:F) -> 2852.57 | M29: =SUMIF(Inventory!B:B,H29,Inventory!E:E) -> 2553.8 | N29: =SUMIF(Inventory!B:B,H29,Inventory!G:G) -> 298.77 | O29: =(N29/L29) -> 0.10473713 | Q29: =IFERROR(__xludf.DUMMYFUNCTION("""COMPUTED_VALUE"""),"Black Myth: Wukong") -> Black Myth: Wukong | R29: =IFERROR(__xludf.DUMMYFUNCTION("""COMPUTED_VALUE"""),1.8799999999999955) -> 1.88 | S29: =IFERROR(__xludf.DUMMYFUNCTION("""COMPUTED_VALUE"""),"CDKeys") -> CDKeys | T29: =IFERROR(__xludf.DUMMYFUNCTION("""COMPUTED_VALUE"""),46200.0) -> 46200
H30: InstGam | I30: =COUNTIF(Inventory!B:B,H30) -> 54 | J30: =COUNTIFS(Inventory!B:B,H30,Inventory!J:J,"Closed") -> 53 | K30: =(I30-J30) -> 1 | L30: =SUMIF(Inventory!B:B,H30,Inventory!F:F) -> 777.19 | M30: =SUMIF(Inventory!B:B,H30,Inventory!E:E) -> 598.69 | N30: =SUMIF(Inventory!B:B,H30,Inventory!G:G) -> 178.5 | O30: =(N30/L30) -> 0.22967357 | Q30: =IFERROR(__xludf.DUMMYFUNCTION("""COMPUTED_VALUE"""),"Tempest Rising") -> Tempest Rising | R30: =IFERROR(__xludf.DUMMYFUNCTION("""COMPUTED_VALUE"""),6.16) -> 6.16 | S30: =IFERROR(__xludf.DUMMYFUNCTION("""COMPUTED_VALUE"""),"King") -> King | T30: =IFERROR(__xludf.DUMMYFUNCTION("""COMPUTED_VALUE"""),46199.0) -> 46199
H31: HRK | I31: =COUNTIF(Inventory!B:B,H31) -> 5 | J31: =COUNTIFS(Inventory!B:B,H31,Inventory!J:J,"Closed") -> 4 | K31: =(I31-J31) -> 1 | L31: =SUMIF(Inventory!B:B,H31,Inventory!F:F) -> 69.3 | M31: =SUMIF(Inventory!B:B,H31,Inventory!E:E) -> 79.36 | N31: =SUMIF(Inventory!B:B,H31,Inventory!G:G) -> -10.06 | O31: =(N31/L31) -> -0.14516595 | Q31: =IFERROR(__xludf.DUMMYFUNCTION("""COMPUTED_VALUE"""),"Fallout 4 VR") -> Fallout 4 VR | R31: =IFERROR(__xludf.DUMMYFUNCTION("""COMPUTED_VALUE"""),1.9299999999999997) -> 1.93 | S31: =IFERROR(__xludf.DUMMYFUNCTION("""COMPUTED_VALUE"""),"CDKeys") -> CDKeys | T31: =IFERROR(__xludf.DUMMYFUNCTION("""COMPUTED_VALUE"""),46199.0) -> 46199
B32: RVN | C32: SPNT | D32: PRFT | E32: SOLD | F32: % | H32: GamersGate | I32: =COUNTIF(Inventory!B:B,H32) -> 44 | J32: =COUNTIFS(Inventory!B:B,H32,Inventory!J:J,"Closed") -> 43 | K32: =(I32-J32) -> 1 | L32: =SUMIF(Inventory!B:B,H32,Inventory!F:F) -> 387.16 | M32: =SUMIF(Inventory!B:B,H32,Inventory!E:E) -> 306.85 | N32: =SUMIF(Inventory!B:B,H32,Inventory!G:G) -> 80.31 | O32: =(N32/L32) -> 0.20743362 | Q32: =IFERROR(__xludf.DUMMYFUNCTION("""COMPUTED_VALUE"""),"Dead by Daylight") -> Dead by Daylight | R32: =IFERROR(__xludf.DUMMYFUNCTION("""COMPUTED_VALUE"""),6.760000000000002) -> 6.76 | S32: =IFERROR(__xludf.DUMMYFUNCTION("""COMPUTED_VALUE"""),"G2A") -> G2A | T32: =IFERROR(__xludf.DUMMYFUNCTION("""COMPUTED_VALUE"""),46199.0) -> 46199
A33: Mon | B33: =IFERROR(__xludf.DUMMYFUNCTION("SUM(FILTER(Inventory!F2:F7005, TEXT(Inventory!L2:L7005, ""ddd"")=A33))"),18426.07799999999) -> 18426.078 | C33: =IFERROR(__xludf.DUMMYFUNCTION("SUM(FILTER(Inventory!E2:E7005, TEXT(Inventory!L2:L7005, ""ddd"")=A33))"),14530.129999999976) -> 14530.13 | D33: =IFERROR(__xludf.DUMMYFUNCTION("SUM(FILTER(Inventory!G2:G7005, TEXT(Inventory!L2:L7005, ""ddd"")=A33))"),3895.948000000003) -> 3895.948 | E33: =COUNTIFS(Inventory!L:L, A33, Inventory!J:J, "Closed") -> 1156 | F33: =(E33*F47)/E47 -> 0.13273625 | H33: GamersOutlet | I33: =COUNTIF(Inventory!B:B,H33) -> 27 | J33: =COUNTIFS(Inventory!B:B,H33,Inventory!J:J,"Closed") -> 27 | K33: =(I33-J33) -> 0 | L33: =SUMIF(Inventory!B:B,H33,Inventory!F:F) -> 764.71 | M33: =SUMIF(Inventory!B:B,H33,Inventory!E:E) -> 617.22 | N33: =SUMIF(Inventory!B:B,H33,Inventory!G:G) -> 147.49 | O33: =(N33/L33) -> 0.1928705 | Q33: =IFERROR(__xludf.DUMMYFUNCTION("""COMPUTED_VALUE"""),"The Last of Us Part 2 Remastered") -> The Last of Us Part 2 Remastered | R33: =IFERROR(__xludf.DUMMYFUNCTION("""COMPUTED_VALUE"""),2.789999999999999) -> 2.79 | S33: =IFERROR(__xludf.DUMMYFUNCTION("""COMPUTED_VALUE"""),"CDKeys") -> CDKeys | T33: =IFERROR(__xludf.DUMMYFUNCTION("""COMPUTED_VALUE"""),46198.0) -> 46198
H34: MMOGA | I34: =COUNTIF(Inventory!B:B,H34) -> 53 | J34: =COUNTIFS(Inventory!B:B,H34,Inventory!J:J,"Closed") -> 49 | K34: =(I34-J34) -> 4 | L34: =SUMIF(Inventory!B:B,H34,Inventory!F:F) -> 986.37 | M34: =SUMIF(Inventory!B:B,H34,Inventory!E:E) -> 644.65 | N34: =SUMIF(Inventory!B:B,H34,Inventory!G:G) -> 341.72 | O34: =(N34/L34) -> 0.346442 | Q34: =IFERROR(__xludf.DUMMYFUNCTION("""COMPUTED_VALUE"""),"Manor Lords") -> Manor Lords | R34: =IFERROR(__xludf.DUMMYFUNCTION("""COMPUTED_VALUE"""),7.259999999999998) -> 7.26 | S34: =IFERROR(__xludf.DUMMYFUNCTION("""COMPUTED_VALUE"""),"CDKeys") -> CDKeys | T34: =IFERROR(__xludf.DUMMYFUNCTION("""COMPUTED_VALUE"""),46198.0) -> 46198
A35: Tue | B35: =IFERROR(__xludf.DUMMYFUNCTION("SUM(FILTER(Inventory!F2:F7005, TEXT(Inventory!L2:L7005, ""ddd"")=A35))"),15561.453000000007) -> 15561.453 | C35: =IFERROR(__xludf.DUMMYFUNCTION("SUM(FILTER(Inventory!E2:E7005, TEXT(Inventory!L2:L7005, ""ddd"")=A35))"),12204.610000000015) -> 12204.61 | D35: =IFERROR(__xludf.DUMMYFUNCTION("SUM(FILTER(Inventory!G2:G7005, TEXT(Inventory!L2:L7005, ""ddd"")=A35))"),3356.843) -> 3356.843 | E35: =COUNTIFS(Inventory!L:L, A35, Inventory!J:J, "Closed") -> 1041 | F35: =(E35*F47)/E47 -> 0.11953152 | H35: YuPlay | I35: =COUNTIF(Inventory!B:B,H35) -> 130 | J35: =COUNTIFS(Inventory!B:B,H35,Inventory!J:J,"Closed") -> 127 | K35: =(I35-J35) -> 3 | L35: =SUMIF(Inventory!B:B,H35,Inventory!F:F) -> 1746.1 | M35: =SUMIF(Inventory!B:B,H35,Inventory!E:E) -> 1376.72 | N35: =SUMIF(Inventory!B:B,H35,Inventory!G:G) -> 369.38 | O35: =(N35/L35) -> 0.21154573 | Q35: =IFERROR(__xludf.DUMMYFUNCTION("""COMPUTED_VALUE"""),"Sid Meier's Civilization VII EU") -> Sid Meier's Civilization VII EU | R35: =IFERROR(__xludf.DUMMYFUNCTION("""COMPUTED_VALUE"""),2.41) -> 2.41 | S35: =IFERROR(__xludf.DUMMYFUNCTION("""COMPUTED_VALUE"""),"CDKeys") -> CDKeys | T35: =IFERROR(__xludf.DUMMYFUNCTION("""COMPUTED_VALUE"""),46198.0) -> 46198
H36: Total | I36: =SUM(I18:I34) -> 8828 | J36: =SUM(J18:J34) -> 8559 | K36: =(I36-J36) -> 269 | L36: =SUM(L18:L34) -> 129587.68 | M36: =SUM(M18:M34) -> 106676.65 | N36: =SUM(N18:N34) -> 22911.035 | O36: =(N36/L36) -> 0.17679948 | Q36: =IFERROR(__xludf.DUMMYFUNCTION("""COMPUTED_VALUE"""),"Sid Meier's Civilization VII EU") -> Sid Meier's Civilization VII EU | R36: =IFERROR(__xludf.DUMMYFUNCTION("""COMPUTED_VALUE"""),2.41) -> 2.41 | S36: =IFERROR(__xludf.DUMMYFUNCTION("""COMPUTED_VALUE"""),"CDKeys") -> CDKeys | T36: =IFERROR(__xludf.DUMMYFUNCTION("""COMPUTED_VALUE"""),46198.0) -> 46198
A37: Wed | B37: =IFERROR(__xludf.DUMMYFUNCTION("SUM(FILTER(Inventory!F2:F7005, TEXT(Inventory!L2:L7005, ""ddd"")=A37))"),15543.910000000014) -> 15543.91 | C37: =IFERROR(__xludf.DUMMYFUNCTION("SUM(FILTER(Inventory!E2:E7005, TEXT(Inventory!L2:L7005, ""ddd"")=A37))"),12169.109999999975) -> 12169.11 | D37: =IFERROR(__xludf.DUMMYFUNCTION("SUM(FILTER(Inventory!G2:G7005, TEXT(Inventory!L2:L7005, ""ddd"")=A37))"),3374.8000000000034) -> 3374.8 | E37: =COUNTIFS(Inventory!L:L, A37, Inventory!J:J, "Closed") -> 1065 | F37: =(E37*F47)/E47 -> 0.12228729 | Q37: =IFERROR(__xludf.DUMMYFUNCTION("""COMPUTED_VALUE"""),"Sid Meier's Civilization VII EU") -> Sid Meier's Civilization VII EU | R37: =IFERROR(__xludf.DUMMYFUNCTION("""COMPUTED_VALUE"""),2.3099999999999987) -> 2.31 | S37: =IFERROR(__xludf.DUMMYFUNCTION("""COMPUTED_VALUE"""),"CDKeys") -> CDKeys | T37: =IFERROR(__xludf.DUMMYFUNCTION("""COMPUTED_VALUE"""),46198.0) -> 46198
A39: Thu | B39: =IFERROR(__xludf.DUMMYFUNCTION("SUM(FILTER(Inventory!F2:F7005, TEXT(Inventory!L2:L7005, ""ddd"")=A39))"),16474.30999999999) -> 16474.31 | C39: =IFERROR(__xludf.DUMMYFUNCTION("SUM(FILTER(Inventory!E2:E7005, TEXT(Inventory!L2:L7005, ""ddd"")=A39))"),13076.360000000006) -> 13076.36 | D39: =IFERROR(__xludf.DUMMYFUNCTION("SUM(FILTER(Inventory!G2:G7005, TEXT(Inventory!L2:L7005, ""ddd"")=A39))"),3397.950000000002) -> 3397.95 | E39: =COUNTIFS(Inventory!L:L, A39, Inventory!J:J, "Closed") -> 1072 | F39: =(E39*F47)/E47 -> 0.12309106 | H39: KEYS
H40: ALL | I40: OPEN | J40: COST | K40: CLOSED
A41: Fri | B41: =IFERROR(__xludf.DUMMYFUNCTION("SUM(FILTER(Inventory!F2:F7005, TEXT(Inventory!L2:L7005, ""ddd"")=A41))"),18772.299999999985) -> 18772.3 | C41: =IFERROR(__xludf.DUMMYFUNCTION("SUM(FILTER(Inventory!E2:E7005, TEXT(Inventory!L2:L7005, ""ddd"")=A41))"),14913.389999999976) -> 14913.39 | D41: =IFERROR(__xludf.DUMMYFUNCTION("SUM(FILTER(Inventory!G2:G7005, TEXT(Inventory!L2:L7005, ""ddd"")=A41))"),3862.299999999993) -> 3862.3 | E41: =COUNTIFS(Inventory!L:L, A41, Inventory!J:J, "Closed") -> 1240 | F41: =(E41*F47)/E47 -> 0.14238144 | I41: =COUNTIF(Inventory!J:J,I40) -> 263 | J41: =SUMIF(Inventory!J:J,I40,Inventory!E:E) -> 4305.18 | K41: =COUNTIF(Inventory!J:J,K40) -> 8709
A43: Sat | B43: =IFERROR(__xludf.DUMMYFUNCTION("SUM(FILTER(Inventory!F2:F7005, TEXT(Inventory!L2:L7005, ""ddd"")=A43))"),23987.738000000023) -> 23987.738 | C43: =IFERROR(__xludf.DUMMYFUNCTION("SUM(FILTER(Inventory!E2:E7005, TEXT(Inventory!L2:L7005, ""ddd"")=A43))"),19040.433730158766) -> 19040.434 | D43: =IFERROR(__xludf.DUMMYFUNCTION("SUM(FILTER(Inventory!G2:G7005, TEXT(Inventory!L2:L7005, ""ddd"")=A43))"),4947.304269841263) -> 4947.3043 | E43: =COUNTIFS(Inventory!L:L, A43, Inventory!J:J, "Closed") -> 1559 | F43: =(E43*F47)/E47 -> 0.17901022 | H43: 2022 | I43: =COUNTIFS(Inventory!J:J, "Open",Inventory!C:C, ">="&DATE(2022,1,1), Inventory!C:C, "<="&DATE(2022,12,31)) -> 11 | J43: =SUMIFS(Inventory!E:E, Inventory!J:J, "Open", Inventory!C:C, ">="&DATE(2022,1,1), Inventory!C:C, "<="&DATE(2022,12,31)) -> 185.92
A45: Sun | B45: =IFERROR(__xludf.DUMMYFUNCTION("SUM(FILTER(Inventory!F2:F7005, TEXT(Inventory!L2:L7005, ""ddd"")=A45))"),23410.980000000036) -> 23410.98 | C45: =IFERROR(__xludf.DUMMYFUNCTION("SUM(FILTER(Inventory!E2:E7005, TEXT(Inventory!L2:L7005, ""ddd"")=A45))"),18485.99214285714) -> 18485.992 | D45: =IFERROR(__xludf.DUMMYFUNCTION("SUM(FILTER(Inventory!G2:G7005, TEXT(Inventory!L2:L7005, ""ddd"")=A45))"),4928.377857142853) -> 4928.3779 | E45: =COUNTIFS(Inventory!L:L, A45, Inventory!J:J, "Closed") -> 1576 | F45: =(E45*F47)/E47 -> 0.18096222 | H45: 2023 | I45: =COUNTIFS(Inventory!J:J, "Open",Inventory!C:C, ">="&DATE(2023,1,1), Inventory!C:C, "<="&DATE(2023,12,31)) -> 73 | J45: =SUMIFS(Inventory!E:E, Inventory!J:J, "Open", Inventory!C:C, ">="&DATE(2023,1,1), Inventory!C:C, "<="&DATE(2023,12,31)) -> 1166.7
A47: TTL | B47: =sum(B33:B46) -> 132176.77 | C47: =sum(C33:C46) -> 104420.03 | D47: =sum(D33:D46) -> 27763.523 | E47: =sum(E33:E46) -> 8709 | F47: 1 | H47: 2024 | I47: =COUNTIFS(Inventory!J:J, "Open",Inventory!C:C, ">="&DATE(2024,1,1), Inventory!C:C, "<="&DATE(2024,12,31)) -> 40 | J47: =SUMIFS(Inventory!E:E, Inventory!J:J, "Open", Inventory!C:C, ">="&DATE(2024,1,1), Inventory!C:C, "<="&DATE(2024,12,31)) -> 708.31
H49: 2025 | I49: =COUNTIFS(Inventory!J:J, "Open",Inventory!C:C, ">="&DATE(2025,1,1), Inventory!C:C, "<="&DATE(2025,12,31)) -> 38 | J49: =SUMIFS(Inventory!E:E, Inventory!J:J, "Open", Inventory!C:C, ">="&DATE(2025,1,1), Inventory!C:C, "<="&DATE(2025,12,31)) -> 666.79
B50: Profit | C50: Revenue | D50: Margin
A51: {=SEQUENCE(DAY(EOMONTH(TODAY(), 0)), 1, DATE(YEAR(TODAY()), MONTH(TODAY()), 1))} -> 46204 | B51: =IF(AND(A51<=EOMONTH(TODAY(),0), A51<=TODAY()), IF(SUMIFS(Inventory!G:G, Inventory!D:D, A51, Inventory!J:J, "closed")=0, "", SUMIFS(Inventory!G:G, Inventory!D:D, A51, Inventory!J:J, "closed")), "") -> 5.06 | C51: =IF(AND(A51<=EOMONTH(TODAY(),0), A51<=TODAY()), IF(SUMIFS(Inventory!F:F, Inventory!D:D, A51, Inventory!J:J, "closed")=0, "", SUMIFS(Inventory!F:F, Inventory!D:D, A51, Inventory!J:J, "closed")), "") -> 19.46 | H51: 2026 | I51: =COUNTIFS(Inventory!J:J, "Open",Inventory!C:C, ">="&DATE(2026,1,1), Inventory!C:C, "<="&DATE(2026,12,31)) -> 99 | J51: =SUMIFS(Inventory!E:E, Inventory!J:J, "Open", Inventory!C:C, ">="&DATE(2026,1,1), Inventory!C:C, "<="&DATE(2026,12,31)) -> 1563.16
A52: 46205 | B52: =IF(AND(A52<=EOMONTH(TODAY(),0), A52<=TODAY()), IF(SUMIFS(Inventory!G:G, Inventory!D:D, A52, Inventory!J:J, "closed")=0, "", SUMIFS(Inventory!G:G, Inventory!D:D, A52, Inventory!J:J, "closed")), "") -> 5.16 | C52: =IF(AND(A52<=EOMONTH(TODAY(),0), A52<=TODAY()), IF(SUMIFS(Inventory!F:F, Inventory!D:D, A52, Inventory!J:J, "closed")=0, "", SUMIFS(Inventory!F:F, Inventory!D:D, A52, Inventory!J:J, "closed")), "") -> 10.15
A53: 46206 | B53: =IF(AND(A53<=EOMONTH(TODAY(),0), A53<=TODAY()), IF(SUMIFS(Inventory!G:G, Inventory!D:D, A53, Inventory!J:J, "closed")=0, "", SUMIFS(Inventory!G:G, Inventory!D:D, A53, Inventory!J:J, "closed")), "") | C53: =IF(AND(A53<=EOMONTH(TODAY(),0), A53<=TODAY()), IF(SUMIFS(Inventory!F:F, Inventory!D:D, A53, Inventory!J:J, "closed")=0, "", SUMIFS(Inventory!F:F, Inventory!D:D, A53, Inventory!J:J, "closed")), "")
A54: 46207 | B54: =IF(AND(A54<=EOMONTH(TODAY(),0), A54<=TODAY()), IF(SUMIFS(Inventory!G:G, Inventory!D:D, A54, Inventory!J:J, "closed")=0, "", SUMIFS(Inventory!G:G, Inventory!D:D, A54, Inventory!J:J, "closed")), "") -> 1.28 | C54: =IF(AND(A54<=EOMONTH(TODAY(),0), A54<=TODAY()), IF(SUMIFS(Inventory!F:F, Inventory!D:D, A54, Inventory!J:J, "closed")=0, "", SUMIFS(Inventory!F:F, Inventory!D:D, A54, Inventory!J:J, "closed")), "") -> 1.28
A55: 46208 | B55: =IF(AND(A55<=EOMONTH(TODAY(),0), A55<=TODAY()), IF(SUMIFS(Inventory!G:G, Inventory!D:D, A55, Inventory!J:J, "closed")=0, "", SUMIFS(Inventory!G:G, Inventory!D:D, A55, Inventory!J:J, "closed")), "") | C55: =IF(AND(A55<=EOMONTH(TODAY(),0), A55<=TODAY()), IF(SUMIFS(Inventory!F:F, Inventory!D:D, A55, Inventory!J:J, "closed")=0, "", SUMIFS(Inventory!F:F, Inventory!D:D, A55, Inventory!J:J, "closed")), "")
A56: 46209 | B56: =IF(AND(A56<=EOMONTH(TODAY(),0), A56<=TODAY()), IF(SUMIFS(Inventory!G:G, Inventory!D:D, A56, Inventory!J:J, "closed")=0, "", SUMIFS(Inventory!G:G, Inventory!D:D, A56, Inventory!J:J, "closed")), "") | C56: =IF(AND(A56<=EOMONTH(TODAY(),0), A56<=TODAY()), IF(SUMIFS(Inventory!F:F, Inventory!D:D, A56, Inventory!J:J, "closed")=0, "", SUMIFS(Inventory!F:F, Inventory!D:D, A56, Inventory!J:J, "closed")), "")
A57: 46210 | B57: =IF(AND(A57<=EOMONTH(TODAY(),0), A57<=TODAY()), IF(SUMIFS(Inventory!G:G, Inventory!D:D, A57, Inventory!J:J, "closed")=0, "", SUMIFS(Inventory!G:G, Inventory!D:D, A57, Inventory!J:J, "closed")), "") | C57: =IF(AND(A57<=EOMONTH(TODAY(),0), A57<=TODAY()), IF(SUMIFS(Inventory!F:F, Inventory!D:D, A57, Inventory!J:J, "closed")=0, "", SUMIFS(Inventory!F:F, Inventory!D:D, A57, Inventory!J:J, "closed")), "")
A58: 46211 | B58: =IF(AND(A58<=EOMONTH(TODAY(),0), A58<=TODAY()), IF(SUMIFS(Inventory!G:G, Inventory!D:D, A58, Inventory!J:J, "closed")=0, "", SUMIFS(Inventory!G:G, Inventory!D:D, A58, Inventory!J:J, "closed")), "") | C58: =IF(AND(A58<=EOMONTH(TODAY(),0), A58<=TODAY()), IF(SUMIFS(Inventory!F:F, Inventory!D:D, A58, Inventory!J:J, "closed")=0, "", SUMIFS(Inventory!F:F, Inventory!D:D, A58, Inventory!J:J, "closed")), "")
A59: 46212 | B59: =IF(AND(A59<=EOMONTH(TODAY(),0), A59<=TODAY()), IF(SUMIFS(Inventory!G:G, Inventory!D:D, A59, Inventory!J:J, "closed")=0, "", SUMIFS(Inventory!G:G, Inventory!D:D, A59, Inventory!J:J, "closed")), "") | C59: =IF(AND(A59<=EOMONTH(TODAY(),0), A59<=TODAY()), IF(SUMIFS(Inventory!F:F, Inventory!D:D, A59, Inventory!J:J, "closed")=0, "", SUMIFS(Inventory!F:F, Inventory!D:D, A59, Inventory!J:J, "closed")), "")
A60: 46213 | B60: =IF(AND(A60<=EOMONTH(TODAY(),0), A60<=TODAY()), IF(SUMIFS(Inventory!G:G, Inventory!D:D, A60, Inventory!J:J, "closed")=0, "", SUMIFS(Inventory!G:G, Inventory!D:D, A60, Inventory!J:J, "closed")), "") | C60: =IF(AND(A60<=EOMONTH(TODAY(),0), A60<=TODAY()), IF(SUMIFS(Inventory!F:F, Inventory!D:D, A60, Inventory!J:J, "closed")=0, "", SUMIFS(Inventory!F:F, Inventory!D:D, A60, Inventory!J:J, "closed")), "")
A61: 46214 | B61: =IF(AND(A61<=EOMONTH(TODAY(),0), A61<=TODAY()), IF(SUMIFS(Inventory!G:G, Inventory!D:D, A61, Inventory!J:J, "closed")=0, "", SUMIFS(Inventory!G:G, Inventory!D:D, A61, Inventory!J:J, "closed")), "") | C61: =IF(AND(A61<=EOMONTH(TODAY(),0), A61<=TODAY()), IF(SUMIFS(Inventory!F:F, Inventory!D:D, A61, Inventory!J:J, "closed")=0, "", SUMIFS(Inventory!F:F, Inventory!D:D, A61, Inventory!J:J, "closed")), "")
A62: 46215 | B62: =IF(AND(A62<=EOMONTH(TODAY(),0), A62<=TODAY()), IF(SUMIFS(Inventory!G:G, Inventory!D:D, A62, Inventory!J:J, "closed")=0, "", SUMIFS(Inventory!G:G, Inventory!D:D, A62, Inventory!J:J, "closed")), "") | C62: =IF(AND(A62<=EOMONTH(TODAY(),0), A62<=TODAY()), IF(SUMIFS(Inventory!F:F, Inventory!D:D, A62, Inventory!J:J, "closed")=0, "", SUMIFS(Inventory!F:F, Inventory!D:D, A62, Inventory!J:J, "closed")), "")
A63: 46216 | B63: =IF(AND(A63<=EOMONTH(TODAY(),0), A63<=TODAY()), IF(SUMIFS(Inventory!G:G, Inventory!D:D, A63, Inventory!J:J, "closed")=0, "", SUMIFS(Inventory!G:G, Inventory!D:D, A63, Inventory!J:J, "closed")), "") | C63: =IF(AND(A63<=EOMONTH(TODAY(),0), A63<=TODAY()), IF(SUMIFS(Inventory!F:F, Inventory!D:D, A63, Inventory!J:J, "closed")=0, "", SUMIFS(Inventory!F:F, Inventory!D:D, A63, Inventory!J:J, "closed")), "")
... A81: 46234 | B81: =IF(AND(A81<=EOMONTH(TODAY(),0), A81<=TODAY()), IF(SUMIFS(Inventory!G:G, Inventory!D:D, A81, Inventory!J:J, "closed")=0, "", SUMIFS(Inventory!G:G, Inventory!D:D, A81, Inventory!J:J, "closed")), "") | C81: =IF(AND(A81<=EOMONTH(TODAY(),0), A81<=TODAY()), IF(SUMIFS(Inventory!F:F, Inventory!D:D, A81, Inventory!J:J, "closed")=0, "", SUMIFS(Inventory!F:F, Inventory!D:D, A81, Inventory!J:J, "closed")), "")
B89: =IF(AND(A89<=EOMONTH(TODAY(),0), A89<=TODAY()), IF(SUMIFS(Inventory!G:G, Inventory!D:D, A89, Inventory!J:J, "closed")=0, "", SUMIFS(Inventory!G:G, Inventory!D:D, A89, Inventory!J:J, "closed")), "") | C89: =IF(AND(A89<=EOMONTH(TODAY(),0), A89<=TODAY()), IF(SUMIFS(Inventory!F:F, Inventory!D:D, A89, Inventory!J:J, "closed")=0, "", SUMIFS(Inventory!F:F, Inventory!D:D, A89, Inventory!J:J, "closed")), "")

Sheet Inventory
A1: Name | B1: Vendor | C1: Entry Date | D1: Closed Date | E1: Cost | F1: Sell | G1: Profit | H1: Margin | I1: Key | J1: Status | K1: Duration | L1: Day | M1: Publisher | N1: Img | O1: LP
A2: Bayonetta RoW | B2: Other | C2: 43949 | D2: 43953 | E2: 4.25 | F2: 5.55 | G2: =MINUS(F2,E2) -> 1.3 | H2: =IFERROR(G2/F2,"") -> 0.23423423 | I2: P3KXY-4C6G3-9B8A6 | J2: Closed | K2: =IFERROR(DATEDIF(C2,D2,"D"), "") -> 4 | L2: =IF(D2="","",TEXT(D2,"DDD")) -> Sat | M2: =IFERROR(VLOOKUP(A2, Entries!A:B,2,false),"") -> SEGA | N2: =IFERROR(VLOOKUP(A2, Entries!A:K,11,false),"") | O2: =IFERROR(VLOOKUP(A2, Entries!A:I,8,false),"") -> FALSE
A3: Bayonetta RoW | B3: Other | C3: 43949 | D3: 43960 | E3: 4.25 | F3: 5.05 | G3: =MINUS(F3,E3) -> 0.8 | H3: =IFERROR(G3/F3,"") -> 0.15841584 | I3: BRNIJ-ECE0I-HYGEM | J3: Closed | K3: =IFERROR(DATEDIF(C3,D3,"D"), "") -> 11 | L3: =IF(D3="","",TEXT(D3,"DDD")) -> Sat | M3: =IFERROR(VLOOKUP(A3, Entries!A:B,2,false),"") -> SEGA | N3: =IFERROR(VLOOKUP(A3, Entries!A:K,11,false),"") | O3: =IFERROR(VLOOKUP(A3, Entries!A:I,8,false),"") -> FALSE
A4: Bayonetta RoW | B4: Other | C4: 43949 | D4: 43962 | E4: 4.25 | F4: 5.72 | G4: =MINUS(F4,E4) -> 1.47 | H4: =IFERROR(G4/F4,"") -> 0.25699301 | I4: J2TZF-N4V43-LKJNN | J4: Closed | K4: =IFERROR(DATEDIF(C4,D4,"D"), "") -> 13 | L4: =IF(D4="","",TEXT(D4,"DDD")) -> Mon | M4: =IFERROR(VLOOKUP(A4, Entries!A:B,2,false),"") -> SEGA | N4: =IFERROR(VLOOKUP(A4, Entries!A:K,11,false),"") | O4: =IFERROR(VLOOKUP(A4, Entries!A:I,8,false),"") -> FALSE
A5: Bayonetta RoW | B5: Other | C5: 43949 | D5: 43967 | E5: 4.19 | F5: 5.93 | G5: =MINUS(F5,E5) -> 1.74 | H5: =IFERROR(G5/F5,"") -> 0.29342327 | I5: 9L354-YT0MY-GT40T | J5: Closed | K5: =IFERROR(DATEDIF(C5,D5,"D"), "") -> 18 | L5: =IF(D5="","",TEXT(D5,"DDD")) -> Sat | M5: =IFERROR(VLOOKUP(A5, Entries!A:B,2,false),"") -> SEGA | N5: =IFERROR(VLOOKUP(A5, Entries!A:K,11,false),"") | O5: =IFERROR(VLOOKUP(A5, Entries!A:I,8,false),"") -> FALSE
A6: LEGO: Marvel Super Heroes 2 (Deluxe Edition) | B6: Eneba | C6: 43949 | D6: 43952 | E6: 7.16 | F6: 8.34 | G6: =MINUS(F6,E6) -> 1.18 | H6: =IFERROR(G6/F6,"") -> 0.14148681 | I6: BA2EG-4JTEV-W8TN8 | J6: Closed | K6: =IFERROR(DATEDIF(C6,D6,"D"), "") -> 3 | L6: =IF(D6="","",TEXT(D6,"DDD")) -> Fri | M6: =IFERROR(VLOOKUP(A6, Entries!A:B,2,false),"") -> Warner Bros | N6: =IFERROR(VLOOKUP(A6, Entries!A:K,11,false),"") | O6: =IFERROR(VLOOKUP(A6, Entries!A:I,8,false),"") -> FALSE
A7: Shadow of the Tomb Raider Definitive Edition | B7: Fanatical | C7: 43949 | D7: 43949 | E7: 16.19 | F7: 18.3 | G7: =MINUS(F7,E7) -> 2.11 | H7: =IFERROR(G7/F7,"") -> 0.11530055 | I7: XHVTQ-45RXF-TQLF9 | J7: Closed | K7: =IFERROR(DATEDIF(C7,D7,"D"), "") -> 0 | L7: =IF(D7="","",TEXT(D7,"DDD")) -> Tue | M7: =IFERROR(VLOOKUP(A7, Entries!A:B,2,false),"") -> Square Enix | N7: =IFERROR(VLOOKUP(A7, Entries!A:K,11,false),"") | O7: =IFERROR(VLOOKUP(A7, Entries!A:I,8,false),"") -> TRUE
A8: Shadow of the Tomb Raider Definitive Edition | B8: Fanatical | C8: 43949 | D8: 43950 | E8: 16.19 | F8: 18.3 | G8: =MINUS(F8,E8) -> 2.11 | H8: =IFERROR(G8/F8,"") -> 0.11530055 | I8: J83FK-3N60R-DKDE4 | J8: Closed | K8: =IFERROR(DATEDIF(C8,D8,"D"), "") -> 1 | L8: =IF(D8="","",TEXT(D8,"DDD")) -> Wed | M8: =IFERROR(VLOOKUP(A8, Entries!A:B,2,false),"") -> Square Enix | N8: =IFERROR(VLOOKUP(A8, Entries!A:K,11,false),"") | O8: =IFERROR(VLOOKUP(A8, Entries!A:I,8,false),"") -> TRUE
A9: NBA 2K20 | B9: Gamivo | C9: 43950 | D9: 43982 | E9: 13.42 | F9: 14.71 | G9: =MINUS(F9,E9) -> 1.29 | H9: =IFERROR(G9/F9,"") -> 0.087695445 | I9: 36MW7-4HZQT-ZAM27 | J9: Closed | K9: =IFERROR(DATEDIF(C9,D9,"D"), "") -> 32 | L9: =IF(D9="","",TEXT(D9,"DDD")) -> Sun | M9: =IFERROR(VLOOKUP(A9, Entries!A:B,2,false),"") -> 2K | N9: =IFERROR(VLOOKUP(A9, Entries!A:K,11,false),"") | O9: =IFERROR(VLOOKUP(A9, Entries!A:I,8,false),"") -> FALSE
A10: NBA 2K20 | B10: Gamivo | C10: 43950 | D10: 43982 | E10: 13.41 | F10: 15.15 | G10: =MINUS(F10,E10) -> 1.74 | H10: =IFERROR(G10/F10,"") -> 0.11485149 | I10: 34MZM-H02ZH-2YV04 | J10: Closed | K10: =IFERROR(DATEDIF(C10,D10,"D"), "") -> 32 | L10: =IF(D10="","",TEXT(D10,"DDD")) -> Sun | M10: =IFERROR(VLOOKUP(A10, Entries!A:B,2,false),"") -> 2K | N10: =IFERROR(VLOOKUP(A10, Entries!A:K,11,false),"") | O10: =IFERROR(VLOOKUP(A10, Entries!A:I,8,false),"") -> FALSE
A11: NBA 2K20 | B11: Gamivo | C11: 43950 | D11: 43953 | E11: 13.5 | F11: 16.05 | G11: =MINUS(F11,E11) -> 2.55 | H11: =IFERROR(G11/F11,"") -> 0.1588785 | I11: F7NZG-FB4W5-ZV8P6 | J11: Closed | K11: =IFERROR(DATEDIF(C11,D11,"D"), "") -> 3 | L11: =IF(D11="","",TEXT(D11,"DDD")) -> Sat | M11: =IFERROR(VLOOKUP(A11, Entries!A:B,2,false),"") -> 2K | N11: =IFERROR(VLOOKUP(A11, Entries!A:K,11,false),"") | O11: =IFERROR(VLOOKUP(A11, Entries!A:I,8,false),"") -> FALSE
A12: NBA 2K20 | B12: Gamivo | C12: 43950 | D12: 43961 | E12: 13.5 | F12: 15.6 | G12: =MINUS(F12,E12) -> 2.1 | H12: =IFERROR(G12/F12,"") -> 0.13461538 | I12: CMTB2-R49K2-FZBZD | J12: Closed | K12: =IFERROR(DATEDIF(C12,D12,"D"), "") -> 11 | L12: =IF(D12="","",TEXT(D12,"DDD")) -> Sun | M12: =IFERROR(VLOOKUP(A12, Entries!A:B,2,false),"") -> 2K | N12: =IFERROR(VLOOKUP(A12, Entries!A:K,11,false),"") | O12: =IFERROR(VLOOKUP(A12, Entries!A:I,8,false),"") -> FALSE
A13: NBA 2K20 | B13: Gamivo | C13: 43950 | D13: 43982 | E13: 13.6 | F13: 15.15 | G13: =MINUS(F13,E13) -> 1.55 | H13: =IFERROR(G13/F13,"") -> 0.10231023 | I13: C7YC5-8NIY6-J08LW | J13: Closed | K13: =IFERROR(DATEDIF(C13,D13,"D"), "") -> 32 | L13: =IF(D13="","",TEXT(D13,"DDD")) -> Sun | M13: =IFERROR(VLOOKUP(A13, Entries!A:B,2,false),"") -> 2K | N13: =IFERROR(VLOOKUP(A13, Entries!A:K,11,false),"") | O13: =IFERROR(VLOOKUP(A13, Entries!A:I,8,false),"") -> FALSE
... A792: Overload | B792: Gamivo | C792: 44322 | D792: 44375 | E792: 0.35 | F792: 0.42 | G792: =MINUS(F792,E792) -> 0.07 | H792: =IFERROR(G792/F792,"") -> 0.16666667 | I792: 3XEXV-TEABP-K7NYL | J792: Closed | K792: =IFERROR(DATEDIF(C792,D792,"D"), "") -> 53 | L792: =IF(D792="","",TEXT(D792,"DDD")) -> Mon | M792: =IFERROR(VLOOKUP(A792, Entries!A:B,2,false),"") -> Revival Productions | N792: =IFERROR(VLOOKUP(A792, Entries!A:K,11,false),"") | O792: =IFERROR(VLOOKUP(A792, Entries!A:I,8,false),"") -> FALSE
A793: Overload | B793: Gamivo | C793: 44322 | E793: 0.35 | G793: =MINUS(F793,E793) -> -0.35 | H793: =IFERROR(G793/F793,"") | J793: Rejected | K793: =IFERROR(DATEDIF(C793,D793,"D"), "") | L793: =IF(D793="","",TEXT(D793,"DDDD")) | M793: =IFERROR(VLOOKUP(A793, Unique!A:E,5,false),"")
A794: Shadow of the Tomb Raider Definitive Edition | B794: Fanatical | C794: 44323 | D794: 44324 | E794: 11.38 | F794: 13.92 | G794: =MINUS(F794,E794) -> 2.54 | H794: =IFERROR(G794/F794,"") -> 0.18247126 | I794: W2RBY-R8J86-ZCZWT | J794: Closed | K794: =IFERROR(DATEDIF(C794,D794,"D"), "") -> 1 | L794: =IF(D794="","",TEXT(D794,"DDD")) -> Sat | M794: =IFERROR(VLOOKUP(A794, Entries!A:B,2,false),"") -> Square Enix | N794: =IFERROR(VLOOKUP(A794, Entries!A:K,11,false),"") | O794: =IFERROR(VLOOKUP(A794, Entries!A:I,8,false),"") -> TRUE
A795: Shadow of the Tomb Raider Definitive Edition | B795: Fanatical | C795: 44323 | D795: 44326 | E795: 11.38 | F795: 13.93 | G795: =MINUS(F795,E795) -> 2.55 | H795: =IFERROR(G795/F795,"") -> 0.18305815 | I795: E6T4B-GXFGX-7PEPZ | J795: Closed | K795: =IFERROR(DATEDIF(C795,D795,"D"), "") -> 3 | L795: =IF(D795="","",TEXT(D795,"DDD")) -> Mon | M795: =IFERROR(VLOOKUP(A795, Entries!A:B,2,false),"") -> Square Enix | N795: =IFERROR(VLOOKUP(A795, Entries!A:K,11,false),"") | O795: =IFERROR(VLOOKUP(A795, Entries!A:I,8,false),"") -> TRUE
A796: Transport Fever 2 | B796: GamesPlanet | C796: 44324 | D796: 44324 | E796: 18.24 | F796: 23.01 | G796: =MINUS(F796,E796) -> 4.77 | H796: =IFERROR(G796/F796,"") -> 0.20730117 | I796: HWGLI-N6YI5-N0L50 | J796: Closed | K796: =IFERROR(DATEDIF(C796,D796,"D"), "") -> 0 | L796: =IF(D796="","",TEXT(D796,"DDD")) -> Sat | M796: =IFERROR(VLOOKUP(A796, Entries!A:B,2,false),"") -> Good Shepherd Entertainment | N796: =IFERROR(VLOOKUP(A796, Entries!A:K,11,false),"") | O796: =IFERROR(VLOOKUP(A796, Entries!A:I,8,false),"") -> FALSE
A797: Transport Fever 2 | B797: GamesPlanet | C797: 44324 | D797: 44327 | E797: 18.24 | F797: 22.24 | G797: =MINUS(F797,E797) -> 4 | H797: =IFERROR(G797/F797,"") -> 0.17985612 | I797: 8PJMA-QAXFC-60EC3 | J797: Closed | K797: =IFERROR(DATEDIF(C797,D797,"D"), "") -> 3 | L797: =IF(D797="","",TEXT(D797,"DDD")) -> Tue | M797: =IFERROR(VLOOKUP(A797, Entries!A:B,2,false),"") -> Good Shepherd Entertainment | N797: =IFERROR(VLOOKUP(A797, Entries!A:K,11,false),"") | O797: =IFERROR(VLOOKUP(A797, Entries!A:I,8,false),"") -> FALSE
A798: Shadow of the Tomb Raider Definitive Edition | B798: Fanatical | C798: 44324 | D798: 44329 | E798: 11.32 | F798: 15.85 | G798: =MINUS(F798,E798) -> 4.53 | H798: =IFERROR(G798/F798,"") -> 0.28580442 | I798: GN46P-MKI5L-CFQ37 | J798: Closed | K798: =IFERROR(DATEDIF(C798,D798,"D"), "") -> 5 | L798: =IF(D798="","",TEXT(D798,"DDD")) -> Thu | M798: =IFERROR(VLOOKUP(A798, Entries!A:B,2,false),"") -> Square Enix | N798: =IFERROR(VLOOKUP(A798, Entries!A:K,11,false),"") | O798: =IFERROR(VLOOKUP(A798, Entries!A:I,8,false),"") -> TRUE
A799: Praetorians HD Remaster | B799: Fanatical | C799: 44324 | D799: 44326 | E799: 2.88 | F799: 3.76 | G799: =MINUS(F799,E799) -> 0.88 | H799: =IFERROR(G799/F799,"") -> 0.23404255 | I799: DHJ8H-FGEWX-6XW9V | J799: Closed | K799: =IFERROR(DATEDIF(C799,D799,"D"), "") -> 2 | L799: =IF(D799="","",TEXT(D799,"DDD")) -> Mon | M799: =IFERROR(VLOOKUP(A799, Entries!A:B,2,false),"") -> Kalypso Media | N799: =IFERROR(VLOOKUP(A799, Entries!A:K,11,false),"") | O799: =IFERROR(VLOOKUP(A799, Entries!A:I,8,false),"") -> FALSE
A800: DiRT Rally 2.0 Game of the Year Edition | B800: Fanatical | C800: 44324 | D800: 44324 | E800: 2.88 | F800: 4.28 | G800: =MINUS(F800,E800) -> 1.4 | H800: =IFERROR(G800/F800,"") -> 0.3271028 | I800: Img | J800: Closed | K800: =IFERROR(DATEDIF(C800,D800,"D"), "") -> 0 | L800: =IF(D800="","",TEXT(D800,"DDD")) -> Sat | M800: =IFERROR(VLOOKUP(A800, Entries!A:B,2,false),"") -> Codemasters | N800: =IFERROR(VLOOKUP(A800, Entries!A:K,11,false),"") | O800: =IFERROR(VLOOKUP(A800, Entries!A:I,8,false),"") -> FALSE
A801: Verdun | B801: Fanatical | C801: 44324 | D801: 44326 | E801: 2.87 | F801: 3.72 | G801: =MINUS(F801,E801) -> 0.85 | H801: =IFERROR(G801/F801,"") -> 0.22849462 | I801: EQLFV-HDL8Z-N4QLR | J801: Closed | K801: =IFERROR(DATEDIF(C801,D801,"D"), "") -> 2 | L801: =IF(D801="","",TEXT(D801,"DDD")) -> Mon | M801: =IFERROR(VLOOKUP(A801, Entries!A:B,2,false),"") -> M2H | N801: =IFERROR(VLOOKUP(A801, Entries!A:K,11,false),"") | O801: =IFERROR(VLOOKUP(A801, Entries!A:I,8,false),"") -> TRUE
A802: NieR: Automata Game of the YoRHa Edition | B802: GreenMan | C802: 44324 | D802: 44325 | E802: 17.29 | F802: 24.04 | G802: =MINUS(F802,E802) -> 6.75 | H802: =IFERROR(G802/F802,"") -> 0.28078203 | I802: RX70B-9EJ37-MM6YQ | J802: Closed | K802: =IFERROR(DATEDIF(C802,D802,"D"), "") -> 1 | L802: =IF(D802="","",TEXT(D802,"DDD")) -> Sun | M802: =IFERROR(VLOOKUP(A802, Entries!A:B,2,false),"") -> Square Enix | N802: =IFERROR(VLOOKUP(A802, Entries!A:K,11,false),"") | O802: =IFERROR(VLOOKUP(A802, Entries!A:I,8,false),"") -> TRUE
A803: NieR: Automata - 3C3C1D119440927 DLC | B803: GreenMan | C803: 44324 | D803: 44353 | E803: 3.54 | F803: 4.49 | G803: =MINUS(F803,E803) -> 0.95 | H803: =IFERROR(G803/F803,"") -> 0.21158129 | I803: JWE9D-VZJT9-D7D2A | J803: Closed | K803: =IFERROR(DATEDIF(C803,D803,"D"), "") -> 29 | L803: =IF(D803="","",TEXT(D803,"DDD")) -> Sun | M803: =IFERROR(VLOOKUP(A803, Entries!A:B,2,false),"") -> Square Enix | N803: =IFERROR(VLOOKUP(A803, Entries!A:K,11,false),"") | O803: =IFERROR(VLOOKUP(A803, Entries!A:I,8,false),"") -> FALSE
A804: Resident Evil 7: Biohazard EMEA | B804: Fanatical | C804: 44326 | D804: 44326 | E804: 7.38 | F804: 12.36 | G804: =MINUS(F804,E804) -> 4.98 | H804: =IFERROR(G804/F804,"") -> 0.40291262 | I804: BV8MB-45VMW-4K25J | J804: Closed | K804: =IFERROR(DATEDIF(C804,D804,"D"), "") -> 0 | L804: =IF(D804="","",TEXT(D804,"DDD")) -> Mon | M804: =IFERROR(VLOOKUP(A804, Entries!A:B,2,false),"") -> CAPCOM | N804: =IFERROR(VLOOKUP(A804, Entries!A:K,11,false),"") | O804: =IFERROR(VLOOKUP(A804, Entries!A:I,8,false),"") -> FALSE
A805: Resident Evil 7: Biohazard EMEA | B805: Fanatical | C805: 44326 | D805: 44327 | E805: 7.38 | F805: 12.31 | G805: =MINUS(F805,E805) -> 4.93 | H805: =IFERROR(G805/F805,"") -> 0.40048741 | I805: AVY89-YBVBQ-LHV5B | J805: Closed | K805: =IFERROR(DATEDIF(C805,D805,"D"), "") -> 1 | L805: =IF(D805="","",TEXT(D805,"DDD")) -> Tue | M805: =IFERROR(VLOOKUP(A805, Entries!A:B,2,false),"") -> CAPCOM | N805: =IFERROR(VLOOKUP(A805, Entries!A:K,11,false),"") | O805: =IFERROR(VLOOKUP(A805, Entries!A:I,8,false),"") -> FALSE
... A820: Overload | B820: G2A | C820: 44328 | D820: 44498 | E820: 0.15 | F820: 0.41 | G820: =MINUS(F820,E820) -> 0.26 | H820: =IFERROR(G820/F820,"") -> 0.63414634 | I820: AYXLY-IZWM6-WXKWM | J820: Closed | K820: =IFERROR(DATEDIF(C820,D820,"D"), "") -> 170 | L820: =IF(D820="","",TEXT(D820,"DDD")) -> Fri | M820: =IFERROR(VLOOKUP(A820, Entries!A:B,2,false),"") -> Revival Productions | N820: =IFERROR(VLOOKUP(A820, Entries!A:K,11,false),"") | O820: =IFERROR(VLOOKUP(A820, Entries!A:I,8,false),"") -> FALSE
A821: Overload | B821: G2A | C821: 44328 | D821: 44501 | E821: 0.15 | F821: 0 | G821: =MINUS(F821,E821) -> -0.15 | H821: =IFERROR(G821/F821,"") | I821: BKX66-VRWT8-72KC | J821: Rejected | K821: =IFERROR(DATEDIF(C821,D821,"D"), "") -> 173 | L821: =IF(D821="","",TEXT(D821,"DDDD")) -> Monday | M821: =IFERROR(VLOOKUP(A821, Unique!A:E,5,false),"")
A822: The Sherlock Holmes Collection | B822: Fanatical | C822: 44328 | D822: 44329 | E822: 7.18 | F822: 11.47 | G822: =MINUS(F822,E822) -> 4.29 | H822: =IFERROR(G822/F822,"") -> 0.37401918 | I822: VQJDV-W6MXR-4JYLH | J822: Closed | K822: =IFERROR(DATEDIF(C822,D822,"D"), "") -> 1 | L822: =IF(D822="","",TEXT(D822,"DDD")) -> Thu | M822: =IFERROR(VLOOKUP(A822, Entries!A:B,2,false),"") -> Frogwares | N822: =IFERROR(VLOOKUP(A822, Entries!A:K,11,false),"") | O822: =IFERROR(VLOOKUP(A822, Entries!A:I,8,false),"") -> FALSE
A823: Garfield Kart Furious Racing | B823: Fanatical | C823: 44329 | D823: 44362 | E823: 2.61 | F823: 3.78 | G823: =MINUS(F823,E823) -> 1.17 | H823: =IFERROR(G823/F823,"") -> 0.30952381 | I823: img | J823: Closed | K823: =IFERROR(DATEDIF(C823,D823,"D"), "") -> 33 | L823: =IF(D823="","",TEXT(D823,"DDD")) -> Tue | M823: =IFERROR(VLOOKUP(A823, Entries!A:B,2,false),"") -> Microids | N823: =IFERROR(VLOOKUP(A823, Entries!A:K,11,false),"") | O823: =IFERROR(VLOOKUP(A823, Entries!A:I,8,false),"") -> FALSE
A824: Remothered: Tormented Fathers | B824: Fanatical | C824: 44329 | D824: 44352 | E824: 4.91 | F824: 7.64 | G824: =MINUS(F824,E824) -> 2.73 | H824: =IFERROR(G824/F824,"") -> 0.35732984 | I824: 53ZNW-Q5B2R-65JVY | J824: Closed | K824: =IFERROR(DATEDIF(C824,D824,"D"), "") -> 23 | L824: =IF(D824="","",TEXT(D824,"DDD")) -> Sat | M824: =IFERROR(VLOOKUP(A824, Entries!A:B,2,false),"") -> Modus Games | N824: =IFERROR(VLOOKUP(A824, Entries!A:K,11,false),"") | O824: =IFERROR(VLOOKUP(A824, Entries!A:I,8,false),"") -> FALSE
A825: The Sherlock Holmes Collection | B825: Fanatical | C825: 44329 | E825: 7.21 | G825: =MINUS(F825,E825) -> -7.21 | H825: =IFERROR(G825/F825,"") | I825: DEFEE-RXNK8-97JKI | J825: Open | K825: =IFERROR(DATEDIF(C825,D825,"D"), "") | L825: =IF(D825="","",TEXT(D825,"DDD")) | M825: =IFERROR(VLOOKUP(A825, Entries!A:B,2,false),"") -> Frogwares | O825: =IFERROR(VLOOKUP(A825, Entries!A:I,8,false),"") -> FALSE
A826: Praetorians HD Remaster | B826: Fanatical | C826: 44329 | D826: 44359 | E826: 2.88 | F826: 4.64 | G826: =MINUS(F826,E826) -> 1.76 | H826: =IFERROR(G826/F826,"") -> 0.37931034 | I826: IIFWA-9NAY4-L0C6X | J826: Closed | K826: =IFERROR(DATEDIF(C826,D826,"D"), "") -> 30 | L826: =IF(D826="","",TEXT(D826,"DDD")) -> Sat | M826: =IFERROR(VLOOKUP(A826, Entries!A:B,2,false),"") -> Kalypso Media | N826: =IFERROR(VLOOKUP(A826, Entries!A:K,11,false),"") | O826: =IFERROR(VLOOKUP(A826, Entries!A:I,8,false),"") -> FALSE
A827: Cultist Simulator | B827: Fanatical | C827: 44329 | D827: 44368 | E827: 2.87 | F827: 3.39 | G827: =MINUS(F827,E827) -> 0.52 | H827: =IFERROR(G827/F827,"") -> 0.15339233 | I827: RBDN5-6BK72-6XN44 | J827: Closed | K827: =IFERROR(DATEDIF(C827,D827,"D"), "") -> 39 | L827: =IF(D827="","",TEXT(D827,"DDD")) -> Mon | M827: =IFERROR(VLOOKUP(A827, Entries!A:B,2,false),"") -> Weather Factory | N827: =IFERROR(VLOOKUP(A827, Entries!A:K,11,false),"") | O827: =IFERROR(VLOOKUP(A827, Entries!A:I,8,false),"") -> FALSE
A828: DiRT Rally 2.0 Game of the Year Edition | B828: Fanatical | C828: 44329 | D828: 44361 | E828: 2.88 | F828: 4.47 | G828: =MINUS(F828,E828) -> 1.59 | H828: =IFERROR(G828/F828,"") -> 0.3557047 | I828: Img2h | J828: Closed | K828: =IFERROR(DATEDIF(C828,D828,"D"), "") -> 32 | L828: =IF(D828="","",TEXT(D828,"DDD")) -> Mon | M828: =IFERROR(VLOOKUP(A828, Entries!A:B,2,false),"") -> Codemasters | N828: =IFERROR(VLOOKUP(A828, Entries!A:K,11,false),"") | O828: =IFERROR(VLOOKUP(A828, Entries!A:I,8,false),"") -> FALSE
A829: Warpips | B829: G2A | C829: 44330 | D829: 44331 | E829: 6.71 | F829: 8.29 | G829: =MINUS(F829,E829) -> 1.58 | H829: =IFERROR(G829/F829,"") -> 0.19059107 | I829: BXRBG-73QYY-FB0EN | J829: Closed | K829: =IFERROR(DATEDIF(C829,D829,"D"), "") -> 1 | L829: =IF(D829="","",TEXT(D829,"DDD")) -> Sat | M829: =IFERROR(VLOOKUP(A829, Entries!A:B,2,false),"") -> Daedalic Entertainment | N829: =IFERROR(VLOOKUP(A829, Entries!A:K,11,false),"") | O829: =IFERROR(VLOOKUP(A829, Entries!A:I,8,false),"") -> FALSE
A830: Warpips | B830: GreenMan | C830: 44331 | D830: 44337 | E830: 6.62 | F830: 7.25 | G830: =MINUS(F830,E830) -> 0.63 | H830: =IFERROR(G830/F830,"") -> 0.086896552 | I830: HV0JA-027EZ-KJL2T | J830: Closed | K830: =IFERROR(DATEDIF(C830,D830,"D"), "") -> 6 | L830: =IF(D830="","",TEXT(D830,"DDD")) -> Fri | M830: =IFERROR(VLOOKUP(A830, Entries!A:B,2,false),"") -> Daedalic Entertainment | N830: =IFERROR(VLOOKUP(A830, Entries!A:K,11,false),"") | O830: =IFERROR(VLOOKUP(A830, Entries!A:I,8,false),"") -> FALSE
A831: Warpips | B831: G2A | C831: 44331 | D831: 44347 | E831: 6.67 | F831: 7.99 | G831: =MINUS(F831,E831) -> 1.32 | H831: =IFERROR(G831/F831,"") -> 0.16520651 | I831: 36W7G-L7NFG-8BTB8 | J831: Closed | K831: =IFERROR(DATEDIF(C831,D831,"D"), "") -> 16 | L831: =IF(D831="","",TEXT(D831,"DDD")) -> Mon | M831: =IFERROR(VLOOKUP(A831, Entries!A:B,2,false),"") -> Daedalic Entertainment | N831: =IFERROR(VLOOKUP(A831, Entries!A:K,11,false),"") | O831: =IFERROR(VLOOKUP(A831, Entries!A:I,8,false),"") -> FALSE
A832: Warpips | B832: G2A | C832: 44331 | D832: 44368 | E832: 6.67 | F832: 8.13 | G832: =MINUS(F832,E832) -> 1.46 | H832: =IFERROR(G832/F832,"") -> 0.1795818 | I832: QBGRF-5HZ6C-YDZ8X | J832: Closed | K832: =IFERROR(DATEDIF(C832,D832,"D"), "") -> 37 | L832: =IF(D832="","",TEXT(D832,"DDD")) -> Mon | M832: =IFERROR(VLOOKUP(A832, Entries!A:B,2,false),"") -> Daedalic Entertainment | N832: =IFERROR(VLOOKUP(A832, Entries!A:K,11,false),"") | O832: =IFERROR(VLOOKUP(A832, Entries!A:I,8,false),"") -> FALSE
A833: Warpips | B833: G2A | C833: 44331 | D833: 44843 | E833: 6.67 | F833: 0.98 | G833: =MINUS(F833,E833) -> -5.69 | H833: =IFERROR(G833/F833,"") -> -5.8061224 | I833: 4KZRY-BRJR8-ZW0AE | J833: Closed | K833: =IFERROR(DATEDIF(C833,D833,"D"), "") -> 512 | L833: =IF(D833="","",TEXT(D833,"DDD")) -> Sun | M833: =IFERROR(VLOOKUP(A833, Entries!A:B,2,false),"") -> Daedalic Entertainment | N833: =IFERROR(VLOOKUP(A833, Entries!A:K,11,false),"") | O833: =IFERROR(VLOOKUP(A833, Entries!A:I,8,false),"") -> FALSE
A834: Before We Leave | B834: Gamivo | C834: 44336 | D834: 44337 | E834: 9.53 | F834: 10.83 | G834: =MINUS(F834,E834) -> 1.3 | H834: =IFERROR(G834/F834,"") -> 0.12003693 | I834: B6ETQ-43QR7-YZGYK | J834: Closed | K834: =IFERROR(DATEDIF(C834,D834,"D"), "") -> 1 | L834: =IF(D834="","",TEXT(D834,"DDD")) -> Fri | M834: =IFERROR(VLOOKUP(A834, Entries!A:B,2,false),"") -> Team17 Digital | N834: =IFERROR(VLOOKUP(A834, Entries!A:K,11,false),"") | O834: =IFERROR(VLOOKUP(A834, Entries!A:I,8,false),"") -> FALSE
A835: Absolver | B835: Fanatical | C835: 44337 | D835: 44388 | E835: 6.1 | F835: 8.08 | G835: =MINUS(F835,E835) -> 1.98 | H835: =IFERROR(G835/F835,"") -> 0.24504951 | I835: WAFYH-2QCNZ-VBE6Q | J835: Closed | K835: =IFERROR(DATEDIF(C835,D835,"D"), "") -> 51 | L835: =IF(D835="","",TEXT(D835,"DDD")) -> Sun | M835: =IFERROR(VLOOKUP(A835, Entries!A:B,2,false),"") -> Devolver Digital | N835: =IFERROR(VLOOKUP(A835, Entries!A:K,11,false),"") | O835: =IFERROR(VLOOKUP(A835, Entries!A:I,8,false),"") -> FALSE
A836: Before We Leave | B836: Gamivo | C836: 44337 | D836: 44339 | E836: 9.16 | F836: 10.09 | G836: =MINUS(F836,E836) -> 0.93 | H836: =IFERROR(G836/F836,"") -> 0.092170466 | I836: HG6BR-8ABWM-XZDM2 | J836: Closed | K836: =IFERROR(DATEDIF(C836,D836,"D"), "") -> 2 | L836: =IF(D836="","",TEXT(D836,"DDD")) -> Sun | M836: =IFERROR(VLOOKUP(A836, Entries!A:B,2,false),"") -> Team17 Digital | N836: =IFERROR(VLOOKUP(A836, Entries!A:K,11,false),"") | O836: =IFERROR(VLOOKUP(A836, Entries!A:I,8,false),"") -> FALSE
A837: Before We Leave | B837: Gamivo | C837: 44337 | D837: 44353 | E837: 9.16 | F837: 10.05 | G837: =MINUS(F837,E837) -> 0.89 | H837: =IFERROR(G837/F837,"") -> 0.088557214 | I837: JWYBY-G4TVW-XXCAM | J837: Closed | K837: =IFERROR(DATEDIF(C837,D837,"D"), "") -> 16 | L837: =IF(D837="","",TEXT(D837,"DDD")) -> Sun | M837: =IFERROR(VLOOKUP(A837, Entries!A:B,2,false),"") -> Team17 Digital | N837: =IFERROR(VLOOKUP(A837, Entries!A:K,11,false),"") | O837: =IFERROR(VLOOKUP(A837, Entries!A:I,8,false),"") -> FALSE
... A850: Dead Cells | B850: GamesPlanet | C850: 44343 | D850: 44348 | E850: 11.96 | F850: 15.55 | G850: =MINUS(F850,E850) -> 3.59 | H850: =IFERROR(G850/F850,"") -> 0.23086817 | I850: XLYXG-MVGB3-9PJ38 | J850: Closed | K850: =IFERROR(DATEDIF(C850,D850,"D"), "") -> 5 | L850: =IF(D850="","",TEXT(D850,"DDD")) -> Tue | M850: =IFERROR(VLOOKUP(A850, Entries!A:B,2,false),"") -> Motion Twin | N850: =IFERROR(VLOOKUP(A850, Entries!A:K,11,false),"") | O850: =IFERROR(VLOOKUP(A850, Entries!A:I,8,false),"") -> FALSE
A851: The Sherlock Holmes Collection | B851: Fanatical | C851: 44344 | E851: 7.09 | G851: =MINUS(F851,E851) -> -7.09 | H851: =IFERROR(G851/F851,"") | I851: F7M9K-XNYCR-57HK0 | J851: Open | K851: =IFERROR(DATEDIF(C851,D851,"D"), "") | L851: =IF(D851="","",TEXT(D851,"DDD")) | M851: =IFERROR(VLOOKUP(A851, Entries!A:B,2,false),"") -> Frogwares | O851: =IFERROR(VLOOKUP(A851, Entries!A:I,8,false),"") -> FALSE | S851: =IF(AND(TODAY()-ROW(A27)+1 <= 30, J27="Closed"), TEXT(TODAY()-ROW(A27)+1, "dd-mm-yyyy"), "")
A852: F1 2020 Deluxe Schumacher Edition EU | B852: Fanatical | C852: 44344 | D852: 44348 | E852: 11.37 | F852: 14.69 | G852: =MINUS(F852,E852) -> 3.32 | H852: =IFERROR(G852/F852,"") -> 0.22600408 | I852: TN2NJ-7MWEY-4059M | J852: Closed | K852: =IFERROR(DATEDIF(C852,D852,"D"), "") -> 4 | L852: =IF(D852="","",TEXT(D852,"DDD")) -> Tue | M852: =IFERROR(VLOOKUP(A852, Entries!A:B,2,false),"") -> Codemasters | N852: =IFERROR(VLOOKUP(A852, Entries!A:K,11,false),"") | O852: =IFERROR(VLOOKUP(A852, Entries!A:I,8,false),"") -> FALSE
A853: Internet Cafe Simulator | B853: Fanatical | C853: 44346 | D853: 44366 | E853: 0.86 | F853: 0.9 | G853: =MINUS(F853,E853) -> 0.04 | H853: =IFERROR(G853/F853,"") -> 0.044444444 | I853: 4R3MT-FT4IT-KW28M | J853: Closed | K853: =IFERROR(DATEDIF(C853,D853,"D"), "") -> 20 | L853: =IF(D853="","",TEXT(D853,"DDD")) -> Sat | M853: =IFERROR(VLOOKUP(A853, Entries!A:B,2,false),"") -> Cheesecake Dev | N853: =IFERROR(VLOOKUP(A853, Entries!A:K,11,false),"") | O853: =IFERROR(VLOOKUP(A853, Entries!A:I,8,false),"") -> TRUE
A854: Among the Sleep - Enhanced Edition | B854: Fanatical | C854: 44346 | D854: 44348 | E854: 0.86 | F854: 1.45 | G854: =MINUS(F854,E854) -> 0.59 | H854: =IFERROR(G854/F854,"") -> 0.40689655 | I854: 0M8AL-M5LMA-5BHDM | J854: Closed | K854: =IFERROR(DATEDIF(C854,D854,"D"), "") -> 2 | L854: =IF(D854="","",TEXT(D854,"DDD")) -> Tue | M854: =IFERROR(VLOOKUP(A854, Entries!A:B,2,false),"") -> Krillbite Studio | N854: =IFERROR(VLOOKUP(A854, Entries!A:K,11,false),"") | O854: =IFERROR(VLOOKUP(A854, Entries!A:I,8,false),"") -> FALSE
A855: Dark Souls: Remastered | B855: GamesPlanet | C855: 44347 | D855: 44357 | E855: 14.59 | F855: 16.36 | G855: =MINUS(F855,E855) -> 1.77 | H855: =IFERROR(G855/F855,"") -> 0.10819071 | I855: N9F56-XJ8HF-XZQP8 | J855: Closed | K855: =IFERROR(DATEDIF(C855,D855,"D"), "") -> 10 | L855: =IF(D855="","",TEXT(D855,"DDD")) -> Thu | M855: =IFERROR(VLOOKUP(A855, Entries!A:B,2,false),"") -> BANDAI NAMCO | N855: =IFERROR(VLOOKUP(A855, Entries!A:K,11,false),"") | O855: =IFERROR(VLOOKUP(A855, Entries!A:I,8,false),"") -> FALSE
A856: Monster Energy Supercross - The Official Videogame 3 | B856: Eneba | C856: 44347 | D856: 44409 | E856: 6.35 | F856: 10.28 | G856: =MINUS(F856,E856) -> 3.93 | H856: =IFERROR(G856/F856,"") -> 0.38229572 | I856: P0K5W-TN4H8-Z308L | J856: Closed | K856: =IFERROR(DATEDIF(C856,D856,"D"), "") -> 62 | L856: =IF(D856="","",TEXT(D856,"DDD")) -> Sun | M856: =IFERROR(VLOOKUP(A856, Entries!A:B,2,false),"") -> Milestone | N856: =IFERROR(VLOOKUP(A856, Entries!A:K,11,false),"") | O856: =IFERROR(VLOOKUP(A856, Entries!A:I,8,false),"") -> FALSE
A857: Neverwinter Nights Bundle | B857: Fanatical | C857: 44350 | D857: 44366 | E857: 4.06 | F857: 7.36 | G857: =MINUS(F857,E857) -> 3.3 | H857: =IFERROR(G857/F857,"") -> 0.44836957 | I857: img3a | J857: Closed | K857: =IFERROR(DATEDIF(C857,D857,"D"), "") -> 16 | L857: =IF(D857="","",TEXT(D857,"DDD")) -> Sat | M857: =IFERROR(VLOOKUP(A857, Entries!A:B,2,false),"") -> Beamdog | N857: =IFERROR(VLOOKUP(A857, Entries!A:K,11,false),"") | O857: =IFERROR(VLOOKUP(A857, Entries!A:I,8,false),"") -> TRUE
A858: Neverwinter Nights Bundle | B858: Fanatical | C858: 44350 | D858: 44368 | E858: 4.06 | F858: 7.2 | G858: =MINUS(F858,E858) -> 3.14 | H858: =IFERROR(G858/F858,"") -> 0.43611111 | I858: img3b | J858: Closed | K858: =IFERROR(DATEDIF(C858,D858,"D"), "") -> 18 | L858: =IF(D858="","",TEXT(D858,"DDD")) -> Mon | M858: =IFERROR(VLOOKUP(A858, Entries!A:B,2,false),"") -> Beamdog | N858: =IFERROR(VLOOKUP(A858, Entries!A:K,11,false),"") | O858: =IFERROR(VLOOKUP(A858, Entries!A:I,8,false),"") -> TRUE
A859: Dead Rising 4 Frank's Big Package | B859: GamesPlanet | C859: 44351 | D859: 44369 | E859: 6.68 | F859: 7.99 | G859: =MINUS(F859,E859) -> 1.31 | H859: =IFERROR(G859/F859,"") -> 0.16395494 | I859: DQ2ZZ-ZM057-67GY3 | J859: Closed | K859: =IFERROR(DATEDIF(C859,D859,"D"), "") -> 18 | L859: =IF(D859="","",TEXT(D859,"DDD")) -> Tue | M859: =IFERROR(VLOOKUP(A859, Entries!A:B,2,false),"") -> CAPCOM | N859: =IFERROR(VLOOKUP(A859, Entries!A:K,11,false),"") | O859: =IFERROR(VLOOKUP(A859, Entries!A:I,8,false),"") -> FALSE
A860: Tomb Raider GOTY Edition | B860: Fanatical | C860: 44352 | D860: 44386 | E860: 2.86 | F860: 3.93 | G860: =MINUS(F860,E860) -> 1.07 | H860: =IFERROR(G860/F860,"") -> 0.27226463 | I860: M7B9W-LWVZK-LAC5H | J860: Closed | K860: =IFERROR(DATEDIF(C860,D860,"D"), "") -> 34 | L860: =IF(D860="","",TEXT(D860,"DDD")) -> Fri | M860: =IFERROR(VLOOKUP(A860, Entries!A:B,2,false),"") -> Square Enix | N860: =IFERROR(VLOOKUP(A860, Entries!A:K,11,false),"") | O860: =IFERROR(VLOOKUP(A860, Entries!A:I,8,false),"") -> FALSE
A861: Tesla Force | B861: Fanatical | C861: 44352 | D861: 44362 | E861: 2.87 | F861: 3.85 | G861: =MINUS(F861,E861) -> 0.98 | H861: =IFERROR(G861/F861,"") -> 0.25454545 | I861: ZVKD9-46WQG-4P3MA | J861: Closed | K861: =IFERROR(DATEDIF(C861,D861,"D"), "") -> 10 | L861: =IF(D861="","",TEXT(D861,"DDD")) -> Tue | M861: =IFERROR(VLOOKUP(A861, Entries!A:B,2,false),"") -> 10tons Ltd | N861: =IFERROR(VLOOKUP(A861, Entries!A:K,11,false),"") | O861: =IFERROR(VLOOKUP(A861, Entries!A:I,8,false),"") -> FALSE
A862: Commandos 2 HD Remaster | B862: Fanatical | C862: 44352 | D862: 44352 | E862: 2.87 | F862: 3.41 | G862: =MINUS(F862,E862) -> 0.54 | H862: =IFERROR(G862/F862,"") -> 0.15835777 | I862: IY5KA-F6Y8V-ZE344 | J862: Closed | K862: =IFERROR(DATEDIF(C862,D862,"D"), "") -> 0 | L862: =IF(D862="","",TEXT(D862,"DDD")) -> Sat | M862: =IFERROR(VLOOKUP(A862, Entries!A:B,2,false),"") -> Kalypso Media | N862: =IFERROR(VLOOKUP(A862, Entries!A:K,11,false),"") | O862: =IFERROR(VLOOKUP(A862, Entries!A:I,8,false),"") -> FALSE
A863: Shadow of the Tomb Raider Definitive Edition | B863: Fanatical | C863: 44361 | D863: 44361 | E863: 11.29 | F863: 17.84 | G863: =MINUS(F863,E863) -> 6.55 | H863: =IFERROR(G863/F863,"") -> 0.36715247 | I863: P2GDI-95A9C-2MBDD | J863: Closed | K863: =IFERROR(DATEDIF(C863,D863,"D"), "") -> 0 | L863: =IF(D863="","",TEXT(D863,"DDD")) -> Mon | M863: =IFERROR(VLOOKUP(A863, Entries!A:B,2,false),"") -> Square Enix | N863: =IFERROR(VLOOKUP(A863, Entries!A:K,11,false),"") | O863: =IFERROR(VLOOKUP(A863, Entries!A:I,8,false),"") -> TRUE
... A1212: Killer7 | B1212: Fanatical | C1212: 44510 | D1212: 44699 | E1212: 5.1 | F1212: 4.95 | G1212: =MINUS(F1212,E1212) -> -0.15 | H1212: =IFERROR(G1212/F1212,"") -> -0.03030303 | I1212: 24WTN-4KYM2-A00BI | J1212: Closed | K1212: =IFERROR(DATEDIF(C1212,D1212,"D"), "") -> 189 | L1212: =IF(D1212="","",TEXT(D1212,"DDD")) -> Wed | M1212: =IFERROR(VLOOKUP(A1212, Entries!A:B,2,false),"") -> NIS America | N1212: =IFERROR(VLOOKUP(A1212, Entries!A:K,11,false),"") | O1212: =IFERROR(VLOOKUP(A1212, Entries!A:I,8,false),"") -> FALSE
A1213: Yomawari: Midnight Shadows | B1213: Fanatical | C1213: 44510 | D1213: 44541 | E1213: 6.59 | F1213: 6.59 | G1213: =MINUS(F1213,E1213) -> 0 | H1213: 0.0869 | I1213: J3W9A-NY38R-22B3Y | J1213: Closed | K1213: =IFERROR(DATEDIF(C1213,D1213,"D"), "") -> 31 | L1213: =IF(D1213="","",TEXT(D1213,"DDD")) -> Sat | M1213: =IFERROR(VLOOKUP(A1213, Entries!A:B,2,false),"") -> NIS America | N1213: =IFERROR(VLOOKUP(A1213, Entries!A:K,11,false),"") | O1213: =IFERROR(VLOOKUP(A1213, Entries!A:I,8,false),"") -> FALSE
A1214: eFootball PES 2021 Season Update Standard Edition EU | B1214: Fanatical | C1214: 44510 | D1214: 44511 | E1214: 3.85 | F1214: 7.66 | G1214: =MINUS(F1214,E1214) -> 3.81 | H1214: =IFERROR(G1214/F1214,"") -> 0.49738903 | I1214: BYGZF-9CTAK-D004X | J1214: Closed | K1214: =IFERROR(DATEDIF(C1214,D1214,"D"), "") -> 1 | L1214: =IF(D1214="","",TEXT(D1214,"DDD")) -> Thu | M1214: =IFERROR(VLOOKUP(A1214, Entries!A:B,2,false),"") -> Konami | N1214: =IFERROR(VLOOKUP(A1214, Entries!A:K,11,false),"") | O1214: =IFERROR(VLOOKUP(A1214, Entries!A:I,8,false),"") -> FALSE
A1215: eFootball PES 2021 Season Update Standard Edition EU | B1215: Fanatical | C1215: 44511 | D1215: 44513 | E1215: 3.85 | F1215: 7.55 | G1215: =MINUS(F1215,E1215) -> 3.7 | H1215: =IFERROR(G1215/F1215,"") -> 0.49006623 | I1215: N6APF-WI0PL-8FLIV | J1215: Closed | K1215: =IFERROR(DATEDIF(C1215,D1215,"D"), "") -> 2 | L1215: =IF(D1215="","",TEXT(D1215,"DDD")) -> Sat | M1215: =IFERROR(VLOOKUP(A1215, Entries!A:B,2,false),"") -> Konami | N1215: =IFERROR(VLOOKUP(A1215, Entries!A:K,11,false),"") | O1215: =IFERROR(VLOOKUP(A1215, Entries!A:I,8,false),"") -> FALSE
A1216: Just Cause 3 XXL Edition Bundle | B1216: Fanatical | C1216: 44511 | D1216: 44513 | E1216: 2.73 | F1216: 3.83 | G1216: =MINUS(F1216,E1216) -> 1.1 | H1216: =IFERROR(G1216/F1216,"") -> 0.28720627 | I1216: BRE2M-NTAEQ-EJGWK | J1216: Closed | K1216: =IFERROR(DATEDIF(C1216,D1216,"D"), "") -> 2 | L1216: =IF(D1216="","",TEXT(D1216,"DDD")) -> Sat | M1216: =IFERROR(VLOOKUP(A1216, Entries!A:B,2,false),"") -> Square Enix | N1216: =IFERROR(VLOOKUP(A1216, Entries!A:K,11,false),"") | O1216: =IFERROR(VLOOKUP(A1216, Entries!A:I,8,false),"") -> TRUE
A1217: Tesla Force | B1217: Fanatical | C1217: 44511 | D1217: 44582 | E1217: 2.73 | F1217: 6.2 | G1217: =MINUS(F1217,E1217) -> 3.47 | H1217: =IFERROR(G1217/F1217,"") -> 0.55967742 | I1217: HLLMZ-2NPNX-6H2GW | J1217: Closed | K1217: =IFERROR(DATEDIF(C1217,D1217,"D"), "") -> 71 | L1217: =IF(D1217="","",TEXT(D1217,"DDD")) -> Fri | M1217: =IFERROR(VLOOKUP(A1217, Entries!A:B,2,false),"") -> 10tons Ltd | N1217: =IFERROR(VLOOKUP(A1217, Entries!A:K,11,false),"") | O1217: =IFERROR(VLOOKUP(A1217, Entries!A:I,8,false),"") -> FALSE
A1218: Wild Guns Reloaded | B1218: Fanatical | C1218: 44511 | D1218: 44512 | E1218: 2.73 | F1218: 3.22 | G1218: =MINUS(F1218,E1218) -> 0.49 | H1218: =IFERROR(G1218/F1218,"") -> 0.15217391 | I1218: 9YF7N-JB7VK-29397 | J1218: Closed | K1218: =IFERROR(DATEDIF(C1218,D1218,"D"), "") -> 1 | L1218: =IF(D1218="","",TEXT(D1218,"DDD")) -> Fri | M1218: =IFERROR(VLOOKUP(A1218, Entries!A:B,2,false),"") -> Natsume | N1218: =IFERROR(VLOOKUP(A1218, Entries!A:K,11,false),"") | O1218: =IFERROR(VLOOKUP(A1218, Entries!A:I,8,false),"") -> FALSE
A1219: Farming Simulator 19 | B1219: GamesPlanet | C1219: 44513 | D1219: 44513 | E1219: 6.36 | F1219: 7.5 | G1219: =MINUS(F1219,E1219) -> 1.14 | H1219: =IFERROR(G1219/F1219,"") -> 0.152 | I1219: AHNEK-N2465-3GZZ0 | J1219: Closed | K1219: =IFERROR(DATEDIF(C1219,D1219,"D"), "") -> 0 | L1219: =IF(D1219="","",TEXT(D1219,"DDD")) -> Sat | M1219: =IFERROR(VLOOKUP(A1219, Entries!A:B,2,false),"") -> Focus Home Interactive | N1219: =IFERROR(VLOOKUP(A1219, Entries!A:K,11,false),"") | O1219: =IFERROR(VLOOKUP(A1219, Entries!A:I,8,false),"") -> FALSE
A1220: Farming Simulator 19 Premium Edition | B1220: GamesPlanet | C1220: 44513 | D1220: 44643 | E1220: 16.38 | F1220: 16.75 | G1220: =MINUS(F1220,E1220) -> 0.37 | H1220: =IFERROR(G1220/F1220,"") -> 0.022089552 | I1220: GC8EJ-9NA49-FJHFK | J1220: Closed | K1220: =IFERROR(DATEDIF(C1220,D1220,"D"), "") -> 130 | L1220: =IF(D1220="","",TEXT(D1220,"DDD")) -> Wed | M1220: =IFERROR(VLOOKUP(A1220, Entries!A:B,2,false),"") -> Focus Home Interactive | N1220: =IFERROR(VLOOKUP(A1220, Entries!A:K,11,false),"") | O1220: =IFERROR(VLOOKUP(A1220, Entries!A:I,8,false),"") -> FALSE
A1221: Farming Simulator 19 | B1221: GamesPlanet | C1221: 44513 | D1221: 44513 | E1221: 6.37 | F1221: 7.5 | G1221: =MINUS(F1221,E1221) -> 1.13 | H1221: =IFERROR(G1221/F1221,"") -> 0.15066667 | I1221: Z53D6-J7Q7W-Q6JFQ | J1221: Closed | K1221: =IFERROR(DATEDIF(C1221,D1221,"D"), "") -> 0 | L1221: =IF(D1221="","",TEXT(D1221,"DDD")) -> Sat | M1221: =IFERROR(VLOOKUP(A1221, Entries!A:B,2,false),"") -> Focus Home Interactive | N1221: =IFERROR(VLOOKUP(A1221, Entries!A:K,11,false),"") | O1221: =IFERROR(VLOOKUP(A1221, Entries!A:I,8,false),"") -> FALSE
A1222: Farming Simulator 19 | B1222: GamesPlanet | C1222: 44513 | D1222: 44514 | E1222: 6.37 | F1222: 7.49 | G1222: =MINUS(F1222,E1222) -> 1.12 | H1222: =IFERROR(G1222/F1222,"") -> 0.14953271 | I1222: DR7Z5-09JCH-8DMCJ | J1222: Closed | K1222: =IFERROR(DATEDIF(C1222,D1222,"D"), "") -> 1 | L1222: =IF(D1222="","",TEXT(D1222,"DDD")) -> Sun | M1222: =IFERROR(VLOOKUP(A1222, Entries!A:B,2,false),"") -> Focus Home Interactive | N1222: =IFERROR(VLOOKUP(A1222, Entries!A:K,11,false),"") | O1222: =IFERROR(VLOOKUP(A1222, Entries!A:I,8,false),"") -> FALSE
A1223: eFootball PES 2021 Season Update Standard Edition EU | B1223: Fanatical | C1223: 44513 | D1223: 44515 | E1223: 3.18 | F1223: 7.5 | G1223: =MINUS(F1223,E1223) -> 4.32 | H1223: =IFERROR(G1223/F1223,"") -> 0.576 | I1223: 0LN7A-CIQNJ-AI8D6 | J1223: Closed | K1223: =IFERROR(DATEDIF(C1223,D1223,"D"), "") -> 2 | L1223: =IF(D1223="","",TEXT(D1223,"DDD")) -> Mon | M1223: =IFERROR(VLOOKUP(A1223, Entries!A:B,2,false),"") -> Konami | N1223: =IFERROR(VLOOKUP(A1223, Entries!A:K,11,false),"") | O1223: =IFERROR(VLOOKUP(A1223, Entries!A:I,8,false),"") -> FALSE
A1224: Iron Harvest | B1224: Fanatical | C1224: 44518 | D1224: 45520 | E1224: 11.86 | F1224: 1.89 | G1224: =MINUS(F1224,E1224) -> -9.97 | H1224: =IFERROR(G1224/F1224,"") -> -5.2751323 | I1224: IEK2J-799W5-RLAXK | J1224: Closed | K1224: =IFERROR(DATEDIF(C1224,D1224,"D"), "") -> 1002 | L1224: =IF(D1224="","",TEXT(D1224,"DDD")) -> Fri | M1224: =IFERROR(VLOOKUP(A1224, Entries!A:B,2,false),"") -> Prime Matter | N1224: =IFERROR(VLOOKUP(A1224, Entries!A:K,11,false),"") | O1224: =IFERROR(VLOOKUP(A1224, Entries!A:I,8,false),"") -> FALSE
A1225: The Forgotten City | B1225: Fanatical | C1225: 44518 | D1225: 44552 | E1225: 14.71 | F1225: 15.5 | G1225: =MINUS(F1225,E1225) -> 0.79 | H1225: =IFERROR(G1225/F1225,"") -> 0.050967742 | I1225: DPD5Y-DP4NN-NP6B0 | J1225: Closed | K1225: =IFERROR(DATEDIF(C1225,D1225,"D"), "") -> 34 | L1225: =IF(D1225="","",TEXT(D1225,"DDD")) -> Wed | M1225: =IFERROR(VLOOKUP(A1225, Entries!A:B,2,false),"") -> Dear Villagers | N1225: =IFERROR(VLOOKUP(A1225, Entries!A:K,11,false),"") | O1225: =IFERROR(VLOOKUP(A1225, Entries!A:I,8,false),"") -> FALSE
... A1377: Trash Sailors | B1377: G2A | C1377: 44574 | D1377: 44633 | E1377: 6.27 | F1377: 8.35 | G1377: =MINUS(F1377,E1377) -> 2.08 | H1377: =IFERROR(G1377/F1377,"") -> 0.2491018 | I1377: KR920-EAZDC-RW0QG | J1377: Closed | K1377: =IFERROR(DATEDIF(C1377,D1377,"D"), "") -> 59 | L1377: =IF(D1377="","",TEXT(D1377,"DDD")) -> Sun | M1377: =IFERROR(VLOOKUP(A1377, Entries!A:B,2,false),"") -> tinyBuild | N1377: =IFERROR(VLOOKUP(A1377, Entries!A:K,11,false),"") | O1377: =IFERROR(VLOOKUP(A1377, Entries!A:I,8,false),"") -> FALSE
A1378: ScourgeBringer | B1378: GamesPlanet | C1378: 44574 | E1378: 9.17 | G1378: =MINUS(F1378,E1378) -> -9.17 | H1378: =IFERROR(G1378/F1378,"") | I1378: KX8Q4-MBRBJ-M023P | J1378: Open | K1378: =IFERROR(DATEDIF(C1378,D1378,"D"), "") | L1378: =IF(D1378="","",TEXT(D1378,"DDD")) | M1378: =IFERROR(VLOOKUP(A1378, Entries!A:B,2,false),"") -> Dear Villagers | N1378: =IFERROR(VLOOKUP(A1378, Entries!A:K,11,false),"") | O1378: =IFERROR(VLOOKUP(A1378, Entries!A:I,8,false),"") -> FALSE | S1378: =IF(AND(TODAY()-ROW(A554)+1 <= 30, J554="Closed"), TEXT(TODAY()-ROW(A554)+1, "dd-mm-yyyy"), "")
A1379: Just Cause 3 XXL Edition Bundle | B1379: Fanatical | C1379: 44574 | D1379: 44576 | E1379: 2.86 | F1379: 3.48 | G1379: =MINUS(F1379,E1379) -> 0.62 | H1379: =IFERROR(G1379/F1379,"") -> 0.17816092 | I1379: DA7KQ-5Z5E9-QW0MY | J1379: Closed | K1379: =IFERROR(DATEDIF(C1379,D1379,"D"), "") -> 2 | L1379: =IF(D1379="","",TEXT(D1379,"DDD")) -> Sat | M1379: =IFERROR(VLOOKUP(A1379, Entries!A:B,2,false),"") -> Square Enix | N1379: =IFERROR(VLOOKUP(A1379, Entries!A:K,11,false),"") | O1379: =IFERROR(VLOOKUP(A1379, Entries!A:I,8,false),"") -> TRUE
A1380: Just Cause 3 XXL Edition Bundle | B1380: Fanatical | C1380: 44574 | D1380: 44576 | E1380: 2.86 | F1380: 3.48 | G1380: =MINUS(F1380,E1380) -> 0.62 | H1380: =IFERROR(G1380/F1380,"") -> 0.17816092 | I1380: 47WVP-A7LDX-TGWC4 | J1380: Closed | K1380: =IFERROR(DATEDIF(C1380,D1380,"D"), "") -> 2 | L1380: =IF(D1380="","",TEXT(D1380,"DDD")) -> Sat | M1380: =IFERROR(VLOOKUP(A1380, Entries!A:B,2,false),"") -> Square Enix | N1380: =IFERROR(VLOOKUP(A1380, Entries!A:K,11,false),"") | O1380: =IFERROR(VLOOKUP(A1380, Entries!A:I,8,false),"") -> TRUE
A1381: Saints Row IV: Game of the Century Edition | B1381: Fanatical | C1381: 44574 | D1381: 44577 | E1381: 2.74 | F1381: 3.76 | G1381: =MINUS(F1381,E1381) -> 1.02 | H1381: =IFERROR(G1381/F1381,"") -> 0.2712766 | I1381: EDEF7-J9MMW-CDBQ3 | J1381: Closed | K1381: =IFERROR(DATEDIF(C1381,D1381,"D"), "") -> 3 | L1381: =IF(D1381="","",TEXT(D1381,"DDD")) -> Sun | M1381: =IFERROR(VLOOKUP(A1381, Entries!A:B,2,false),"") -> Deep Silver | N1381: =IFERROR(VLOOKUP(A1381, Entries!A:K,11,false),"") | O1381: =IFERROR(VLOOKUP(A1381, Entries!A:I,8,false),"") -> TRUE
A1382: Saints Row IV: Game of the Century Edition | B1382: Fanatical | C1382: 44577 | D1382: 44586 | E1382: 2.73 | F1382: 3.63 | G1382: =MINUS(F1382,E1382) -> 0.9 | H1382: =IFERROR(G1382/F1382,"") -> 0.24793388 | I1382: 57E8X-64ZQZ-KNQ9P | J1382: Closed | K1382: =IFERROR(DATEDIF(C1382,D1382,"D"), "") -> 9 | L1382: =IF(D1382="","",TEXT(D1382,"DDD")) -> Tue | M1382: =IFERROR(VLOOKUP(A1382, Entries!A:B,2,false),"") -> Deep Silver | N1382: =IFERROR(VLOOKUP(A1382, Entries!A:K,11,false),"") | O1382: =IFERROR(VLOOKUP(A1382, Entries!A:I,8,false),"") -> TRUE
A1383: Redout Complete Pack | B1383: Fanatical | C1383: 44578 | D1383: 44601 | E1383: 3.76 | F1383: 5.63 | G1383: =MINUS(F1383,E1383) -> 1.87 | H1383: =IFERROR(G1383/F1383,"") -> 0.3321492 | I1383: Imga17a | J1383: Closed | K1383: =IFERROR(DATEDIF(C1383,D1383,"D"), "") -> 23 | L1383: =IF(D1383="","",TEXT(D1383,"DDD")) -> Wed | M1383: =IFERROR(VLOOKUP(A1383, Entries!A:B,2,false),"") -> 34BigThings | N1383: =IFERROR(VLOOKUP(A1383, Entries!A:K,11,false),"") | O1383: =IFERROR(VLOOKUP(A1383, Entries!A:I,8,false),"") -> FALSE
A1384: Clue/Cluedo: The Classic Mystery Game | B1384: Fanatical | C1384: 44579 | D1384: 44580 | E1384: 3.54 | F1384: 7.64 | G1384: =MINUS(F1384,E1384) -> 4.1 | H1384: =IFERROR(G1384/F1384,"") -> 0.53664921 | I1384: IYPRW-W33VZ-4F6TE | J1384: Closed | K1384: =IFERROR(DATEDIF(C1384,D1384,"D"), "") -> 1 | L1384: =IF(D1384="","",TEXT(D1384,"DDD")) -> Wed | M1384: =IFERROR(VLOOKUP(A1384, Entries!A:B,2,false),"") -> Marmalade Game Studio | N1384: =IFERROR(VLOOKUP(A1384, Entries!A:K,11,false),"") | O1384: =IFERROR(VLOOKUP(A1384, Entries!A:I,8,false),"") -> FALSE
A1385: Clue/Cluedo: The Classic Mystery Game | B1385: Fanatical | C1385: 44579 | D1385: 44600 | E1385: 3.54 | F1385: 4.23 | G1385: =MINUS(F1385,E1385) -> 0.69 | H1385: =IFERROR(G1385/F1385,"") -> 0.16312057 | I1385: ARMTW-K396D-5F8ZC | J1385: Closed | K1385: =IFERROR(DATEDIF(C1385,D1385,"D"), "") -> 21 | L1385: =IF(D1385="","",TEXT(D1385,"DDD")) -> Tue | M1385: =IFERROR(VLOOKUP(A1385, Entries!A:B,2,false),"") -> Marmalade Game Studio | N1385: =IFERROR(VLOOKUP(A1385, Entries!A:K,11,false),"") | O1385: =IFERROR(VLOOKUP(A1385, Entries!A:I,8,false),"") -> FALSE
A1386: Clue/Cluedo: The Classic Mystery Game | B1386: Fanatical | C1386: 44580 | D1386: 44600 | E1386: 3.56 | F1386: 4.23 | G1386: =MINUS(F1386,E1386) -> 0.67 | H1386: =IFERROR(G1386/F1386,"") -> 0.15839243 | I1386: KNQY7-6CM6Y-H804N | J1386: Closed | K1386: =IFERROR(DATEDIF(C1386,D1386,"D"), "") -> 20 | L1386: =IF(D1386="","",TEXT(D1386,"DDD")) -> Tue | M1386: =IFERROR(VLOOKUP(A1386, Entries!A:B,2,false),"") -> Marmalade Game Studio | N1386: =IFERROR(VLOOKUP(A1386, Entries!A:K,11,false),"") | O1386: =IFERROR(VLOOKUP(A1386, Entries!A:I,8,false),"") -> FALSE
A1387: Brick Rigs | B1387: Fanatical | C1387: 44580 | D1387: 44583 | E1387: 6.56 | F1387: 7.87 | G1387: =MINUS(F1387,E1387) -> 1.31 | H1387: =IFERROR(G1387/F1387,"") -> 0.16645489 | I1387: PAN98-K8PXC-M832K | J1387: Closed | K1387: =IFERROR(DATEDIF(C1387,D1387,"D"), "") -> 3 | L1387: =IF(D1387="","",TEXT(D1387,"DDD")) -> Sat | M1387: =IFERROR(VLOOKUP(A1387, Entries!A:B,2,false),"") -> Lukas Rustemeyer | N1387: =IFERROR(VLOOKUP(A1387, Entries!A:K,11,false),"") | O1387: =IFERROR(VLOOKUP(A1387, Entries!A:I,8,false),"") -> TRUE
A1388: Clue/Cluedo: The Classic Mystery Game | B1388: Fanatical | C1388: 44580 | D1388: 44600 | E1388: 3.56 | F1388: 4.23 | G1388: =MINUS(F1388,E1388) -> 0.67 | H1388: =IFERROR(G1388/F1388,"") -> 0.15839243 | I1388: EHGDA-44KMM-QZAL8 | J1388: Closed | K1388: =IFERROR(DATEDIF(C1388,D1388,"D"), "") -> 20 | L1388: =IF(D1388="","",TEXT(D1388,"DDD")) -> Tue | M1388: =IFERROR(VLOOKUP(A1388, Entries!A:B,2,false),"") -> Marmalade Game Studio | N1388: =IFERROR(VLOOKUP(A1388, Entries!A:K,11,false),"") | O1388: =IFERROR(VLOOKUP(A1388, Entries!A:I,8,false),"") -> FALSE
A1389: Brick Rigs | B1389: Fanatical | C1389: 44580 | D1389: 44583 | E1389: 6.56 | F1389: 7.87 | G1389: =MINUS(F1389,E1389) -> 1.31 | H1389: =IFERROR(G1389/F1389,"") -> 0.16645489 | I1389: JZ5KA-T7CJ0-WA8CA | J1389: Closed | K1389: =IFERROR(DATEDIF(C1389,D1389,"D"), "") -> 3 | L1389: =IF(D1389="","",TEXT(D1389,"DDD")) -> Sat | M1389: =IFERROR(VLOOKUP(A1389, Entries!A:B,2,false),"") -> Lukas Rustemeyer | N1389: =IFERROR(VLOOKUP(A1389, Entries!A:K,11,false),"") | O1389: =IFERROR(VLOOKUP(A1389, Entries!A:I,8,false),"") -> TRUE
A1390: Pathfinder: Wrath of the Righteous | B1390: CDKeys | C1390: 44580 | D1390: 44581 | E1390: 34.33 | F1390: 39.9 | G1390: =MINUS(F1390,E1390) -> 5.57 | H1390: =IFERROR(G1390/F1390,"") -> 0.139599 | I1390: GNWVW-K0IGT-46LLJ | J1390: Closed | K1390: =IFERROR(DATEDIF(C1390,D1390,"D"), "") -> 1 | L1390: =IF(D1390="","",TEXT(D1390,"DDD")) -> Thu | M1390: =IFERROR(VLOOKUP(A1390, Entries!A:B,2,false),"") -> META Publishing | N1390: =IFERROR(VLOOKUP(A1390, Entries!A:K,11,false),"") | O1390: =IFERROR(VLOOKUP(A1390, Entries!A:I,8,false),"") -> TRUE
... A1409: The Elder Scrolls V: Skyrim VR | B1409: CDKeys | C1409: 44584 | D1409: 44585 | E1409: 19.07 | F1409: 24.28 | G1409: =MINUS(F1409,E1409) -> 5.21 | H1409: =IFERROR(G1409/F1409,"") -> 0.2145799 | I1409: CLR53-7ZQIH-4R0D4 | J1409: Closed | K1409: =IFERROR(DATEDIF(C1409,D1409,"D"), "") -> 1 | L1409: =IF(D1409="","",TEXT(D1409,"DDD")) -> Mon | M1409: =IFERROR(VLOOKUP(A1409, Entries!A:B,2,false),"") -> Bethesda Softworks | N1409: =IFERROR(VLOOKUP(A1409, Entries!A:K,11,false),"") | O1409: =IFERROR(VLOOKUP(A1409, Entries!A:I,8,false),"") -> TRUE
A1410: Pathfinder: Wrath of the Righteous | B1410: CDKeys | C1410: 44585 | D1410: 46147 | E1410: 33.82 | F1410: 1.68 | G1410: =MINUS(F1410,E1410) -> -32.14 | H1410: =IFERROR(G1410/F1410,"") -> -19.130952 | I1410: TEW7J-6952G-3GLKY | J1410: Closed | K1410: =IFERROR(DATEDIF(C1410,D1410,"D"), "") -> 1562 | L1410: =IF(D1410="","",TEXT(D1410,"DDD")) -> Tue | M1410: =IFERROR(VLOOKUP(A1410, Entries!A:B,2,false),"") -> META Publishing | N1410: =IFERROR(VLOOKUP(A1410, Entries!A:K,11,false),"") | O1410: =IFERROR(VLOOKUP(A1410, Entries!A:I,8,false),"") -> TRUE | S1410: =IF(AND(TODAY()-ROW(A586)+1 <= 30, J586="Closed"), TEXT(TODAY()-ROW(A586)+1, "dd-mm-yyyy"), "")
A1411: NBA 2K22 EU | B1411: GreenMan | C1411: 44585 | D1411: 44585 | E1411: 15.51 | F1411: 18.18 | G1411: =MINUS(F1411,E1411) -> 2.67 | H1411: =IFERROR(G1411/F1411,"") -> 0.14686469 | I1411: N7X4J-DR728-0Z2AW | J1411: Closed | K1411: =IFERROR(DATEDIF(C1411,D1411,"D"), "") -> 0 | L1411: =IF(D1411="","",TEXT(D1411,"DDD")) -> Mon | M1411: =IFERROR(VLOOKUP(A1411, Entries!A:B,2,false),"") -> 2K | N1411: =IFERROR(VLOOKUP(A1411, Entries!A:K,11,false),"") | O1411: =IFERROR(VLOOKUP(A1411, Entries!A:I,8,false),"") -> FALSE
A1412: Shadow Warrior 2 | B1412: Fanatical | C1412: 44585 | D1412: 44585 | E1412: 3.49 | F1412: 4.69 | G1412: =MINUS(F1412,E1412) -> 1.2 | H1412: =IFERROR(G1412/F1412,"") -> 0.25586354 | I1412: FQHH2-FVYEI-448Z7 | J1412: Closed | K1412: =IFERROR(DATEDIF(C1412,D1412,"D"), "") -> 0 | L1412: =IF(D1412="","",TEXT(D1412,"DDD")) -> Mon | M1412: =IFERROR(VLOOKUP(A1412, Entries!A:B,2,false),"") -> Devolver Digital | N1412: =IFERROR(VLOOKUP(A1412, Entries!A:K,11,false),"") | O1412: =IFERROR(VLOOKUP(A1412, Entries!A:I,8,false),"") -> FALSE
A1413: Shadow Warrior 2 | B1413: Fanatical | C1413: 44585 | D1413: 44585 | E1413: 3.49 | F1413: 4.69 | G1413: =MINUS(F1413,E1413) -> 1.2 | H1413: =IFERROR(G1413/F1413,"") -> 0.25586354 | I1413: DCQIM-MRIZE-NB8EL | J1413: Closed | K1413: =IFERROR(DATEDIF(C1413,D1413,"D"), "") -> 0 | L1413: =IF(D1413="","",TEXT(D1413,"DDD")) -> Mon | M1413: =IFERROR(VLOOKUP(A1413, Entries!A:B,2,false),"") -> Devolver Digital | N1413: =IFERROR(VLOOKUP(A1413, Entries!A:K,11,false),"") | O1413: =IFERROR(VLOOKUP(A1413, Entries!A:I,8,false),"") -> FALSE
A1414: NBA 2K22 EU | B1414: GreenMan | C1414: 44585 | D1414: 44814 | E1414: 15.51 | F1414: 7.95 | G1414: =MINUS(F1414,E1414) -> -7.56 | H1414: =IFERROR(G1414/F1414,"") -> -0.9509434 | I1414: IMC5P-ZDB7T-YX0EV | J1414: Closed | K1414: =IFERROR(DATEDIF(C1414,D1414,"D"), "") -> 229 | L1414: =IF(D1414="","",TEXT(D1414,"DDD")) -> Sat | M1414: =IFERROR(VLOOKUP(A1414, Entries!A:B,2,false),"") -> 2K | N1414: =IFERROR(VLOOKUP(A1414, Entries!A:K,11,false),"") | O1414: =IFERROR(VLOOKUP(A1414, Entries!A:I,8,false),"") -> FALSE
A1415: NBA 2K22 EU | B1415: GreenMan | C1415: 44585 | D1415: 44814 | E1415: 15.52 | F1415: 8.18 | G1415: =MINUS(F1415,E1415) -> -7.34 | H1415: =IFERROR(G1415/F1415,"") -> -0.89731051 | I1415: 98EVY-RVGLN-PQPCN | J1415: Closed | K1415: =IFERROR(DATEDIF(C1415,D1415,"D"), "") -> 229 | L1415: =IF(D1415="","",TEXT(D1415,"DDD")) -> Sat | M1415: =IFERROR(VLOOKUP(A1415, Entries!A:B,2,false),"") -> 2K | N1415: =IFERROR(VLOOKUP(A1415, Entries!A:K,11,false),"") | O1415: =IFERROR(VLOOKUP(A1415, Entries!A:I,8,false),"") -> FALSE
A1416: The Elder Scrolls V: Skyrim VR | B1416: CDKeys | C1416: 44585 | D1416: 44585 | E1416: 18.78 | F1416: 24.17 | G1416: =MINUS(F1416,E1416) -> 5.39 | H1416: =IFERROR(G1416/F1416,"") -> 0.22300372 | I1416: QGYTZ-XJNWP-W0DBN | J1416: Closed | K1416: =IFERROR(DATEDIF(C1416,D1416,"D"), "") -> 0 | L1416: =IF(D1416="","",TEXT(D1416,"DDD")) -> Mon | M1416: =IFERROR(VLOOKUP(A1416, Entries!A:B,2,false),"") -> Bethesda Softworks | N1416: =IFERROR(VLOOKUP(A1416, Entries!A:K,11,false),"") | O1416: =IFERROR(VLOOKUP(A1416, Entries!A:I,8,false),"") -> TRUE
A1417: The Elder Scrolls V: Skyrim VR | B1417: CDKeys | C1417: 44585 | D1417: 44585 | E1417: 18.78 | F1417: 24.03 | G1417: =MINUS(F1417,E1417) -> 5.25 | H1417: =IFERROR(G1417/F1417,"") -> 0.2184769 | I1417: DHRMJ-DFCFB-33GGC | J1417: Closed | K1417: =IFERROR(DATEDIF(C1417,D1417,"D"), "") -> 0 | L1417: =IF(D1417="","",TEXT(D1417,"DDD")) -> Mon | M1417: =IFERROR(VLOOKUP(A1417, Entries!A:B,2,false),"") -> Bethesda Softworks | N1417: =IFERROR(VLOOKUP(A1417, Entries!A:K,11,false),"") | O1417: =IFERROR(VLOOKUP(A1417, Entries!A:I,8,false),"") -> TRUE
A1418: Serious Sam 4 | B1418: Fanatical | C1418: 44585 | D1418: 44597 | E1418: 14 | F1418: 15.43 | G1418: =MINUS(F1418,E1418) -> 1.43 | H1418: =IFERROR(G1418/F1418,"") -> 0.092676604 | I1418: 0Z3RC-LD422-IN3HD | J1418: Closed | K1418: =IFERROR(DATEDIF(C1418,D1418,"D"), "") -> 12 | L1418: =IF(D1418="","",TEXT(D1418,"DDD")) -> Sat | M1418: =IFERROR(VLOOKUP(A1418, Entries!A:B,2,false),"") -> Devolver Digital | N1418: =IFERROR(VLOOKUP(A1418, Entries!A:K,11,false),"") | O1418: =IFERROR(VLOOKUP(A1418, Entries!A:I,8,false),"") -> FALSE
A1419: River City Ransom: Underground | B1419: Fanatical | C1419: 44585 | D1419: 44585 | E1419: 0 | F1419: 1.21 | G1419: =MINUS(F1419,E1419) -> 1.21 | H1419: =IFERROR(G1419/F1419,"") -> 1 | I1419: 9MBMN-N3X5H-25A79 | J1419: Closed | K1419: =IFERROR(DATEDIF(C1419,D1419,"D"), "") -> 0 | L1419: =IF(D1419="","",TEXT(D1419,"DDD")) -> Mon | M1419: =IFERROR(VLOOKUP(A1419, Entries!A:B,2,false),"") -> Conatus Creative | N1419: =IFERROR(VLOOKUP(A1419, Entries!A:K,11,false),"") | O1419: =IFERROR(VLOOKUP(A1419, Entries!A:I,8,false),"") -> FALSE
A1420: Shadow Warrior 2 | B1420: Fanatical | C1420: 44585 | D1420: 44585 | E1420: 3.49 | F1420: 4.69 | G1420: =MINUS(F1420,E1420) -> 1.2 | H1420: =IFERROR(G1420/F1420,"") -> 0.25586354 | I1420: XBLRI-WVIA9-YMB6F | J1420: Closed | K1420: =IFERROR(DATEDIF(C1420,D1420,"D"), "") -> 0 | L1420: =IF(D1420="","",TEXT(D1420,"DDD")) -> Mon | M1420: =IFERROR(VLOOKUP(A1420, Entries!A:B,2,false),"") -> Devolver Digital | N1420: =IFERROR(VLOOKUP(A1420, Entries!A:K,11,false),"") | O1420: =IFERROR(VLOOKUP(A1420, Entries!A:I,8,false),"") -> FALSE
A1421: Creed: Rise to Glory | B1421: Fanatical | C1421: 44585 | D1421: 44586 | E1421: 6.04 | F1421: 6.93 | G1421: =MINUS(F1421,E1421) -> 0.89 | H1421: =IFERROR(G1421/F1421,"") -> 0.12842713 | I1421: L8YY6-AAMBM-XWYH3 | J1421: Closed | K1421: =IFERROR(DATEDIF(C1421,D1421,"D"), "") -> 1 | L1421: =IF(D1421="","",TEXT(D1421,"DDD")) -> Tue | M1421: =IFERROR(VLOOKUP(A1421, Entries!A:B,2,false),"") -> Survios | N1421: =IFERROR(VLOOKUP(A1421, Entries!A:K,11,false),"") | O1421: =IFERROR(VLOOKUP(A1421, Entries!A:I,8,false),"") -> TRUE
...

Sheet Summary
B1: April | D1: May | F1: June | H1: July | J1: August | L1: September | N1: October | P1: November | R1: December | T1: January | V1: February | X1: March | Z1: Final
B2: 43922 | C2: 43951 | D2: 43952 | E2: 43982 | F2: 43983 | G2: 44012 | H2: 44013 | I2: 44043 | J2: 44044 | K2: 44074 | L2: 44075 | M2: 44104 | N2: 44105 | O2: 44135 | P2: 44136 | Q2: 44165 | R2: 44166 | S2: 44196 | T2: 44197 | U2: 44227 | V2: 44228 | W2: 44255 | X2: 44256 | Y2: 44286
A3: Total Income | B3: =IFERROR(__xludf.DUMMYFUNCTION("SUM(FILTER(Inventory!F:F,Inventory!J:J=""Closed"",Inventory!D:D>=B2,Inventory!D:D<=C2))"),65.97) -> 65.97 | D3: =IFERROR(__xludf.DUMMYFUNCTION("SUM(FILTER(Inventory!F:F,Inventory!J:J=""Closed"",Inventory!D:D>=D2,Inventory!D:D<=E2))"),346.67) -> 346.67 | F3: =IFERROR(__xludf.DUMMYFUNCTION("SUM(FILTER(Inventory!F:F,Inventory!J:J=""Closed"",Inventory!D:D>=F2,Inventory!D:D<=G2))"),410.05999999999966) -> 410.06 | H3: =IFERROR(__xludf.DUMMYFUNCTION("SUM(FILTER(Inventory!F:F,Inventory!J:J=""Closed"",Inventory!D:D>=H2,Inventory!D:D<=I2))"),416.56999999999994) -> 416.57 | J3: =SUMIFS(Inventory!F:F, Inventory!D:D,">="&J2,Inventory!D:D,"<="&K2) -> 432.68 | L3: =IFERROR(__xludf.DUMMYFUNCTION("SUM(FILTER(Inventory!F:F,Inventory!J:J=""Closed"",Inventory!D:D>=L2,Inventory!D:D<=M2))"),281.75000000000006) -> 281.75 | N3: =IFERROR(__xludf.DUMMYFUNCTION("SUM(FILTER(Inventory!F:F,Inventory!J:J=""Closed"",Inventory!D:D>=N2,Inventory!D:D<=O2))"),417.96999999999997) -> 417.97 | P3: =IFERROR(__xludf.DUMMYFUNCTION("SUM(FILTER(Inventory!F:F,Inventory!J:J=""Closed"",Inventory!D:D>=P2,Inventory!D:D<=Q2))"),219.04) -> 219.04 | R3: =IFERROR(__xludf.DUMMYFUNCTION("SUM(FILTER(Inventory!F:F,Inventory!J:J=""Closed"",Inventory!D:D>=R2,Inventory!D:D<=S2))"),370.59) -> 370.59 | T3: =IFERROR(__xludf.DUMMYFUNCTION("SUM(FILTER(Inventory!F:F,Inventory!J:J=""Closed"",Inventory!D:D>=T2,Inventory!D:D<=U2))"),318.6200000000002) -> 318.62 | V3: =IFERROR(__xludf.DUMMYFUNCTION("SUM(FILTER(Inventory!F:F,Inventory!J:J=""Closed"",Inventory!D:D>=V2,Inventory!D:D<=W2))"),102.67) -> 102.67 | X3: =IFERROR(__xludf.DUMMYFUNCTION("SUM(FILTER(Inventory!F:F,Inventory!J:J=""Closed"",Inventory!D:D>=X2,Inventory!D:D<=Y2))"),233.06000000000003) -> 233.06
A4: Total Spent | B4: =IFERROR(__xludf.DUMMYFUNCTION("SUM(FILTER(Inventory!E:E,Inventory!J:J=""Closed"",Inventory!D:D>=B2,Inventory!D:D<=C2))"),54.33) -> 54.33 | D4: =IFERROR(__xludf.DUMMYFUNCTION("SUM(FILTER(Inventory!E:E,Inventory!J:J=""Closed"",Inventory!D:D>=D2,Inventory!D:D<=E2))"),249.37000000000006) -> 249.37 | F4: =IFERROR(__xludf.DUMMYFUNCTION("SUM(FILTER(Inventory!E:E,Inventory!J:J=""Closed"",Inventory!D:D>=F2,Inventory!D:D<=G2))"),288.35999999999996) -> 288.36 | H4: =IFERROR(__xludf.DUMMYFUNCTION("SUM(FILTER(Inventory!E:E,Inventory!J:J=""Closed"",Inventory!D:D>=H2,Inventory!D:D<=I2))"),288.36999999999995) -> 288.37 | J4: =SUMIFS(Inventory!E:E, Inventory!D:D,">="&J2,Inventory!D:D,"<="&K2) -> 291.44 | L4: =IFERROR(__xludf.DUMMYFUNCTION("SUM(FILTER(Inventory!E:E,Inventory!J:J=""Closed"",Inventory!D:D>=L2,Inventory!D:D<=M2))"),195.22999999999988) -> 195.23 | N4: =IFERROR(__xludf.DUMMYFUNCTION("SUM(FILTER(Inventory!E:E,Inventory!J:J=""Closed"",Inventory!D:D>=N2,Inventory!D:D<=O2))"),290.0999999999999) -> 290.1 | P4: =IFERROR(__xludf.DUMMYFUNCTION("SUM(FILTER(Inventory!E:E,Inventory!J:J=""Closed"",Inventory!D:D>=P2,Inventory!D:D<=Q2))"),152.52999999999997) -> 152.53 | R4: =IFERROR(__xludf.DUMMYFUNCTION("SUM(FILTER(Inventory!E:E,Inventory!J:J=""Closed"",Inventory!D:D>=R2,Inventory!D:D<=S2))"),261.33) -> 261.33 | T4: =IFERROR(__xludf.DUMMYFUNCTION("SUM(FILTER(Inventory!E:E,Inventory!J:J=""Closed"",Inventory!D:D>=T2,Inventory!D:D<=U2))"),236.65999999999994) -> 236.66 | V4: =IFERROR(__xludf.DUMMYFUNCTION("SUM(FILTER(Inventory!E:E,Inventory!J:J=""Closed"",Inventory!D:D>=V2,Inventory!D:D<=W2))"),78.96000000000001) -> 78.96 | X4: =IFERROR(__xludf.DUMMYFUNCTION("SUM(FILTER(Inventory!E:E,Inventory!J:J=""Closed"",Inventory!D:D>=X2,Inventory!D:D<=Y2))"),176.26000000000002) -> 176.26
A5: Total Profit | B5: =IFERROR(__xludf.DUMMYFUNCTION("SUM(FILTER(Inventory!G:G,Inventory!J:J=""Closed"",Inventory!D:D>=B2,Inventory!D:D<=C2))"),11.639999999999997) -> 11.64 | D5: =IFERROR(__xludf.DUMMYFUNCTION("SUM(FILTER(Inventory!G:G,Inventory!J:J=""Closed"",Inventory!D:D>=D2,Inventory!D:D<=E2))"),97.29999999999998) -> 97.3 | F5: =IFERROR(__xludf.DUMMYFUNCTION("SUM(FILTER(Inventory!G:G,Inventory!J:J=""Closed"",Inventory!D:D>=F2,Inventory!D:D<=G2))"),121.69999999999999) -> 121.7 | H5: =IFERROR(__xludf.DUMMYFUNCTION("SUM(FILTER(Inventory!G:G,Inventory!J:J=""Closed"",Inventory!D:D>=H2,Inventory!D:D<=I2))"),128.20000000000002) -> 128.2 | J5: =SUMIFS(Inventory!G:G, Inventory!D:D,">="&J2,Inventory!D:D,"<="&K2) -> 141.24 | L5: =IFERROR(__xludf.DUMMYFUNCTION("SUM(FILTER(Inventory!G:G,Inventory!J:J=""Closed"",Inventory!D:D>=L2,Inventory!D:D<=M2))"),86.52000000000002) -> 86.52 | N5: =IFERROR(__xludf.DUMMYFUNCTION("SUM(FILTER(Inventory!G:G,Inventory!J:J=""Closed"",Inventory!D:D>=N2,Inventory!D:D<=O2))"),127.86999999999996) -> 127.87 | P5: =IFERROR(__xludf.DUMMYFUNCTION("SUM(FILTER(Inventory!G:G,Inventory!J:J=""Closed"",Inventory!D:D>=P2,Inventory!D:D<=Q2))"),66.50999999999999) -> 66.51 | R5: =IFERROR(__xludf.DUMMYFUNCTION("SUM(FILTER(Inventory!G:G,Inventory!J:J=""Closed"",Inventory!D:D>=R2,Inventory!D:D<=S2))"),109.25999999999999) -> 109.26 | T5: =IFERROR(__xludf.DUMMYFUNCTION("SUM(FILTER(Inventory!G:G,Inventory!J:J=""Closed"",Inventory!D:D>=T2,Inventory!D:D<=U2))"),81.96) -> 81.96 | V5: =IFERROR(__xludf.DUMMYFUNCTION("SUM(FILTER(Inventory!G:G,Inventory!J:J=""Closed"",Inventory!D:D>=V2,Inventory!D:D<=W2))"),23.709999999999994) -> 23.71 | X5: =IFERROR(__xludf.DUMMYFUNCTION("SUM(FILTER(Inventory!G:G,Inventory!J:J=""Closed"",Inventory!D:D>=X2,Inventory!D:D<=Y2))"),56.800000000000004) -> 56.8
A6: Sold Items | B6: =COUNTIFS(Inventory!J:J,"Closed", Inventory!D:D,">="&B2,Inventory!D:D,"<="&C2) -> 4 | D6: =COUNTIFS(Inventory!J:J,"Closed", Inventory!D:D,">="&D2,Inventory!D:D,"<="&E2) -> 38 | F6: =COUNTIFS(Inventory!J:J,"Closed", Inventory!D:D,">="&F2,Inventory!D:D,"<="&G2) -> 67 | H6: =COUNTIFS(Inventory!J:J,"Closed", Inventory!D:D,">="&H2,Inventory!D:D,"<="&I2) -> 69 | J6: =COUNTIFS(Inventory!J:J,"Closed", Inventory!D:D,">="&J2,Inventory!D:D,"<="&K2) -> 94 | L6: =COUNTIFS(Inventory!J:J,"Closed", Inventory!D:D,">="&L2,Inventory!D:D,"<="&M2) -> 70 | N6: =COUNTIFS(Inventory!J:J,"Closed", Inventory!D:D,">="&N2,Inventory!D:D,"<="&O2) -> 73 | P6: =COUNTIFS(Inventory!J:J,"Closed", Inventory!D:D,">="&P2,Inventory!D:D,"<="&Q2) -> 38 | R6: =COUNTIFS(Inventory!J:J,"Closed", Inventory!D:D,">="&R2,Inventory!D:D,"<="&S2) -> 80 | T6: =COUNTIFS(Inventory!J:J,"Closed", Inventory!D:D,">="&T2,Inventory!D:D,"<="&U2) -> 46 | V6: =COUNTIFS(Inventory!J:J,"Closed", Inventory!D:D,">="&V2,Inventory!D:D,"<="&W2) -> 16 | X6: =COUNTIFS(Inventory!J:J,"Closed", Inventory!D:D,">="&X2,Inventory!D:D,"<="&Y2) -> 29
A7: Avg Sold Price | B7: =IFERROR(__xludf.DUMMYFUNCTION("AVERAGE(FILTER(Inventory!F:F,Inventory!J:J=""Closed"",Inventory!D:D>=B2,Inventory!D:D<=C2))"),16.4925) -> 16.4925 | D7: =IFERROR(__xludf.DUMMYFUNCTION("AVERAGE(FILTER(Inventory!F:F,Inventory!J:J=""Closed"",Inventory!D:D>=D2,Inventory!D:D<=F2))"),8.972750000000001) -> 8.97275 | F7: =IFERROR(__xludf.DUMMYFUNCTION("AVERAGE(FILTER(Inventory!F:F,Inventory!J:J=""Closed"",Inventory!D:D>=F2,Inventory!D:D<=G2))"),6.120298507462682) -> 6.1202985 | H7: =IFERROR(__xludf.DUMMYFUNCTION("AVERAGE(FILTER(Inventory!F:F,Inventory!J:J=""Closed"",Inventory!D:D>=H2,Inventory!D:D<=I2))"),6.037246376811593) -> 6.0372464 | J7: =IFERROR(__xludf.DUMMYFUNCTION("AVERAGE(FILTER(Inventory!F:F,Inventory!J:J=""Closed"",Inventory!D:D>=J2,Inventory!D:D<=K2))"),4.602978723404255) -> 4.6029787 | L7: =IFERROR(__xludf.DUMMYFUNCTION("AVERAGE(FILTER(Inventory!F:F,Inventory!J:J=""Closed"",Inventory!D:D>=L2,Inventory!D:D<=M2))"),4.025000000000001) -> 4.025 | N7: =IFERROR(__xludf.DUMMYFUNCTION("AVERAGE(FILTER(Inventory!F:F,Inventory!J:J=""Closed"",Inventory!D:D>=N2,Inventory!D:D<=O2))"),5.725616438356164) -> 5.7256164 | P7: =IFERROR(__xludf.DUMMYFUNCTION("AVERAGE(FILTER(Inventory!F:F,Inventory!J:J=""Closed"",Inventory!D:D>=P2,Inventory!D:D<=Q2))"),5.7642105263157895) -> 5.7642105 | R7: =IFERROR(__xludf.DUMMYFUNCTION("AVERAGE(FILTER(Inventory!F:F,Inventory!J:J=""Closed"",Inventory!D:D>=R2,Inventory!D:D<=S2))"),4.632375) -> 4.632375 | T7: =IFERROR(__xludf.DUMMYFUNCTION("AVERAGE(FILTER(Inventory!F:F,Inventory!J:J=""Closed"",Inventory!D:D>=T2,Inventory!D:D<=U2))"),6.926521739130439) -> 6.9265217 | V7: =IFERROR(__xludf.DUMMYFUNCTION("AVERAGE(FILTER(Inventory!F:F,Inventory!J:J=""Closed"",Inventory!D:D>=V2,Inventory!D:D<=W2))"),6.416875) -> 6.416875 | X7: =IFERROR(__xludf.DUMMYFUNCTION("AVERAGE(FILTER(Inventory!F:F,Inventory!J:J=""Closed"",Inventory!D:D>=X2,Inventory!D:D<=Y2))"),8.036551724137933) -> 8.0365517
A8: Average Profit | B8: =IFERROR(__xludf.DUMMYFUNCTION("AVERAGE(FILTER(Inventory!G:G,Inventory!J:J=""Closed"",Inventory!D:D>=B2,Inventory!D:D<=C2))"),2.9099999999999993) -> 2.91 | D8: =IFERROR(__xludf.DUMMYFUNCTION("AVERAGE(FILTER(Inventory!G:G,Inventory!J:J=""Closed"",Inventory!D:D>=D2,Inventory!D:D<=E2))"),2.560526315789473) -> 2.5605263 | F8: =IFERROR(__xludf.DUMMYFUNCTION("AVERAGE(FILTER(Inventory!G:G,Inventory!J:J=""Closed"",Inventory!D:D>=F2,Inventory!D:D<=G2))"),1.8164179104477611) -> 1.8164179 | H8: =IFERROR(__xludf.DUMMYFUNCTION("AVERAGE(FILTER(Inventory!G:G,Inventory!J:J=""Closed"",Inventory!D:D>=H2,Inventory!D:D<=I2))"),1.857971014492754) -> 1.857971 | J8: =(J5/J6) -> 1.5025532 | L8: =IFERROR(__xludf.DUMMYFUNCTION("AVERAGE(FILTER(Inventory!G:G,Inventory!J:J=""Closed"",Inventory!D:D>=L2,Inventory!D:D<=M2))"),1.2360000000000004) -> 1.236 | N8: =IFERROR(__xludf.DUMMYFUNCTION("AVERAGE(FILTER(Inventory!G:G,Inventory!J:J=""Closed"",Inventory!D:D>=N2,Inventory!D:D<=O2))"),1.7516438356164379) -> 1.7516438 | P8: =IFERROR(__xludf.DUMMYFUNCTION("AVERAGE(FILTER(Inventory!G:G,Inventory!J:J=""Closed"",Inventory!D:D>=P2,Inventory!D:D<=Q2))"),1.7502631578947365) -> 1.7502632 | R8: =IFERROR(__xludf.DUMMYFUNCTION("AVERAGE(FILTER(Inventory!G:G,Inventory!J:J=""Closed"",Inventory!D:D>=R2,Inventory!D:D<=S2))"),1.3657499999999998) -> 1.36575 | T8: =IFERROR(__xludf.DUMMYFUNCTION("AVERAGE(FILTER(Inventory!G:G,Inventory!J:J=""Closed"",Inventory!D:D>=T2,Inventory!D:D<=U2))"),1.7817391304347825) -> 1.7817391 | V8: =IFERROR(__xludf.DUMMYFUNCTION("AVERAGE(FILTER(Inventory!G:G,Inventory!J:J=""Closed"",Inventory!D:D>=V2,Inventory!D:D<=W2))"),1.4818749999999996) -> 1.481875 | X8: =IFERROR(__xludf.DUMMYFUNCTION("AVERAGE(FILTER(Inventory!G:G,Inventory!J:J=""Closed"",Inventory!D:D>=X2,Inventory!D:D<=Y2))"),1.9586206896551726) -> 1.9586207
A9: Average Margin | B9: =IFERROR(__xludf.DUMMYFUNCTION("AVERAGE(FILTER(Inventory!H:H,Inventory!J:J=""Closed"",Inventory!D:D>=B2,Inventory!D:D<=C2))"),0.18396908295652564) -> 0.18396908 | D9: =IFERROR(__xludf.DUMMYFUNCTION("AVERAGE(FILTER(Inventory!H:H,Inventory!J:J=""Closed"",Inventory!D:D>=D2,Inventory!D:D<=E2))"),0.3621047756206788) -> 0.36210478 | F9: =IFERROR(__xludf.DUMMYFUNCTION("AVERAGE(FILTER(Inventory!H:H,Inventory!J:J=""Closed"",Inventory!D:D>=F2,Inventory!D:D<=G2))"),0.340298310285003) -> 0.34029831 | H9: =IFERROR(__xludf.DUMMYFUNCTION("AVERAGE(FILTER(Inventory!H:H,Inventory!J:J=""Closed"",Inventory!D:D>=H2,Inventory!D:D<=I2))"),0.44620493213612916) -> 0.44620493 | J9: =IFERROR(__xludf.DUMMYFUNCTION("AVERAGE(FILTER(Inventory!H:H,Inventory!J:J=""Closed"",Inventory!D:D>=J2,Inventory!D:D<=K2))"),0.4975077121623062) -> 0.49750771 | L9: =IFERROR(__xludf.DUMMYFUNCTION("AVERAGE(FILTER(Inventory!H:H,Inventory!J:J=""Closed"",Inventory!D:D>=L2,Inventory!D:D<=M2))"),0.3924121493497027) -> 0.39241215 | N9: =IFERROR(__xludf.DUMMYFUNCTION("AVERAGE(FILTER(Inventory!H:H,Inventory!J:J=""Closed"",Inventory!D:D>=N2,Inventory!D:D<=O2))"),0.3238315889657102) -> 0.32383159 | P9: =IFERROR(__xludf.DUMMYFUNCTION("AVERAGE(FILTER(Inventory!H:H,Inventory!J:J=""Closed"",Inventory!D:D>=P2,Inventory!D:D<=Q2))"),0.4045801260039225) -> 0.40458013 | R9: =IFERROR(__xludf.DUMMYFUNCTION("AVERAGE(FILTER(Inventory!H:H,Inventory!J:J=""Closed"",Inventory!D:D>=R2,Inventory!D:D<=S2))"),0.28682595626752533) -> 0.28682596 | T9: =IFERROR(__xludf.DUMMYFUNCTION("AVERAGE(FILTER(Inventory!H:H,Inventory!J:J=""Closed"",Inventory!D:D>=T2,Inventory!D:D<=U2))"),0.38155756404871605) -> 0.38155756 | V9: =IFERROR(__xludf.DUMMYFUNCTION("AVERAGE(FILTER(Inventory!H:H,Inventory!J:J=""Closed"",Inventory!D:D>=V2,Inventory!D:D<=W2))"),0.39288486309342485) -> 0.39288486 | X9: =IFERROR(__xludf.DUMMYFUNCTION("AVERAGE(FILTER(Inventory!H:H,Inventory!J:J=""Closed"",Inventory!D:D>=X2,Inventory!D:D<=Y2))"),0.39256338427621873) -> 0.39256338
A10: Average Duration | B10: =IFERROR(__xludf.DUMMYFUNCTION("AVERAGE(FILTER(Inventory!K:K,Inventory!J:J=""Closed"",Inventory!D:D>=B2,Inventory!D:D<=C2))"),0.25) -> 0.25 | D10: =IFERROR(__xludf.DUMMYFUNCTION("AVERAGE(FILTER(Inventory!K:K,Inventory!J:J=""Closed"",Inventory!D:D>=D2,Inventory!D:D<=E2))"),12.973684210526315) -> 12.973684 | F10: =IFERROR(__xludf.DUMMYFUNCTION("AVERAGE(FILTER(Inventory!K:K,Inventory!J:J=""Closed"",Inventory!D:D>=F2,Inventory!D:D<=G2))"),7.477611940298507) -> 7.4776119 | H10: =IFERROR(__xludf.DUMMYFUNCTION("AVERAGE(FILTER(Inventory!K:K,Inventory!J:J=""Closed"",Inventory!D:D>=H2,Inventory!D:D<=I2))"),10.18840579710145) -> 10.188406 | J10: =IFERROR(__xludf.DUMMYFUNCTION("AVERAGE(FILTER(Inventory!K:K,Inventory!J:J=""Closed"",Inventory!D:D>=J2,Inventory!D:D<=K2))"),14.585106382978724) -> 14.585106 | L10: =IFERROR(__xludf.DUMMYFUNCTION("AVERAGE(FILTER(Inventory!K:K,Inventory!J:J=""Closed"",Inventory!D:D>=L2,Inventory!D:D<=M2))"),21.4) -> 21.4 | N10: =IFERROR(__xludf.DUMMYFUNCTION("AVERAGE(FILTER(Inventory!K:K,Inventory!J:J=""Closed"",Inventory!D:D>=N2,Inventory!D:D<=O2))"),16.28767123287671) -> 16.287671 | P10: =IFERROR(__xludf.DUMMYFUNCTION("AVERAGE(FILTER(Inventory!K:K,Inventory!J:J=""Closed"",Inventory!D:D>=P2,Inventory!D:D<=Q2))"),27.789473684210527) -> 27.789474 | R10: =IFERROR(__xludf.DUMMYFUNCTION("AVERAGE(FILTER(Inventory!K:K,Inventory!J:J=""Closed"",Inventory!D:D>=R2,Inventory!D:D<=S2))"),26.4) -> 26.4 | T10: =IFERROR(__xludf.DUMMYFUNCTION("AVERAGE(FILTER(Inventory!K:K,Inventory!J:J=""Closed"",Inventory!D:D>=T2,Inventory!D:D<=U2))"),43.869565217391305) -> 43.869565 | V10: =IFERROR(__xludf.DUMMYFUNCTION("AVERAGE(FILTER(Inventory!K:K,Inventory!J:J=""Closed"",Inventory!D:D>=V2,Inventory!D:D<=W2))"),69.5) -> 69.5 | X10: =IFERROR(__xludf.DUMMYFUNCTION("AVERAGE(FILTER(Inventory!K:K,Inventory!J:J=""Closed"",Inventory!D:D>=X2,Inventory!D:D<=Y2))"),69.72413793103448) -> 69.724138
A11: =IFERROR(__xludf.DUMMYFUNCTION("AVERAGE(FILTER(Inventory!K:K,Inventory!J:J=""Closed"",Inventory!D:D>=J23,Inventory!D:D<=K23))"),24.782608695652176) -> 24.782609
B12: 44287 | C12: 44316 | D12: 44317 | E12: 44347 | F12: 44348 | G12: 44377 | H12: 44378 | I12: 44408 | J12: 44409 | K12: 44439 | L12: 44440 | M12: 44469 | N12: 44470 | O12: 44500 | P12: 44501 | Q12: 44530 | R12: 44531 | S12: 44561 | T12: 44562 | U12: 44592 | V12: 44593 | W12: 44620 | X12: 44621 | Y12: 44651
A13: Revenue | B13: =IFERROR(__xludf.DUMMYFUNCTION("SUM(FILTER(Inventory!F:F,Inventory!J:J=""Closed"",Inventory!D:D>=B12,Inventory!D:D<=C12))"),359.35) -> 359.35 | D13: =IFERROR(__xludf.DUMMYFUNCTION("SUM(FILTER(Inventory!F:F,Inventory!J:J=""Closed"",Inventory!D:D>=D12,Inventory!D:D<=E12))"),483.0400000000001) -> 483.04 | F13: =IFERROR(__xludf.DUMMYFUNCTION("SUM(FILTER(Inventory!F:F,Inventory!J:J=""Closed"",Inventory!D:D>=F12,Inventory!D:D<=G12))"),509.4400000000001) -> 509.44 | H13: =IFERROR(__xludf.DUMMYFUNCTION("SUM(FILTER(Inventory!F:F,Inventory!J:J=""Closed"",Inventory!D:D>=H12,Inventory!D:D<=I12))"),334.81000000000006) -> 334.81 | J13: =IFERROR(__xludf.DUMMYFUNCTION("SUM(FILTER(Inventory!F:F,Inventory!J:J=""Closed"",Inventory!D:D>=J12,Inventory!D:D<=K12))"),151.37) -> 151.37 | L13: =IFERROR(__xludf.DUMMYFUNCTION("SUM(FILTER(Inventory!F:F,Inventory!J:J=""Closed"",Inventory!D:D>=L12,Inventory!D:D<=M12))"),686.7) -> 686.7 | N13: =IFERROR(__xludf.DUMMYFUNCTION("SUM(FILTER(Inventory!F:F,Inventory!J:J=""Closed"",Inventory!D:D>=N12,Inventory!D:D<=O12))"),1075.9500000000003) -> 1075.95 | P13: =IFERROR(__xludf.DUMMYFUNCTION("SUM(FILTER(Inventory!F:F,Inventory!J:J=""Closed"",Inventory!D:D>=P12,Inventory!D:D<=Q12))"),483.97000000000014) -> 483.97 | R13: =IFERROR(__xludf.DUMMYFUNCTION("SUM(FILTER(Inventory!F:F,Inventory!J:J=""Closed"",Inventory!D:D>=R12,Inventory!D:D<=S12))"),914.11) -> 914.11 | T13: =IFERROR(__xludf.DUMMYFUNCTION("SUM(FILTER(Inventory!F:F,Inventory!J:J=""Closed"",Inventory!D:D>=T12,Inventory!D:D<=U12))"),1045.08) -> 1045.08 | V13: =IFERROR(__xludf.DUMMYFUNCTION("SUM(FILTER(Inventory!F:F,Inventory!J:J=""Closed"",Inventory!D:D>=V12,Inventory!D:D<=W12))"),1103.8300000000002) -> 1103.83 | X13: =IFERROR(__xludf.DUMMYFUNCTION("SUM(FILTER(Inventory!F:F,Inventory!J:J=""Closed"",Inventory!D:D>=X12,Inventory!D:D<=Y12))"),1380.39) -> 1380.39
A14: Expenses | B14: =IFERROR(__xludf.DUMMYFUNCTION("SUM(FILTER(Inventory!E:E,Inventory!J:J=""Closed"",Inventory!D:D>=B12,Inventory!D:D<=C12))"),249.9) -> 249.9 | D14: =IFERROR(__xludf.DUMMYFUNCTION("SUM(FILTER(Inventory!E:E,Inventory!J:J=""Closed"",Inventory!D:D>=D12,Inventory!D:D<=E12))"),358.80000000000007) -> 358.8 | F14: =IFERROR(__xludf.DUMMYFUNCTION("SUM(FILTER(Inventory!E:E,Inventory!J:J=""Closed"",Inventory!D:D>=F12,Inventory!D:D<=G12))"),368.16) -> 368.16 | H14: =IFERROR(__xludf.DUMMYFUNCTION("SUM(FILTER(Inventory!E:E,Inventory!J:J=""Closed"",Inventory!D:D>=H12,Inventory!D:D<=I12))"),258.01000000000005) -> 258.01 | J14: =IFERROR(__xludf.DUMMYFUNCTION("SUM(FILTER(Inventory!E:E,Inventory!J:J=""Closed"",Inventory!D:D>=J12,Inventory!D:D<=K12))"),106.01999999999998) -> 106.02 | L14: =IFERROR(__xludf.DUMMYFUNCTION("SUM(FILTER(Inventory!E:E,Inventory!J:J=""Closed"",Inventory!D:D>=L12,Inventory!D:D<=M12))"),466.16999999999996) -> 466.17 | N14: =IFERROR(__xludf.DUMMYFUNCTION("SUM(FILTER(Inventory!E:E,Inventory!J:J=""Closed"",Inventory!D:D>=N12,Inventory!D:D<=O12))"),827.4099999999999) -> 827.41 | P14: =IFERROR(__xludf.DUMMYFUNCTION("SUM(FILTER(Inventory!E:E,Inventory!J:J=""Closed"",Inventory!D:D>=P12,Inventory!D:D<=Q12))"),349.70000000000005) -> 349.7 | R14: =IFERROR(__xludf.DUMMYFUNCTION("SUM(FILTER(Inventory!E:E,Inventory!J:J=""Closed"",Inventory!D:D>=R12,Inventory!D:D<=S12))"),723.6) -> 723.6 | T14: =IFERROR(__xludf.DUMMYFUNCTION("SUM(FILTER(Inventory!E:E,Inventory!J:J=""Closed"",Inventory!D:D>=T12,Inventory!D:D<=U12))"),815.9399999999999) -> 815.94 | V14: =IFERROR(__xludf.DUMMYFUNCTION("SUM(FILTER(Inventory!E:E,Inventory!J:J=""Closed"",Inventory!D:D>=V12,Inventory!D:D<=W12))"),891.26) -> 891.26 | X14: =IFERROR(__xludf.DUMMYFUNCTION("SUM(FILTER(Inventory!E:E,Inventory!J:J=""Closed"",Inventory!D:D>=X12,Inventory!D:D<=Y12))"),1090.6700000000005) -> 1090.67
A15: Profit | B15: =IFERROR(__xludf.DUMMYFUNCTION("SUM(FILTER(Inventory!G:G,Inventory!J:J=""Closed"",Inventory!D:D>=B12,Inventory!D:D<=C12))"),109.45) -> 109.45 | D15: =IFERROR(__xludf.DUMMYFUNCTION("SUM(FILTER(Inventory!G:G,Inventory!J:J=""Closed"",Inventory!D:D>=D12,Inventory!D:D<=E12))"),124.24000000000005) -> 124.24 | F15: =IFERROR(__xludf.DUMMYFUNCTION("SUM(FILTER(Inventory!G:G,Inventory!J:J=""Closed"",Inventory!D:D>=F12,Inventory!D:D<=G12))"),141.27999999999997) -> 141.28 | H15: =IFERROR(__xludf.DUMMYFUNCTION("SUM(FILTER(Inventory!G:G,Inventory!J:J=""Closed"",Inventory!D:D>=H12,Inventory!D:D<=I12))"),76.80000000000003) -> 76.8 | J15: =IFERROR(__xludf.DUMMYFUNCTION("SUM(FILTER(Inventory!G:G,Inventory!J:J=""Closed"",Inventory!D:D>=J12,Inventory!D:D<=K12))"),45.35000000000001) -> 45.35 | L15: =IFERROR(__xludf.DUMMYFUNCTION("SUM(FILTER(Inventory!G:G,Inventory!J:J=""Closed"",Inventory!D:D>=L12,Inventory!D:D<=M12))"),220.52999999999994) -> 220.53 | N15: =IFERROR(__xludf.DUMMYFUNCTION("SUM(FILTER(Inventory!G:G,Inventory!J:J=""Closed"",Inventory!D:D>=N12,Inventory!D:D<=O12))"),248.53999999999982) -> 248.54 | P15: =IFERROR(__xludf.DUMMYFUNCTION("SUM(FILTER(Inventory!G:G,Inventory!J:J=""Closed"",Inventory!D:D>=P12,Inventory!D:D<=Q12))"),134.26999999999998) -> 134.27 | R15: =IFERROR(__xludf.DUMMYFUNCTION("SUM(FILTER(Inventory!G:G,Inventory!J:J=""Closed"",Inventory!D:D>=R12,Inventory!D:D<=S12))"),190.50999999999993) -> 190.51 | T15: =IFERROR(__xludf.DUMMYFUNCTION("SUM(FILTER(Inventory!G:G,Inventory!J:J=""Closed"",Inventory!D:D>=T12,Inventory!D:D<=U12))"),229.13999999999993) -> 229.14 | V15: =IFERROR(__xludf.DUMMYFUNCTION("SUM(FILTER(Inventory!G:G,Inventory!J:J=""Closed"",Inventory!D:D>=V12,Inventory!D:D<=W12))"),212.57000000000022) -> 212.57 | X15: =IFERROR(__xludf.DUMMYFUNCTION("SUM(FILTER(Inventory!G:G,Inventory!J:J=""Closed"",Inventory!D:D>=X12,Inventory!D:D<=Y12))"),289.7199999999999) -> 289.72
A16: Sold Items | B16: =COUNTIFS(Inventory!J:J,"Closed", Inventory!D:D,">="&B12,Inventory!D:D,"<="&C12) -> 63 | D16: =COUNTIFS(Inventory!J:J,"Closed", Inventory!D:D,">="&D12,Inventory!D:D,"<="&E12) -> 62 | F16: =COUNTIFS(Inventory!J:J,"Closed", Inventory!D:D,">="&F12,Inventory!D:D,"<="&G12) -> 65 | H16: =COUNTIFS(Inventory!J:J,"Closed", Inventory!D:D,">="&H12,Inventory!D:D,"<="&I12) -> 47 | J16: =COUNTIFS(Inventory!J:J,"Closed", Inventory!D:D,">="&J12,Inventory!D:D,"<="&K12) -> 18 | L16: =COUNTIFS(Inventory!J:J,"Closed", Inventory!D:D,">="&L12,Inventory!D:D,"<="&M12) -> 88 | N16: =COUNTIFS(Inventory!J:J,"Closed", Inventory!D:D,">="&N12,Inventory!D:D,"<="&O12) -> 125 | P16: =COUNTIFS(Inventory!J:J,"Closed", Inventory!D:D,">="&P12,Inventory!D:D,"<="&Q12) -> 56 | R16: =COUNTIFS(Inventory!J:J,"Closed", Inventory!D:D,">="&R12,Inventory!D:D,"<="&S12) -> 71 | T16: =COUNTIFS(Inventory!J:J,"Closed", Inventory!D:D,">="&T12,Inventory!D:D,"<="&U12) -> 100 | V16: =COUNTIFS(Inventory!J:J,"Closed", Inventory!D:D,">="&V12,Inventory!D:D,"<="&W12) -> 152 | X16: =COUNTIFS(Inventory!J:J,"Closed", Inventory!D:D,">="&X12,Inventory!D:D,"<="&Y12) -> 133
A17: ~Sold Price | B17: =IFERROR(__xludf.DUMMYFUNCTION("AVERAGE(FILTER(Inventory!F:F,Inventory!J:J=""Closed"",Inventory!D:D>=B12,Inventory!D:D<=C12))"),5.703968253968254) -> 5.7039683 | D17: =IFERROR(__xludf.DUMMYFUNCTION("AVERAGE(FILTER(Inventory!F:F,Inventory!J:J=""Closed"",Inventory!D:D>=D12,Inventory!D:D<=E12))"),7.790967741935485) -> 7.7909677 | F17: =IFERROR(__xludf.DUMMYFUNCTION("AVERAGE(FILTER(Inventory!F:F,Inventory!J:J=""Closed"",Inventory!D:D>=F12,Inventory!D:D<=G12))"),7.837538461538463) -> 7.8375385 | H17: =IFERROR(__xludf.DUMMYFUNCTION("AVERAGE(FILTER(Inventory!F:F,Inventory!J:J=""Closed"",Inventory!D:D>=H12,Inventory!D:D<=I12))"),7.123617021276597) -> 7.123617 | J17: =IFERROR(__xludf.DUMMYFUNCTION("AVERAGE(FILTER(Inventory!F:F,Inventory!J:J=""Closed"",Inventory!D:D>=J12,Inventory!D:D<=K12))"),8.409444444444444) -> 8.4094444 | L17: =IFERROR(__xludf.DUMMYFUNCTION("AVERAGE(FILTER(Inventory!F:F,Inventory!J:J=""Closed"",Inventory!D:D>=L12,Inventory!D:D<=M12))"),7.803409090909091) -> 7.8034091 | N17: =IFERROR(__xludf.DUMMYFUNCTION("AVERAGE(FILTER(Inventory!F:F,Inventory!J:J=""Closed"",Inventory!D:D>=N12,Inventory!D:D<=O12))"),8.607600000000001) -> 8.6076 | P17: =IFERROR(__xludf.DUMMYFUNCTION("AVERAGE(FILTER(Inventory!F:F,Inventory!J:J=""Closed"",Inventory!D:D>=P12,Inventory!D:D<=Q12))"),8.642321428571432) -> 8.6423214 | R17: =IFERROR(__xludf.DUMMYFUNCTION("AVERAGE(FILTER(Inventory!F:F,Inventory!J:J=""Closed"",Inventory!D:D>=R12,Inventory!D:D<=S12))"),12.874788732394366) -> 12.874789 | T17: =IFERROR(__xludf.DUMMYFUNCTION("AVERAGE(FILTER(Inventory!F:F,Inventory!J:J=""Closed"",Inventory!D:D>=T12,Inventory!D:D<=U12))"),10.4508) -> 10.4508 | V17: =IFERROR(__xludf.DUMMYFUNCTION("AVERAGE(FILTER(Inventory!F:F,Inventory!J:J=""Closed"",Inventory!D:D>=V12,Inventory!D:D<=W12))"),7.2620394736842115) -> 7.2620395 | X17: =IFERROR(__xludf.DUMMYFUNCTION("AVERAGE(FILTER(Inventory!F:F,Inventory!J:J=""Closed"",Inventory!D:D>=X12,Inventory!D:D<=Y12))"),10.378872180451129) -> 10.378872
A18: ~Profit | B18: =IFERROR(__xludf.DUMMYFUNCTION("AVERAGE(FILTER(Inventory!G:G,Inventory!J:J=""Closed"",Inventory!D:D>=B12,Inventory!D:D<=C12))"),1.7373015873015873) -> 1.7373016 | D18: =IFERROR(__xludf.DUMMYFUNCTION("AVERAGE(FILTER(Inventory!G:G,Inventory!J:J=""Closed"",Inventory!D:D>=D12,Inventory!D:D<=E12))"),2.0038709677419364) -> 2.003871 | F18: =IFERROR(__xludf.DUMMYFUNCTION("AVERAGE(FILTER(Inventory!G:G,Inventory!J:J=""Closed"",Inventory!D:D>=F12,Inventory!D:D<=G12))"),2.173538461538461) -> 2.1735385 | H18: =IFERROR(__xludf.DUMMYFUNCTION("AVERAGE(FILTER(Inventory!G:G,Inventory!J:J=""Closed"",Inventory!D:D>=H12,Inventory!D:D<=I12))"),1.63404255319149) -> 1.6340426 | J18: =IFERROR(__xludf.DUMMYFUNCTION("AVERAGE(FILTER(Inventory!G:G,Inventory!J:J=""Closed"",Inventory!D:D>=J12,Inventory!D:D<=K12))"),2.519444444444445) -> 2.5194444 | L18: =IFERROR(__xludf.DUMMYFUNCTION("AVERAGE(FILTER(Inventory!G:G,Inventory!J:J=""Closed"",Inventory!D:D>=L12,Inventory!D:D<=M12))"),2.5060227272727267) -> 2.5060227 | N18: =IFERROR(__xludf.DUMMYFUNCTION("AVERAGE(FILTER(Inventory!G:G,Inventory!J:J=""Closed"",Inventory!D:D>=N12,Inventory!D:D<=O12))"),1.9883199999999985) -> 1.98832 | P18: =IFERROR(__xludf.DUMMYFUNCTION("AVERAGE(FILTER(Inventory!G:G,Inventory!J:J=""Closed"",Inventory!D:D>=P12,Inventory!D:D<=Q12))"),2.397678571428571) -> 2.3976786 | R18: =IFERROR(__xludf.DUMMYFUNCTION("AVERAGE(FILTER(Inventory!G:G,Inventory!J:J=""Closed"",Inventory!D:D>=R12,Inventory!D:D<=S12))"),2.683239436619717) -> 2.6832394 | T18: =IFERROR(__xludf.DUMMYFUNCTION("AVERAGE(FILTER(Inventory!G:G,Inventory!J:J=""Closed"",Inventory!D:D>=T12,Inventory!D:D<=U12))"),2.2913999999999994) -> 2.2914 | V18: =IFERROR(__xludf.DUMMYFUNCTION("AVERAGE(FILTER(Inventory!G:G,Inventory!J:J=""Closed"",Inventory!D:D>=V12,Inventory!D:D<=W12))"),1.3984868421052645) -> 1.3984868 | X18: =IFERROR(__xludf.DUMMYFUNCTION("AVERAGE(FILTER(Inventory!G:G,Inventory!J:J=""Closed"",Inventory!D:D>=X12,Inventory!D:D<=Y12))"),2.1783458646616536) -> 2.1783459
A19: ~Margin | B19: =IFERROR(__xludf.DUMMYFUNCTION("AVERAGE(FILTER(Inventory!H:H,Inventory!J:J=""Closed"",Inventory!D:D>=B12,Inventory!D:D<=C12))"),0.39615872420745) -> 0.39615872 | D19: =IFERROR(__xludf.DUMMYFUNCTION("AVERAGE(FILTER(Inventory!H:H,Inventory!J:J=""Closed"",Inventory!D:D>=D12,Inventory!D:D<=E12))"),0.31651896175352817) -> 0.31651896 | F19: =IFERROR(__xludf.DUMMYFUNCTION("AVERAGE(FILTER(Inventory!H:H,Inventory!J:J=""Closed"",Inventory!D:D>=F12,Inventory!D:D<=G12))"),0.3364384376790562) -> 0.33643844 | H19: =IFERROR(__xludf.DUMMYFUNCTION("AVERAGE(FILTER(Inventory!H:H,Inventory!J:J=""Closed"",Inventory!D:D>=H12,Inventory!D:D<=I12))"),0.2372228933615589) -> 0.23722289 | J19: =IFERROR(__xludf.DUMMYFUNCTION("AVERAGE(FILTER(Inventory!H:H,Inventory!J:J=""Closed"",Inventory!D:D>=J12,Inventory!D:D<=K12))"),0.38786084182359415) -> 0.38786084 | L19: =IFERROR(__xludf.DUMMYFUNCTION("AVERAGE(FILTER(Inventory!H:H,Inventory!J:J=""Closed"",Inventory!D:D>=L12,Inventory!D:D<=M12))"),0.34385336145593187) -> 0.34385336 | N19: =IFERROR(__xludf.DUMMYFUNCTION("AVERAGE(FILTER(Inventory!H:H,Inventory!J:J=""Closed"",Inventory!D:D>=N12,Inventory!D:D<=O12))"),0.3719084297381303) -> 0.37190843 | P19: =IFERROR(__xludf.DUMMYFUNCTION("AVERAGE(FILTER(Inventory!H:H,Inventory!J:J=""Closed"",Inventory!D:D>=P12,Inventory!D:D<=Q12))"),0.08915441228265818) -> 0.089154412 | R19: =IFERROR(__xludf.DUMMYFUNCTION("AVERAGE(FILTER(Inventory!H:H,Inventory!J:J=""Closed"",Inventory!D:D>=R12,Inventory!D:D<=S12))"),0.239561415608409) -> 0.23956142 | T19: =IFERROR(__xludf.DUMMYFUNCTION("AVERAGE(FILTER(Inventory!H:H,Inventory!J:J=""Closed"",Inventory!D:D>=T12,Inventory!D:D<=U12))"),0.32381878394813857) -> 0.32381878 | V19: =IFERROR(__xludf.DUMMYFUNCTION("AVERAGE(FILTER(Inventory!H:H,Inventory!J:J=""Closed"",Inventory!D:D>=V12,Inventory!D:D<=W12))"),0.2557398387120027) -> 0.25573984 | X19: =IFERROR(__xludf.DUMMYFUNCTION("AVERAGE(FILTER(Inventory!H:H,Inventory!J:J=""Closed"",Inventory!D:D>=X12,Inventory!D:D<=Y12))"),-0.260196663792876) -> -0.26019666
A20: ~Duration | B20: =IFERROR(__xludf.DUMMYFUNCTION("AVERAGE(FILTER(Inventory!K:K,Inventory!J:J=""Closed"",Inventory!D:D>=B12,Inventory!D:D<=C12))"),21.11111111111111) -> 21.111111 | D20: =IFERROR(__xludf.DUMMYFUNCTION("AVERAGE(FILTER(Inventory!K:K,Inventory!J:J=""Closed"",Inventory!D:D>=D12,Inventory!D:D<=E12))"),37.25806451612903) -> 37.258065 | F20: =IFERROR(__xludf.DUMMYFUNCTION("AVERAGE(FILTER(Inventory!K:K,Inventory!J:J=""Closed"",Inventory!D:D>=F12,Inventory!D:D<=G12))"),20.907692307692308) -> 20.907692 | H20: =IFERROR(__xludf.DUMMYFUNCTION("AVERAGE(FILTER(Inventory!K:K,Inventory!J:J=""Closed"",Inventory!D:D>=H12,Inventory!D:D<=I12))"),34.97872340425532) -> 34.978723 | J20: =IFERROR(__xludf.DUMMYFUNCTION("AVERAGE(FILTER(Inventory!K:K,Inventory!J:J=""Closed"",Inventory!D:D>=J12,Inventory!D:D<=K12))"),36.55555555555556) -> 36.555556 | L20: =IFERROR(__xludf.DUMMYFUNCTION("AVERAGE(FILTER(Inventory!K:K,Inventory!J:J=""Closed"",Inventory!D:D>=L12,Inventory!D:D<=M12))"),52.71590909090909) -> 52.715909 | N20: =IFERROR(__xludf.DUMMYFUNCTION("AVERAGE(FILTER(Inventory!K:K,Inventory!J:J=""Closed"",Inventory!D:D>=N12,Inventory!D:D<=O12))"),37.544) -> 37.544 | P20: =IFERROR(__xludf.DUMMYFUNCTION("AVERAGE(FILTER(Inventory!K:K,Inventory!J:J=""Closed"",Inventory!D:D>=P12,Inventory!D:D<=Q12))"),33.482142857142854) -> 33.482143 | R20: =IFERROR(__xludf.DUMMYFUNCTION("AVERAGE(FILTER(Inventory!K:K,Inventory!J:J=""Closed"",Inventory!D:D>=R12,Inventory!D:D<=S12))"),26.070422535211268) -> 26.070423 | T20: =IFERROR(__xludf.DUMMYFUNCTION("AVERAGE(FILTER(Inventory!K:K,Inventory!J:J=""Closed"",Inventory!D:D>=T12,Inventory!D:D<=U12))"),15.52) -> 15.52 | V20: =IFERROR(__xludf.DUMMYFUNCTION("AVERAGE(FILTER(Inventory!K:K,Inventory!J:J=""Closed"",Inventory!D:D>=V12,Inventory!D:D<=W12))"),13.921052631578947) -> 13.921053 | X20: =IFERROR(__xludf.DUMMYFUNCTION("AVERAGE(FILTER(Inventory!K:K,Inventory!J:J=""Closed"",Inventory!D:D>=X12,Inventory!D:D<=Y12))"),36.02255639097744) -> 36.022556
A21: Payouts | B21: 3 | D21: 6.5 | F21: 7.5 | H21: 2.5 | J21: 3.5 | L21: 5 | N21: 6.5 | P21: 10 | R21: 6.5 | T21: 10.5 | V21: 6.8 | X21: 13.6
T22: 155 | U22: 976.97 | V22: 158 | W22: 924.93 | X22: 156 | Y22: 1001.63
B23: 44652 | C23: 44681 | D23: 44682 | E23: 44712 | F23: 44713 | G23: 44742 | H23: 44743 | I23: 44773 | J23: 44774 | K23: 44804 | L23: 44805 | M23: 44834 | N23: 44835 | O23: 44865 | P23: 44866 | Q23: 44895 | R23: 44896 | S23: 44926 | T23: 44927 | U23: 44957 | V23: 44958 | W23: 44985 | X23: 44986 | Y23: 45016
A24: Revenue | B24: =IFERROR(__xludf.DUMMYFUNCTION("SUM(FILTER(Inventory!F:F,Inventory!J:J=""Closed"",Inventory!D:D>=B23,Inventory!D:D<=C23))"),1754.4100000000008) -> 1754.41 | D24: =IFERROR(__xludf.DUMMYFUNCTION("SUM(FILTER(Inventory!F:F,Inventory!J:J=""Closed"",Inventory!D:D>=D23,Inventory!D:D<=E23))"),2086.269999999998) -> 2086.27 | F24: =IFERROR(__xludf.DUMMYFUNCTION("SUM(FILTER(Inventory!F:F,Inventory!J:J=""Closed"",Inventory!D:D>=F23,Inventory!D:D<=G23))"),1964.4699999999991) -> 1964.47 | H24: =IFERROR(__xludf.DUMMYFUNCTION("SUM(FILTER(Inventory!F:F,Inventory!J:J=""Closed"",Inventory!D:D>=H23,Inventory!D:D<=I23))"),783.9199999999998) -> 783.92 | J24: =IFERROR(__xludf.DUMMYFUNCTION("SUM(FILTER(Inventory!F:F,Inventory!J:J=""Closed"",Inventory!D:D>=J23,Inventory!D:D<=K23))"),1212.78) -> 1212.78 | L24: =IFERROR(__xludf.DUMMYFUNCTION("SUM(FILTER(Inventory!F:F,Inventory!J:J=""Closed"",Inventory!D:D>=L23,Inventory!D:D<=M23))"),719.3999999999997) -> 719.4 | N24: =IFERROR(__xludf.DUMMYFUNCTION("SUM(FILTER(Inventory!F:F,Inventory!J:J=""Closed"",Inventory!D:D>=N23,Inventory!D:D<=O23))"),1898.6600000000005) -> 1898.66 | P24: =IFERROR(__xludf.DUMMYFUNCTION("SUM(FILTER(Inventory!F:F,Inventory!J:J=""Closed"",Inventory!D:D>=P23,Inventory!D:D<=Q23))"),377.01000000000005) -> 377.01 | R24: =IFERROR(__xludf.DUMMYFUNCTION("SUM(FILTER(Inventory!F:F,Inventory!J:J=""Closed"",Inventory!D:D>=R23,Inventory!D:D<=S23))"),456.25) -> 456.25 | T24: =IFERROR(__xludf.DUMMYFUNCTION("SUM(FILTER(Inventory!F:F,Inventory!J:J=""Closed"",Inventory!D:D>=T23,Inventory!D:D<=U23))"),1381.43) -> 1381.43 | V24: =IFERROR(__xludf.DUMMYFUNCTION("SUM(FILTER(Inventory!F:F,Inventory!J:J=""Closed"",Inventory!D:D>=V23,Inventory!D:D<=W23))"),2157.949999999999) -> 2157.95 | X24: =IFERROR(__xludf.DUMMYFUNCTION("SUM(FILTER(Inventory!F:F,Inventory!J:J=""Closed"",Inventory!D:D>=X23,Inventory!D:D<=Y23))"),1777.0199999999988) -> 1777.02
A25: Expenses | B25: =IFERROR(__xludf.DUMMYFUNCTION("SUM(FILTER(Inventory!E:E,Inventory!J:J=""Closed"",Inventory!D:D>=B23,Inventory!D:D<=C23))"),1294.42) -> 1294.42 | D25: =IFERROR(__xludf.DUMMYFUNCTION("SUM(FILTER(Inventory!E:E,Inventory!J:J=""Closed"",Inventory!D:D>=D23,Inventory!D:D<=E23))"),1652.49) -> 1652.49 | F25: =IFERROR(__xludf.DUMMYFUNCTION("SUM(FILTER(Inventory!E:E,Inventory!J:J=""Closed"",Inventory!D:D>=F23,Inventory!D:D<=G23))"),1387.409999999999) -> 1387.41 | H25: =IFERROR(__xludf.DUMMYFUNCTION("SUM(FILTER(Inventory!E:E,Inventory!J:J=""Closed"",Inventory!D:D>=H23,Inventory!D:D<=I23))"),634.4099999999997) -> 634.41 | J25: =IFERROR(__xludf.DUMMYFUNCTION("SUM(FILTER(Inventory!E:E,Inventory!J:J=""Closed"",Inventory!D:D>=J23,Inventory!D:D<=K23))"),887.8699999999993) -> 887.87 | L25: =IFERROR(__xludf.DUMMYFUNCTION("SUM(FILTER(Inventory!E:E,Inventory!J:J=""Closed"",Inventory!D:D>=L23,Inventory!D:D<=M23))"),582.9000000000002) -> 582.9 | N25: =IFERROR(__xludf.DUMMYFUNCTION("SUM(FILTER(Inventory!E:E,Inventory!J:J=""Closed"",Inventory!D:D>=N23,Inventory!D:D<=O23))"),1549.899999999999) -> 1549.9 | P25: =IFERROR(__xludf.DUMMYFUNCTION("SUM(FILTER(Inventory!E:E,Inventory!J:J=""Closed"",Inventory!D:D>=P23,Inventory!D:D<=Q23))"),257.29999999999995) -> 257.3 | R25: =IFERROR(__xludf.DUMMYFUNCTION("SUM(FILTER(Inventory!E:E,Inventory!J:J=""Closed"",Inventory!D:D>=R23,Inventory!D:D<=S23))"),309.05999999999995) -> 309.06 | T25: =IFERROR(__xludf.DUMMYFUNCTION("SUM(FILTER(Inventory!E:E,Inventory!J:J=""Closed"",Inventory!D:D>=T23,Inventory!D:D<=U23))"),1049.0600000000004) -> 1049.06 | V25: =IFERROR(__xludf.DUMMYFUNCTION("SUM(FILTER(Inventory!E:E,Inventory!J:J=""Closed"",Inventory!D:D>=V23,Inventory!D:D<=W23))"),1718.5100000000027) -> 1718.51 | X25: =IFERROR(__xludf.DUMMYFUNCTION("SUM(FILTER(Inventory!E:E,Inventory!J:J=""Closed"",Inventory!D:D>=X23,Inventory!D:D<=Y23))"),1369.8999999999996) -> 1369.9
A26: Profit | B26: =IFERROR(__xludf.DUMMYFUNCTION("SUM(FILTER(Inventory!G:G,Inventory!J:J=""Closed"",Inventory!D:D>=B23,Inventory!D:D<=C23))"),459.98999999999984) -> 459.99 | D26: =IFERROR(__xludf.DUMMYFUNCTION("SUM(FILTER(Inventory!G:G,Inventory!J:J=""Closed"",Inventory!D:D>=D23,Inventory!D:D<=E23))"),433.7800000000001) -> 433.78 | F26: =IFERROR(__xludf.DUMMYFUNCTION("SUM(FILTER(Inventory!G:G,Inventory!J:J=""Closed"",Inventory!D:D>=F23,Inventory!D:D<=G23))"),577.06) -> 577.06 | H26: =IFERROR(__xludf.DUMMYFUNCTION("SUM(FILTER(Inventory!G:G,Inventory!J:J=""Closed"",Inventory!D:D>=H23,Inventory!D:D<=I23))"),149.5100000000001) -> 149.51 | J26: =IFERROR(__xludf.DUMMYFUNCTION("SUM(FILTER(Inventory!G:G,Inventory!J:J=""Closed"",Inventory!D:D>=J23,Inventory!D:D<=K23))"),324.91) -> 324.91 | L26: =IFERROR(__xludf.DUMMYFUNCTION("SUM(FILTER(Inventory!G:G,Inventory!J:J=""Closed"",Inventory!D:D>=L23,Inventory!D:D<=M23))"),136.49999999999997) -> 136.5 | N26: =IFERROR(__xludf.DUMMYFUNCTION("SUM(FILTER(Inventory!G:G,Inventory!J:J=""Closed"",Inventory!D:D>=N23,Inventory!D:D<=O23))"),348.76000000000016) -> 348.76 | P26: =IFERROR(__xludf.DUMMYFUNCTION("SUM(FILTER(Inventory!G:G,Inventory!J:J=""Closed"",Inventory!D:D>=P23,Inventory!D:D<=Q23))"),119.70999999999998) -> 119.71 | R26: =IFERROR(__xludf.DUMMYFUNCTION("SUM(FILTER(Inventory!G:G,Inventory!J:J=""Closed"",Inventory!D:D>=R23,Inventory!D:D<=S23))"),147.19000000000003) -> 147.19 | T26: =IFERROR(__xludf.DUMMYFUNCTION("SUM(FILTER(Inventory!G:G,Inventory!J:J=""Closed"",Inventory!D:D>=T23,Inventory!D:D<=U23))"),332.36999999999995) -> 332.37 | V26: =IFERROR(__xludf.DUMMYFUNCTION("SUM(FILTER(Inventory!G:G,Inventory!J:J=""Closed"",Inventory!D:D>=V23,Inventory!D:D<=W23))"),439.44000000000045) -> 439.44 | X26: =IFERROR(__xludf.DUMMYFUNCTION("SUM(FILTER(Inventory!G:G,Inventory!J:J=""Closed"",Inventory!D:D>=X23,Inventory!D:D<=Y23))"),407.11999999999983) -> 407.12
A27: Sold Items | B27: =COUNTIFS(Inventory!J:J,"Closed", Inventory!D:D,">="&B23,Inventory!D:D,"<="&C23) -> 163 | D27: =COUNTIFS(Inventory!J:J,"Closed", Inventory!D:D,">="&D23,Inventory!D:D,"<="&E23) -> 210 | F27: =COUNTIFS(Inventory!J:J,"Closed", Inventory!D:D,">="&F23,Inventory!D:D,"<="&G23) -> 150 | H27: =COUNTIFS(Inventory!J:J,"Closed", Inventory!D:D,">="&H23,Inventory!D:D,"<="&I23) -> 66 | J27: =COUNTIFS(Inventory!J:J,"Closed", Inventory!D:D,">="&J23,Inventory!D:D,"<="&K23) -> 69 | L27: =COUNTIFS(Inventory!J:J,"Closed", Inventory!D:D,">="&L23,Inventory!D:D,"<="&M23) -> 68 | N27: =COUNTIFS(Inventory!J:J,"Closed", Inventory!D:D,">="&N23,Inventory!D:D,"<="&O23) -> 80 | P27: =COUNTIFS(Inventory!J:J,"Closed", Inventory!D:D,">="&P23,Inventory!D:D,"<="&Q23) -> 29 | R27: =COUNTIFS(Inventory!J:J,"Closed", Inventory!D:D,">="&R23,Inventory!D:D,"<="&S23) -> 32 | T27: =COUNTIFS(Inventory!J:J,"Closed", Inventory!D:D,">="&T23,Inventory!D:D,"<="&U23) -> 78 | V27: =COUNTIFS(Inventory!J:J,"Closed", Inventory!D:D,">="&V23,Inventory!D:D,"<="&W23) -> 186 | X27: =COUNTIFS(Inventory!J:J,"Closed", Inventory!D:D,">="&X23,Inventory!D:D,"<="&Y23) -> 191
A28: ~Sold Price | B28: =IFERROR(__xludf.DUMMYFUNCTION("AVERAGE(FILTER(Inventory!F:F,Inventory!J:J=""Closed"",Inventory!D:D>=B23,Inventory!D:D<=C23))"),10.763251533742336) -> 10.763252 | D28: =IFERROR(__xludf.DUMMYFUNCTION("AVERAGE(FILTER(Inventory!F:F,Inventory!J:J=""Closed"",Inventory!D:D>=D23,Inventory!D:D<=E23))"),9.934619047619039) -> 9.934619 | F28: =IFERROR(__xludf.DUMMYFUNCTION("AVERAGE(FILTER(Inventory!F:F,Inventory!J:J=""Closed"",Inventory!D:D>=F23,Inventory!D:D<=G23))"),13.096466666666661) -> 13.096467 | H28: =IFERROR(__xludf.DUMMYFUNCTION("AVERAGE(FILTER(Inventory!F:F,Inventory!J:J=""Closed"",Inventory!D:D>=H23,Inventory!D:D<=I23))"),11.877575757575755) -> 11.877576 | J28: =IFERROR(__xludf.DUMMYFUNCTION("AVERAGE(FILTER(Inventory!F:F,Inventory!J:J=""Closed"",Inventory!D:D>=J23,Inventory!D:D<=K23))"),17.576521739130435) -> 17.576522 | L28: =IFERROR(__xludf.DUMMYFUNCTION("AVERAGE(FILTER(Inventory!F:F,Inventory!J:J=""Closed"",Inventory!D:D>=L23,Inventory!D:D<=M23))"),10.57941176470588) -> 10.579412 | N28: =IFERROR(__xludf.DUMMYFUNCTION("AVERAGE(FILTER(Inventory!F:F,Inventory!J:J=""Closed"",Inventory!D:D>=N23,Inventory!D:D<=O23))"),23.733250000000005) -> 23.73325 | P28: =IFERROR(__xludf.DUMMYFUNCTION("AVERAGE(FILTER(Inventory!F:F,Inventory!J:J=""Closed"",Inventory!D:D>=P23,Inventory!D:D<=Q23))"),13.000344827586208) -> 13.000345 | R28: =IFERROR(__xludf.DUMMYFUNCTION("AVERAGE(FILTER(Inventory!F:F,Inventory!J:J=""Closed"",Inventory!D:D>=R23,Inventory!D:D<=S23))"),14.2578125) -> 14.257812 | T28: =IFERROR(__xludf.DUMMYFUNCTION("AVERAGE(FILTER(Inventory!F:F,Inventory!J:J=""Closed"",Inventory!D:D>=T23,Inventory!D:D<=U23))"),17.710641025641028) -> 17.710641 | V28: =IFERROR(__xludf.DUMMYFUNCTION("AVERAGE(FILTER(Inventory!F:F,Inventory!J:J=""Closed"",Inventory!D:D>=V23,Inventory!D:D<=W23))"),11.601881720430102) -> 11.601882 | X28: =IFERROR(__xludf.DUMMYFUNCTION("AVERAGE(FILTER(Inventory!F:F,Inventory!J:J=""Closed"",Inventory!D:D>=X23,Inventory!D:D<=Y23))"),9.303769633507848) -> 9.3037696
A29: ~Profit | B29: =IFERROR(__xludf.DUMMYFUNCTION("AVERAGE(FILTER(Inventory!G:G,Inventory!J:J=""Closed"",Inventory!D:D>=B23,Inventory!D:D<=C23))"),2.8220245398772996) -> 2.8220245 | D29: =IFERROR(__xludf.DUMMYFUNCTION("AVERAGE(FILTER(Inventory!G:G,Inventory!J:J=""Closed"",Inventory!D:D>=D23,Inventory!D:D<=E23))"),2.065619047619048) -> 2.065619 | F29: =IFERROR(__xludf.DUMMYFUNCTION("AVERAGE(FILTER(Inventory!G:G,Inventory!J:J=""Closed"",Inventory!D:D>=F23,Inventory!D:D<=G23))"),3.847066666666666) -> 3.8470667 | H29: =IFERROR(__xludf.DUMMYFUNCTION("AVERAGE(FILTER(Inventory!G:G,Inventory!J:J=""Closed"",Inventory!D:D>=H23,Inventory!D:D<=I23))"),2.265303030303032) -> 2.265303 | J29: =IFERROR(__xludf.DUMMYFUNCTION("AVERAGE(FILTER(Inventory!G:G,Inventory!J:J=""Closed"",Inventory!D:D>=J23,Inventory!D:D<=K23))"),4.708840579710145) -> 4.7088406 | L29: =IFERROR(__xludf.DUMMYFUNCTION("AVERAGE(FILTER(Inventory!G:G,Inventory!J:J=""Closed"",Inventory!D:D>=L23,Inventory!D:D<=M23))"),2.00735294117647) -> 2.0073529 | N29: =IFERROR(__xludf.DUMMYFUNCTION("AVERAGE(FILTER(Inventory!G:G,Inventory!J:J=""Closed"",Inventory!D:D>=N23,Inventory!D:D<=O23))"),4.359500000000002) -> 4.3595 | P29: =IFERROR(__xludf.DUMMYFUNCTION("AVERAGE(FILTER(Inventory!G:G,Inventory!J:J=""Closed"",Inventory!D:D>=P23,Inventory!D:D<=Q23))"),4.127931034482758) -> 4.127931 | R29: =IFERROR(__xludf.DUMMYFUNCTION("AVERAGE(FILTER(Inventory!G:G,Inventory!J:J=""Closed"",Inventory!D:D>=R23,Inventory!D:D<=S23))"),4.599687500000001) -> 4.5996875 | T29: =IFERROR(__xludf.DUMMYFUNCTION("AVERAGE(FILTER(Inventory!G:G,Inventory!J:J=""Closed"",Inventory!D:D>=T23,Inventory!D:D<=U23))"),4.261153846153846) -> 4.2611538 | V29: =IFERROR(__xludf.DUMMYFUNCTION("AVERAGE(FILTER(Inventory!G:G,Inventory!J:J=""Closed"",Inventory!D:D>=V23,Inventory!D:D<=W23))"),2.3625806451612927) -> 2.3625806 | X29: =IFERROR(__xludf.DUMMYFUNCTION("AVERAGE(FILTER(Inventory!G:G,Inventory!J:J=""Closed"",Inventory!D:D>=X23,Inventory!D:D<=Y23))"),2.131518324607329) -> 2.1315183
A30: ~Margin | B30: =(B26/B24)*100 -> 26.219071 | D30: =(D26/D24)*100 -> 20.792131 | F30: =(F26/F24)*100 -> 29.374844 | H30: =(H26/H24)*100 -> 19.072099 | J30: =(J26/J24)*100 -> 26.790514 | L30: =(L26/L24)*100 -> 18.974145 | N30: =(N26/N24)*100 -> 18.368744 | P30: =(P26/P24)*100 -> 31.752473 | R30: =(R26/R24)*100 -> 32.260822 | T30: =(T26/T24)*100 -> 24.059851 | V30: =(V26/V24)*100 -> 20.363771 | X30: =(X26/X24)*100 -> 22.910266
A31: ~Duration | B31: =IFERROR(__xludf.DUMMYFUNCTION("AVERAGE(FILTER(Inventory!K:K,Inventory!J:J=""Closed"",Inventory!D:D>=B23,Inventory!D:D<=C23))"),28.141104294478527) -> 28.141104 | D31: =IFERROR(__xludf.DUMMYFUNCTION("AVERAGE(FILTER(Inventory!K:K,Inventory!J:J=""Closed"",Inventory!D:D>=D23,Inventory!D:D<=E23))"),24.347619047619048) -> 24.347619 | F31: =IFERROR(__xludf.DUMMYFUNCTION("AVERAGE(FILTER(Inventory!K:K,Inventory!J:J=""Closed"",Inventory!D:D>=F23,Inventory!D:D<=G23))"),30.233333333333334) -> 30.233333 | H31: =IFERROR(__xludf.DUMMYFUNCTION("AVERAGE(FILTER(Inventory!K:K,Inventory!J:J=""Closed"",Inventory!D:D>=H23,Inventory!D:D<=I23))"),44.56060606060606) -> 44.560606 | J31: =IFERROR(__xludf.DUMMYFUNCTION("AVERAGE(FILTER(Inventory!K:K,Inventory!J:J=""Closed"",Inventory!D:D>=J23,Inventory!D:D<=K23))"),24.782608695652176) -> 24.782609 | L31: =IFERROR(__xludf.DUMMYFUNCTION("AVERAGE(FILTER(Inventory!K:K,Inventory!J:J=""Closed"",Inventory!D:D>=L23,Inventory!D:D<=M23))"),66.8529411764706) -> 66.852941 | N31: =IFERROR(__xludf.DUMMYFUNCTION("AVERAGE(FILTER(Inventory!K:K,Inventory!J:J=""Closed"",Inventory!D:D>=N23,Inventory!D:D<=O23))"),48.2625) -> 48.2625 | P31: =IFERROR(__xludf.DUMMYFUNCTION("AVERAGE(FILTER(Inventory!K:K,Inventory!J:J=""Closed"",Inventory!D:D>=P23,Inventory!D:D<=Q23))"),41.48275862068966) -> 41.482759 | R31: =IFERROR(__xludf.DUMMYFUNCTION("AVERAGE(FILTER(Inventory!K:K,Inventory!J:J=""Closed"",Inventory!D:D>=R23,Inventory!D:D<=S23))"),30.34375) -> 30.34375 | T31: =IFERROR(__xludf.DUMMYFUNCTION("AVERAGE(FILTER(Inventory!K:K,Inventory!J:J=""Closed"",Inventory!D:D>=T23,Inventory!D:D<=U23))"),42.57692307692308) -> 42.576923 | V31: =IFERROR(__xludf.DUMMYFUNCTION("AVERAGE(FILTER(Inventory!K:K,Inventory!J:J=""Closed"",Inventory!D:D>=V23,Inventory!D:D<=W23))"),22.822580645161292) -> 22.822581 | X31: =IFERROR(__xludf.DUMMYFUNCTION("AVERAGE(FILTER(Inventory!K:K,Inventory!J:J=""Closed"",Inventory!D:D>=X23,Inventory!D:D<=Y23))"),28.13612565445026) -> 28.136126
A32: Payouts | B32: 14.2 | D32: 17.6 | F32: 20.6 | H32: 13.5 | J32: 13.3 | L32: 7.2 | N32: 13.8 | P32: 4 | R32: 7 | T32: 11 | V32: 13.6 | X32: 22.6
B33: 159 | C33: 1130.77 | D33: 148 | E33: 1085.33 | F33: 168 | G33: 1342.71 | H33: 163 | I33: 1470.62 | J33: 171 | K33: 1521.14 | L33: 159 | M33: 1497.7 | N33: 148 | O33: 1375.36 | P33: 166 | Q33: 1493.75 | R33: 169 | S33: 1591.76 | T33: 179 | U33: 1690.41 | V33: 179 | W33: 1784.18 | X33: 192 | Y33: 2211.33
B35: 45017 | C35: 45046 | D35: 45047 | E35: 45077 | F35: 45078 | G35: 45107 | H35: 45108 | I35: 45138 | J35: 45139 | K35: 45169 | L35: 45170 | M35: 45199 | N35: 45200 | O35: 45230 | P35: 45231 | Q35: 45260 | R35: 45261 | S35: 45291 | T35: 45292 | U35: 45322 | V35: 45323 | W35: 45351 | X35: 45352 | Y35: 45382
A36: Revenue | B36: =IFERROR(__xludf.DUMMYFUNCTION("SUM(FILTER(Inventory!F:F,Inventory!J:J=""Closed"",Inventory!D:D>=B35,Inventory!D:D<=C35))"),2221.793000000001) -> 2221.793 | D36: =IFERROR(__xludf.DUMMYFUNCTION("SUM(FILTER(Inventory!F:F,Inventory!J:J=""Closed"",Inventory!D:D>=D35,Inventory!D:D<=E35))"),1843.640000000001) -> 1843.64 | F36: =IFERROR(__xludf.DUMMYFUNCTION("SUM(FILTER(Inventory!F:F,Inventory!J:J=""Closed"",Inventory!D:D>=F35,Inventory!D:D<=G35))"),3064.2099999999978) -> 3064.21 | H36: =IFERROR(__xludf.DUMMYFUNCTION("SUM(FILTER(Inventory!F:F,Inventory!J:J=""Closed"",Inventory!D:D>=H35,Inventory!D:D<=I35))"),2253.6899999999987) -> 2253.69 | J36: =IFERROR(__xludf.DUMMYFUNCTION("SUM(FILTER(Inventory!F:F,Inventory!J:J=""Closed"",Inventory!D:D>=J35,Inventory!D:D<=K35))"),1972.5280000000052) -> 1972.528 | L36: =IFERROR(__xludf.DUMMYFUNCTION("SUM(FILTER(Inventory!F:F,Inventory!J:J=""Closed"",Inventory!D:D>=Summary!L35,Inventory!D:D<=Summary!M35))"),3439.569999999998) -> 3439.57 | N36: =IFERROR(__xludf.DUMMYFUNCTION("SUM(FILTER(Inventory!F:F,Inventory!J:J=""Closed"",Inventory!D:D>=Summary!N35,Inventory!D:D<=Summary!O35))"),4214.390000000001) -> 4214.39 | P36: =IFERROR(__xludf.DUMMYFUNCTION("SUM(FILTER(Inventory!F:F,Inventory!J:J=""Closed"",Inventory!D:D>=Summary!P35,Inventory!D:D<=Summary!Q35))"),4548.4000000000015) -> 4548.4 | R36: =IFERROR(__xludf.DUMMYFUNCTION("SUM(FILTER(Inventory!F:F,Inventory!J:J=""Closed"",Inventory!D:D>=Summary!R35,Inventory!D:D<=Summary!S35))"),1484.2699999999986) -> 1484.27 | T36: =IFERROR(__xludf.DUMMYFUNCTION("SUM(FILTER(Inventory!F:F,Inventory!J:J=""Closed"",Inventory!D:D>=Summary!T35,Inventory!D:D<=Summary!U35))"),1216.7800000000002) -> 1216.78 | V36: =IFERROR(__xludf.DUMMYFUNCTION("SUM(FILTER(Inventory!F:F,Inventory!J:J=""Closed"",Inventory!D:D>=Summary!V35,Inventory!D:D<=Summary!W35))"),2750.27) -> 2750.27 | X36: =IFERROR(__xludf.DUMMYFUNCTION("SUM(FILTER(Inventory!F:F,Inventory!J:J=""Closed"",Inventory!D:D>=Summary!X35,Inventory!D:D<=Summary!Y35))"),3520.529999999998) -> 3520.53
A37: Expenses | B37: =IFERROR(__xludf.DUMMYFUNCTION("SUM(FILTER(Inventory!E:E,Inventory!J:J=""Closed"",Inventory!D:D>=B35,Inventory!D:D<=C35))"),1629.9499999999994) -> 1629.95 | D37: =IFERROR(__xludf.DUMMYFUNCTION("SUM(FILTER(Inventory!E:E,Inventory!J:J=""Closed"",Inventory!D:D>=D35,Inventory!D:D<=E35))"),1370.7999999999993) -> 1370.8 | F37: =IFERROR(__xludf.DUMMYFUNCTION("SUM(FILTER(Inventory!E:E,Inventory!J:J=""Closed"",Inventory!D:D>=F35,Inventory!D:D<=G35))"),2433.6799999999976) -> 2433.68 | H37: =IFERROR(__xludf.DUMMYFUNCTION("SUM(FILTER(Inventory!E:E,Inventory!J:J=""Closed"",Inventory!D:D>=H35,Inventory!D:D<=I35))"),1815.3400000000017) -> 1815.34 | J37: =IFERROR(__xludf.DUMMYFUNCTION("SUM(FILTER(Inventory!E:E,Inventory!J:J=""Closed"",Inventory!D:D>=J35,Inventory!D:D<=K35))"),1596.0600000000024) -> 1596.06 | L37: =IFERROR(__xludf.DUMMYFUNCTION("SUM(FILTER(Inventory!E:E,Inventory!J:J=""Closed"",Inventory!D:D>=Summary!L35,Inventory!D:D<=Summary!M35))"),2842.5899999999983) -> 2842.59 | N37: =IFERROR(__xludf.DUMMYFUNCTION("SUM(FILTER(Inventory!E:E,Inventory!J:J=""Closed"",Inventory!D:D>=Summary!N35,Inventory!D:D<=Summary!O35))"),3442.0199999999977) -> 3442.02 | P37: =IFERROR(__xludf.DUMMYFUNCTION("SUM(FILTER(Inventory!E:E,Inventory!J:J=""Closed"",Inventory!D:D>=Summary!P35,Inventory!D:D<=Summary!Q35))"),3596.229999999999) -> 3596.23 | R37: =IFERROR(__xludf.DUMMYFUNCTION("SUM(FILTER(Inventory!E:E,Inventory!J:J=""Closed"",Inventory!D:D>=Summary!R35,Inventory!D:D<=Summary!S35))"),1085.7900000000025) -> 1085.79 | T37: =IFERROR(__xludf.DUMMYFUNCTION("SUM(FILTER(Inventory!E:E,Inventory!J:J=""Closed"",Inventory!D:D>=Summary!T35,Inventory!D:D<=Summary!U35))"),992.3199999999999) -> 992.32 | V37: =IFERROR(__xludf.DUMMYFUNCTION("SUM(FILTER(Inventory!E:E,Inventory!J:J=""Closed"",Inventory!D:D>=Summary!V35,Inventory!D:D<=Summary!W35))"),2304.54) -> 2304.54 | X37: =IFERROR(__xludf.DUMMYFUNCTION("SUM(FILTER(Inventory!E:E,Inventory!J:J=""Closed"",Inventory!D:D>=Summary!X35,Inventory!D:D<=Summary!Y35))"),2859.3000000000006) -> 2859.3
A38: Profit | B38: =IFERROR(__xludf.DUMMYFUNCTION("SUM(FILTER(Inventory!G:G,Inventory!J:J=""Closed"",Inventory!D:D>=B35,Inventory!D:D<=C35))"),591.8429999999997) -> 591.843 | D38: =IFERROR(__xludf.DUMMYFUNCTION("SUM(FILTER(Inventory!G:G,Inventory!J:J=""Closed"",Inventory!D:D>=D35,Inventory!D:D<=E35))"),472.8400000000005) -> 472.84 | F38: =IFERROR(__xludf.DUMMYFUNCTION("SUM(FILTER(Inventory!G:G,Inventory!J:J=""Closed"",Inventory!D:D>=F35,Inventory!D:D<=G35))"),630.5300000000002) -> 630.53 | H38: =IFERROR(__xludf.DUMMYFUNCTION("SUM(FILTER(Inventory!G:G,Inventory!J:J=""Closed"",Inventory!D:D>=H35,Inventory!D:D<=I35))"),438.3499999999995) -> 438.35 | J38: =IFERROR(__xludf.DUMMYFUNCTION("SUM(FILTER(Inventory!G:G,Inventory!J:J=""Closed"",Inventory!D:D>=J35,Inventory!D:D<=K35))"),376.4680000000002) -> 376.468 | L38: =IFERROR(__xludf.DUMMYFUNCTION("SUM(FILTER(Inventory!G:G,Inventory!J:J=""Closed"",Inventory!D:D>=L35,Inventory!D:D<=M35))"),596.9799999999999) -> 596.98 | N38: =IFERROR(__xludf.DUMMYFUNCTION("SUM(FILTER(Inventory!G:G,Inventory!J:J=""Closed"",Inventory!D:D>=N35,Inventory!D:D<=O35))"),772.3700000000008) -> 772.37 | P38: =IFERROR(__xludf.DUMMYFUNCTION("SUM(FILTER(Inventory!G:G,Inventory!J:J=""Closed"",Inventory!D:D>=P35,Inventory!D:D<=Q35))"),952.1700000000001) -> 952.17 | R38: =IFERROR(__xludf.DUMMYFUNCTION("SUM(FILTER(Inventory!G:G,Inventory!J:J=""Closed"",Inventory!D:D>=R35,Inventory!D:D<=S35))"),398.4799999999999) -> 398.48 | T38: =IFERROR(__xludf.DUMMYFUNCTION("SUM(FILTER(Inventory!G:G,Inventory!J:J=""Closed"",Inventory!D:D>=T35,Inventory!D:D<=U35))"),224.45999999999992) -> 224.46 | V38: =IFERROR(__xludf.DUMMYFUNCTION("SUM(FILTER(Inventory!G:G,Inventory!J:J=""Closed"",Inventory!D:D>=V35,Inventory!D:D<=W35))"),445.72999999999996) -> 445.73 | X38: =IFERROR(__xludf.DUMMYFUNCTION("SUM(FILTER(Inventory!G:G,Inventory!J:J=""Closed"",Inventory!D:D>=X35,Inventory!D:D<=Y35))"),661.2299999999997) -> 661.23
A39: Sold Items | B39: =COUNTIFS(Inventory!J:J,"Closed", Inventory!D:D,">="&B35,Inventory!D:D,"<="&C35) -> 187 | D39: =COUNTIFS(Inventory!J:J,"Closed", Inventory!D:D,">="&D35,Inventory!D:D,"<="&E35) -> 136 | F39: =COUNTIFS(Inventory!J:J,"Closed", Inventory!D:D,">="&F35,Inventory!D:D,"<="&G35) -> 163 | H39: =COUNTIFS(Inventory!J:J,"Closed", Inventory!D:D,">="&H35,Inventory!D:D,"<="&I35) -> 184 | J39: =COUNTIFS(Inventory!J:J,"Closed", Inventory!D:D,">="&J35,Inventory!D:D,"<="&K35) -> 280 | L39: =COUNTIFS(Inventory!J:J,"Closed", Inventory!D:D,">="&L35,Inventory!D:D,"<="&M35) -> 242 | N39: =COUNTIFS(Inventory!J:J,"Closed", Inventory!D:D,">="&N35,Inventory!D:D,"<="&O35) -> 251 | P39: =COUNTIFS(Inventory!J:J,"Closed", Inventory!D:D,">="&P35,Inventory!D:D,"<="&Q35) -> 283 | R39: =COUNTIFS(Inventory!J:J,"Closed", Inventory!D:D,">="&R35,Inventory!D:D,"<="&S35) -> 124 | T39: =COUNTIFS(Inventory!J:J,"Closed", Inventory!D:D,">="&T35,Inventory!D:D,"<="&U35) -> 87 | V39: =COUNTIFS(Inventory!J:J,"Closed", Inventory!D:D,">="&V35,Inventory!D:D,"<="&W35) -> 122 | X39: =COUNTIFS(Inventory!J:J,"Closed", Inventory!D:D,">="&X35,Inventory!D:D,"<="&Y35) -> 187
A40: ~Sold Price | B40: =IFERROR(__xludf.DUMMYFUNCTION("AVERAGE(FILTER(Inventory!F:F,Inventory!J:J=""Closed"",Inventory!D:D>=B35,Inventory!D:D<=C35))"),11.881245989304817) -> 11.881246 | D40: =IFERROR(__xludf.DUMMYFUNCTION("AVERAGE(FILTER(Inventory!F:F,Inventory!J:J=""Closed"",Inventory!D:D>=D35,Inventory!D:D<=E35))"),13.556176470588243) -> 13.556176 | F40: =IFERROR(__xludf.DUMMYFUNCTION("AVERAGE(FILTER(Inventory!F:F,Inventory!J:J=""Closed"",Inventory!D:D>=F35,Inventory!D:D<=G35))"),18.798834355828205) -> 18.798834 | H40: =IFERROR(__xludf.DUMMYFUNCTION("AVERAGE(FILTER(Inventory!F:F,Inventory!J:J=""Closed"",Inventory!D:D>=H35,Inventory!D:D<=I35))"),12.248315217391298) -> 12.248315 | J40: =IFERROR(__xludf.DUMMYFUNCTION("AVERAGE(FILTER(Inventory!F:F,Inventory!J:J=""Closed"",Inventory!D:D>=J35,Inventory!D:D<=K35))"),7.044742857142876) -> 7.0447429 | L40: =IFERROR(__xludf.DUMMYFUNCTION("AVERAGE(FILTER(Inventory!F:F,Inventory!J:J=""Closed"",Inventory!D:D>=L35,Inventory!D:D<=M35))"),14.21309917355371) -> 14.213099 | N40: =IFERROR(__xludf.DUMMYFUNCTION("AVERAGE(FILTER(Inventory!F:F,Inventory!J:J=""Closed"",Inventory!D:D>=N35,Inventory!D:D<=O35))"),16.790398406374507) -> 16.790398 | P40: =IFERROR(__xludf.DUMMYFUNCTION("AVERAGE(FILTER(Inventory!F:F,Inventory!J:J=""Closed"",Inventory!D:D>=P35,Inventory!D:D<=Q35))"),16.072084805653716) -> 16.072085 | R40: =IFERROR(__xludf.DUMMYFUNCTION("AVERAGE(FILTER(Inventory!F:F,Inventory!J:J=""Closed"",Inventory!D:D>=R35,Inventory!D:D<=S35))"),11.969919354838698) -> 11.969919 | T40: =IFERROR(__xludf.DUMMYFUNCTION("AVERAGE(FILTER(Inventory!F:F,Inventory!J:J=""Closed"",Inventory!D:D>=T35,Inventory!D:D<=U35))"),13.985977011494255) -> 13.985977 | V40: =IFERROR(__xludf.DUMMYFUNCTION("AVERAGE(FILTER(Inventory!F:F,Inventory!J:J=""Closed"",Inventory!D:D>=V35,Inventory!D:D<=W35))"),22.543196721311475) -> 22.543197 | X40: =IFERROR(__xludf.DUMMYFUNCTION("AVERAGE(FILTER(Inventory!F:F,Inventory!J:J=""Closed"",Inventory!D:D>=X35,Inventory!D:D<=Y35))"),18.826363636363624) -> 18.826364
A41: ~Profit | B41: =IFERROR(__xludf.DUMMYFUNCTION("AVERAGE(FILTER(Inventory!G:G,Inventory!J:J=""Closed"",Inventory!D:D>=B35,Inventory!D:D<=C35))"),3.1649358288770038) -> 3.1649358 | D41: =IFERROR(__xludf.DUMMYFUNCTION("AVERAGE(FILTER(Inventory!G:G,Inventory!J:J=""Closed"",Inventory!D:D>=D35,Inventory!D:D<=E35))"),3.4767647058823563) -> 3.4767647 | F41: =IFERROR(__xludf.DUMMYFUNCTION("AVERAGE(FILTER(Inventory!G:G,Inventory!J:J=""Closed"",Inventory!D:D>=F35,Inventory!D:D<=G35))"),3.8682822085889583) -> 3.8682822 | H41: =IFERROR(__xludf.DUMMYFUNCTION("AVERAGE(FILTER(Inventory!G:G,Inventory!J:J=""Closed"",Inventory!D:D>=H35,Inventory!D:D<=I35))"),2.3823369565217365) -> 2.382337 | J41: =IFERROR(__xludf.DUMMYFUNCTION("AVERAGE(FILTER(Inventory!G:G,Inventory!J:J=""Closed"",Inventory!D:D>=J35,Inventory!D:D<=K35))"),1.3445285714285722) -> 1.3445286 | L41: =IFERROR(__xludf.DUMMYFUNCTION("AVERAGE(FILTER(Inventory!G:G,Inventory!J:J=""Closed"",Inventory!D:D>=L35,Inventory!D:D<=M35))"),2.466859504132231) -> 2.4668595 | N41: =IFERROR(__xludf.DUMMYFUNCTION("AVERAGE(FILTER(Inventory!G:G,Inventory!J:J=""Closed"",Inventory!D:D>=N35,Inventory!D:D<=O35))"),3.077171314741039) -> 3.0771713 | P41: =IFERROR(__xludf.DUMMYFUNCTION("AVERAGE(FILTER(Inventory!G:G,Inventory!J:J=""Closed"",Inventory!D:D>=P35,Inventory!D:D<=Q35))"),3.364558303886926) -> 3.3645583 | R41: =IFERROR(__xludf.DUMMYFUNCTION("AVERAGE(FILTER(Inventory!G:G,Inventory!J:J=""Closed"",Inventory!D:D>=R35,Inventory!D:D<=S35))"),3.2135483870967736) -> 3.2135484 | T41: =IFERROR(__xludf.DUMMYFUNCTION("AVERAGE(FILTER(Inventory!G:G,Inventory!J:J=""Closed"",Inventory!D:D>=T35,Inventory!D:D<=U35))"),2.579999999999999) -> 2.58 | V41: =IFERROR(__xludf.DUMMYFUNCTION("AVERAGE(FILTER(Inventory!G:G,Inventory!J:J=""Closed"",Inventory!D:D>=V35,Inventory!D:D<=W35))"),3.653524590163934) -> 3.6535246 | X41: =IFERROR(__xludf.DUMMYFUNCTION("AVERAGE(FILTER(Inventory!G:G,Inventory!J:J=""Closed"",Inventory!D:D>=X35,Inventory!D:D<=Y35))"),3.5359893048128326) -> 3.5359893
A42: ~Margin | B42: =(B38/B36)*100 -> 26.63808 | D42: =(D38/D36)*100 -> 25.647089 | F42: =(F38/F36)*100 -> 20.577245 | H42: =(H38/H36)*100 -> 19.450324 | J42: =(J38/J36)*100 -> 19.085559 | L42: =(L38/L36)*100 -> 17.356239 | N42: =(N38/N36)*100 -> 18.32697 | P42: =(P38/P36)*100 -> 20.934175 | R42: =(R38/R36)*100 -> 26.846867 | T42: =(T38/T36)*100 -> 18.447049 | V42: =(V38/V36)*100 -> 16.206772 | X42: =(X38/X36)*100 -> 18.782115
A43: ~Duration | B43: =IFERROR(__xludf.DUMMYFUNCTION("AVERAGE(FILTER(Inventory!K:K,Inventory!J:J=""Closed"",Inventory!D:D>=B35,Inventory!D:D<=C35))"),27.13903743315508) -> 27.139037 | D43: =IFERROR(__xludf.DUMMYFUNCTION("AVERAGE(FILTER(Inventory!K:K,Inventory!J:J=""Closed"",Inventory!D:D>=D35,Inventory!D:D<=E35))"),19.683823529411764) -> 19.683824 | F43: =IFERROR(__xludf.DUMMYFUNCTION("AVERAGE(FILTER(Inventory!K:K,Inventory!J:J=""Closed"",Inventory!D:D>=F35,Inventory!D:D<=G35))"),13.042944785276074) -> 13.042945 | H43: =IFERROR(__xludf.DUMMYFUNCTION("AVERAGE(FILTER(Inventory!K:K,Inventory!J:J=""Closed"",Inventory!D:D>=H35,Inventory!D:D<=I35))"),24.559782608695652) -> 24.559783 | J43: =IFERROR(__xludf.DUMMYFUNCTION("AVERAGE(FILTER(Inventory!K:K,Inventory!J:J=""Closed"",Inventory!D:D>=J35,Inventory!D:D<=K35))"),19.9) -> 19.9 | L43: =IFERROR(__xludf.DUMMYFUNCTION("AVERAGE(FILTER(Inventory!K:K,Inventory!J:J=""Closed"",Inventory!D:D>=L35,Inventory!D:D<=M35))"),34.1198347107438) -> 34.119835 | N43: =IFERROR(__xludf.DUMMYFUNCTION("AVERAGE(FILTER(Inventory!K:K,Inventory!J:J=""Closed"",Inventory!D:D>=N35,Inventory!D:D<=O35))"),32.62948207171315) -> 32.629482 | P43: =IFERROR(__xludf.DUMMYFUNCTION("AVERAGE(FILTER(Inventory!K:K,Inventory!J:J=""Closed"",Inventory!D:D>=P35,Inventory!D:D<=Q35))"),20.16254416961131) -> 20.162544 | R43: =IFERROR(__xludf.DUMMYFUNCTION("AVERAGE(FILTER(Inventory!K:K,Inventory!J:J=""Closed"",Inventory!D:D>=R35,Inventory!D:D<=S35))"),10.129032258064516) -> 10.129032 | T43: =IFERROR(__xludf.DUMMYFUNCTION("AVERAGE(FILTER(Inventory!K:K,Inventory!J:J=""Closed"",Inventory!D:D>=T35,Inventory!D:D<=U35))"),18.689655172413794) -> 18.689655 | V43: =IFERROR(__xludf.DUMMYFUNCTION("AVERAGE(FILTER(Inventory!K:K,Inventory!J:J=""Closed"",Inventory!D:D>=V35,Inventory!D:D<=W35))"),30.778688524590162) -> 30.778689 | X43: =IFERROR(__xludf.DUMMYFUNCTION("AVERAGE(FILTER(Inventory!K:K,Inventory!J:J=""Closed"",Inventory!D:D>=X35,Inventory!D:D<=Y35))"),20.336898395721924) -> 20.336898
A44: Payouts | B44: 24.6 | D44: 46.07 | F44: 41.03 | H44: 40 | J44: 40 | L44: 70 | N44: 51 | P44: 58.15 | R44: 60 | T44: 0 | V44: 30 | X44: 60.5
B45: 219 | C45: 2534.23 | D45: 214 | E45: 2490.48 | F45: 205 | G45: 2447.1 | H45: 232 | I45: 2757.74 | J45: 245 | K45: 3110.22 | L45: 236 | M45: 3281.8 | N45: 227 | O45: 3139.24 | P45: 255 | Q45: 3666.76 | R45: 245 | S45: 3640.44 | T45: 247 | U45: 3712.6 | V45: 248 | W45: 3697.02 | X45: 238 | Y45: 3712.97
B47: 45383 | C47: 45412 | D47: 45413 | E47: 45443 | F47: 45444 | G47: 45473 | H47: 45474 | I47: 45504 | J47: 45505 | K47: 45535 | L47: 45536 | M47: 45565 | N47: 45566 | O47: 45596 | P47: 45597 | Q47: 45626 | R47: 45627 | S47: 45657 | T47: 45658 | U47: 45688 | V47: 45689 | W47: 45716 | X47: 45717 | Y47: 45747
A48: Revenue | B48: =IFERROR(__xludf.DUMMYFUNCTION("SUM(FILTER(Inventory!F:F,Inventory!J:J=""Closed"",Inventory!D:D>=B47,Inventory!D:D<=C47))"),6314.66) -> 6314.66 | D48: =IFERROR(__xludf.DUMMYFUNCTION("SUM(FILTER(Inventory!F:F,Inventory!J:J=""Closed"",Inventory!D:D>=D47,Inventory!D:D<=E47))"),3825.189999999995) -> 3825.19 | F48: =IFERROR(__xludf.DUMMYFUNCTION("SUM(FILTER(Inventory!F:F,Inventory!J:J=""Closed"",Inventory!D:D>=F47,Inventory!D:D<=G47))"),3485.1600000000026) -> 3485.16 | H48: =IFERROR(__xludf.DUMMYFUNCTION("SUM(FILTER(Inventory!F:F,Inventory!J:J=""Closed"",Inventory!D:D>=H47,Inventory!D:D<=I47))"),1203.6499999999999) -> 1203.65 | J48: =IFERROR(__xludf.DUMMYFUNCTION("SUM(FILTER(Inventory!F:F,Inventory!J:J=""Closed"",Inventory!D:D>=J47,Inventory!D:D<=K47))"),431.82999999999987) -> 431.83 | L48: =IFERROR(__xludf.DUMMYFUNCTION("SUM(FILTER(Inventory!F:F,Inventory!J:J=""Closed"",Inventory!D:D>=L47,Inventory!D:D<=M47))"),5291.869999999993) -> 5291.87 | N48: =IFERROR(__xludf.DUMMYFUNCTION("SUM(FILTER(Inventory!F:F,Inventory!J:J=""Closed"",Inventory!D:D>=N47,Inventory!D:D<=O47))"),3470.17) -> 3470.17 | P48: =IFERROR(__xludf.DUMMYFUNCTION("SUM(FILTER(Inventory!F:F,Inventory!J:J=""Closed"",Inventory!D:D>=P47,Inventory!D:D<=Q47))"),3315.269999999996) -> 3315.27 | R48: =IFERROR(__xludf.DUMMYFUNCTION("SUM(FILTER(Inventory!F:F,Inventory!J:J=""Closed"",Inventory!D:D>=R47,Inventory!D:D<=S47))"),5750.620000000009) -> 5750.62 | T48: =IFERROR(__xludf.DUMMYFUNCTION("SUM(FILTER(Inventory!F:F,Inventory!J:J=""Closed"",Inventory!D:D>=T47,Inventory!D:D<=U47))"),2463.19) -> 2463.19 | V48: =IFERROR(__xludf.DUMMYFUNCTION("SUM(FILTER(Inventory!F:F,Inventory!J:J=""Closed"",Inventory!D:D>=V47,Inventory!D:D<=W47))"),2733.82) -> 2733.82 | X48: =IFERROR(__xludf.DUMMYFUNCTION("SUM(FILTER(Inventory!F:F,Inventory!J:J=""Closed"",Inventory!D:D>=X47,Inventory!D:D<=Y47))"),3209.4679999999958) -> 3209.468
A49: Expenses | B49: =IFERROR(__xludf.DUMMYFUNCTION("SUM(FILTER(Inventory!E:E,Inventory!J:J=""Closed"",Inventory!D:D>=B47,Inventory!D:D<=C47))"),4980.809999999991) -> 4980.81 | D49: =IFERROR(__xludf.DUMMYFUNCTION("SUM(FILTER(Inventory!E:E,Inventory!J:J=""Closed"",Inventory!D:D>=D47,Inventory!D:D<=E47))"),3082.179999999998) -> 3082.18 | F49: =IFERROR(__xludf.DUMMYFUNCTION("SUM(FILTER(Inventory!E:E,Inventory!J:J=""Closed"",Inventory!D:D>=F47,Inventory!D:D<=G47))"),2828.230000000001) -> 2828.23 | H49: =IFERROR(__xludf.DUMMYFUNCTION("SUM(FILTER(Inventory!E:E,Inventory!J:J=""Closed"",Inventory!D:D>=H47,Inventory!D:D<=I47))"),1007.8400000000001) -> 1007.84 | J49: =IFERROR(__xludf.DUMMYFUNCTION("SUM(FILTER(Inventory!E:E,Inventory!J:J=""Closed"",Inventory!D:D>=J47,Inventory!D:D<=K47))"),394.84000000000003) -> 394.84 | L49: =IFERROR(__xludf.DUMMYFUNCTION("SUM(FILTER(Inventory!E:E,Inventory!J:J=""Closed"",Inventory!D:D>=L47,Inventory!D:D<=M47))"),4169.399999999999) -> 4169.4 | N49: =IFERROR(__xludf.DUMMYFUNCTION("SUM(FILTER(Inventory!E:E,Inventory!J:J=""Closed"",Inventory!D:D>=N47,Inventory!D:D<=O47))"),2688.5799999999963) -> 2688.58 | P49: =IFERROR(__xludf.DUMMYFUNCTION("SUM(FILTER(Inventory!E:E,Inventory!J:J=""Closed"",Inventory!D:D>=P47,Inventory!D:D<=Q47))"),2553.5899999999997) -> 2553.59 | R49: =IFERROR(__xludf.DUMMYFUNCTION("SUM(FILTER(Inventory!E:E,Inventory!J:J=""Closed"",Inventory!D:D>=R47,Inventory!D:D<=S47))"),4396.395873015879) -> 4396.3959 | T49: =IFERROR(__xludf.DUMMYFUNCTION("SUM(FILTER(Inventory!E:E,Inventory!J:J=""Closed"",Inventory!D:D>=T47,Inventory!D:D<=U47))"),2005.6100000000004) -> 2005.61 | V49: =IFERROR(__xludf.DUMMYFUNCTION("SUM(FILTER(Inventory!E:E,Inventory!J:J=""Closed"",Inventory!D:D>=V47,Inventory!D:D<=W47))"),2279.7600000000007) -> 2279.76 | X49: =IFERROR(__xludf.DUMMYFUNCTION("SUM(FILTER(Inventory!E:E,Inventory!J:J=""Closed"",Inventory!D:D>=X47,Inventory!D:D<=Y47))"),2508.9799999999987) -> 2508.98
A50: Profit | B50: =IFERROR(__xludf.DUMMYFUNCTION("SUM(FILTER(Inventory!G:G,Inventory!J:J=""Closed"",Inventory!D:D>=B47,Inventory!D:D<=C47))"),1333.8499999999985) -> 1333.85 | D50: =IFERROR(__xludf.DUMMYFUNCTION("SUM(FILTER(Inventory!G:G,Inventory!J:J=""Closed"",Inventory!D:D>=D47,Inventory!D:D<=E47))"),743.0100000000004) -> 743.01 | F50: =IFERROR(__xludf.DUMMYFUNCTION("SUM(FILTER(Inventory!G:G,Inventory!J:J=""Closed"",Inventory!D:D>=F47,Inventory!D:D<=G47))"),656.9299999999998) -> 656.93 | H50: =IFERROR(__xludf.DUMMYFUNCTION("SUM(FILTER(Inventory!G:G,Inventory!J:J=""Closed"",Inventory!D:D>=H47,Inventory!D:D<=I47))"),195.80999999999995) -> 195.81 | J50: =IFERROR(__xludf.DUMMYFUNCTION("SUM(FILTER(Inventory!G:G,Inventory!J:J=""Closed"",Inventory!D:D>=J47,Inventory!D:D<=K47))"),36.989999999999995) -> 36.99 | L50: =IFERROR(__xludf.DUMMYFUNCTION("SUM(FILTER(Inventory!G:G,Inventory!J:J=""Closed"",Inventory!D:D>=L47,Inventory!D:D<=M47))"),1122.4699999999993) -> 1122.47 | N50: =IFERROR(__xludf.DUMMYFUNCTION("SUM(FILTER(Inventory!G:G,Inventory!J:J=""Closed"",Inventory!D:D>=N47,Inventory!D:D<=O47))"),781.5899999999999) -> 781.59 | P50: =IFERROR(__xludf.DUMMYFUNCTION("SUM(FILTER(Inventory!G:G,Inventory!J:J=""Closed"",Inventory!D:D>=P47,Inventory!D:D<=Q47))"),761.6799999999996) -> 761.68 | R50: =IFERROR(__xludf.DUMMYFUNCTION("SUM(FILTER(Inventory!G:G,Inventory!J:J=""Closed"",Inventory!D:D>=R47,Inventory!D:D<=S47))"),1354.2241269841281) -> 1354.2241 | T50: =IFERROR(__xludf.DUMMYFUNCTION("SUM(FILTER(Inventory!G:G,Inventory!J:J=""Closed"",Inventory!D:D>=T47,Inventory!D:D<=U47))"),457.5800000000001) -> 457.58 | V50: =IFERROR(__xludf.DUMMYFUNCTION("SUM(FILTER(Inventory!G:G,Inventory!J:J=""Closed"",Inventory!D:D>=V47,Inventory!D:D<=W47))"),454.05999999999983) -> 454.06 | X50: =IFERROR(__xludf.DUMMYFUNCTION("SUM(FILTER(Inventory!G:G,Inventory!J:J=""Closed"",Inventory!D:D>=X47,Inventory!D:D<=Y47))"),700.4879999999997) -> 700.488
A51: Sold Items | B51: =COUNTIFS(Inventory!J:J,"Closed", Inventory!D:D,">="&B47,Inventory!D:D,"<="&C47) -> 423 | D51: =COUNTIFS(Inventory!J:J,"Closed", Inventory!D:D,">="&D47,Inventory!D:D,"<="&E47) -> 312 | F51: =COUNTIFS(Inventory!J:J,"Closed", Inventory!D:D,">="&F47,Inventory!D:D,"<="&G47) -> 154 | H51: =COUNTIFS(Inventory!J:J,"Closed", Inventory!D:D,">="&H47,Inventory!D:D,"<="&I47) -> 67 | J51: =COUNTIFS(Inventory!J:J,"Closed", Inventory!D:D,">="&J47,Inventory!D:D,"<="&K47) -> 27 | L51: =COUNTIFS(Inventory!J:J,"Closed", Inventory!D:D,">="&L47,Inventory!D:D,"<="&M47) -> 226 | N51: =COUNTIFS(Inventory!J:J,"Closed", Inventory!D:D,">="&N47,Inventory!D:D,"<="&O47) -> 182 | P51: =COUNTIFS(Inventory!J:J,"Closed", Inventory!D:D,">="&P47,Inventory!D:D,"<="&Q47) -> 153 | R51: =COUNTIFS(Inventory!J:J,"Closed", Inventory!D:D,">="&R47,Inventory!D:D,"<="&S47) -> 291 | T51: =COUNTIFS(Inventory!J:J,"Closed", Inventory!D:D,">="&T47,Inventory!D:D,"<="&U47) -> 145 | V51: =COUNTIFS(Inventory!J:J,"Closed", Inventory!D:D,">="&V47,Inventory!D:D,"<="&W47) -> 144 | X51: =COUNTIFS(Inventory!J:J,"Closed", Inventory!D:D,">="&X47,Inventory!D:D,"<="&Y47) -> 140
A52: ~Sold Price | B52: =IFERROR(__xludf.DUMMYFUNCTION("AVERAGE(FILTER(Inventory!F:F,Inventory!J:J=""Closed"",Inventory!D:D>=B47,Inventory!D:D<=C47))"),14.928274231678486) -> 14.928274 | D52: =IFERROR(__xludf.DUMMYFUNCTION("AVERAGE(FILTER(Inventory!F:F,Inventory!J:J=""Closed"",Inventory!D:D>=D47,Inventory!D:D<=E47))"),12.260224358974343) -> 12.260224 | F52: =IFERROR(__xludf.DUMMYFUNCTION("AVERAGE(FILTER(Inventory!F:F,Inventory!J:J=""Closed"",Inventory!D:D>=F47,Inventory!D:D<=G47))"),22.630909090909107) -> 22.630909 | H52: =IFERROR(__xludf.DUMMYFUNCTION("AVERAGE(FILTER(Inventory!F:F,Inventory!J:J=""Closed"",Inventory!D:D>=H47,Inventory!D:D<=I47))"),17.964925373134328) -> 17.964925 | J52: =IFERROR(__xludf.DUMMYFUNCTION("AVERAGE(FILTER(Inventory!F:F,Inventory!J:J=""Closed"",Inventory!D:D>=J47,Inventory!D:D<=K47))"),15.9937037037037) -> 15.993704 | L52: =IFERROR(__xludf.DUMMYFUNCTION("AVERAGE(FILTER(Inventory!F:F,Inventory!J:J=""Closed"",Inventory!D:D>=L47,Inventory!D:D<=M47))"),23.415353982300854) -> 23.415354 | N52: =IFERROR(__xludf.DUMMYFUNCTION("AVERAGE(FILTER(Inventory!F:F,Inventory!J:J=""Closed"",Inventory!D:D>=N47,Inventory!D:D<=O47))"),19.066868131868134) -> 19.066868 | P52: =IFERROR(__xludf.DUMMYFUNCTION("AVERAGE(FILTER(Inventory!F:F,Inventory!J:J=""Closed"",Inventory!D:D>=P47,Inventory!D:D<=Q47))"),21.668431372548994) -> 21.668431 | R52: =IFERROR(__xludf.DUMMYFUNCTION("AVERAGE(FILTER(Inventory!F:F,Inventory!J:J=""Closed"",Inventory!D:D>=R47,Inventory!D:D<=S47))"),19.761580756013778) -> 19.761581 | T52: =IFERROR(__xludf.DUMMYFUNCTION("AVERAGE(FILTER(Inventory!F:F,Inventory!J:J=""Closed"",Inventory!D:D>=T47,Inventory!D:D<=U47))"),16.98751724137931) -> 16.987517 | V52: =IFERROR(__xludf.DUMMYFUNCTION("AVERAGE(FILTER(Inventory!F:F,Inventory!J:J=""Closed"",Inventory!D:D>=V47,Inventory!D:D<=W47))"),18.984861111111112) -> 18.984861 | X52: =IFERROR(__xludf.DUMMYFUNCTION("AVERAGE(FILTER(Inventory!F:F,Inventory!J:J=""Closed"",Inventory!D:D>=X47,Inventory!D:D<=Y47))"),22.924771428571397) -> 22.924771
A53: ~Profit | B53: =IFERROR(__xludf.DUMMYFUNCTION("AVERAGE(FILTER(Inventory!G:G,Inventory!J:J=""Closed"",Inventory!D:D>=B47,Inventory!D:D<=C47))"),3.1533096926713915) -> 3.1533097 | D53: =IFERROR(__xludf.DUMMYFUNCTION("AVERAGE(FILTER(Inventory!G:G,Inventory!J:J=""Closed"",Inventory!D:D>=D47,Inventory!D:D<=E47))"),2.3814423076923092) -> 2.3814423 | F53: =IFERROR(__xludf.DUMMYFUNCTION("AVERAGE(FILTER(Inventory!G:G,Inventory!J:J=""Closed"",Inventory!D:D>=F47,Inventory!D:D<=G47))"),4.26577922077922) -> 4.2657792 | H53: =IFERROR(__xludf.DUMMYFUNCTION("AVERAGE(FILTER(Inventory!G:G,Inventory!J:J=""Closed"",Inventory!D:D>=H47,Inventory!D:D<=I47))"),2.922537313432835) -> 2.9225373 | J53: =IFERROR(__xludf.DUMMYFUNCTION("AVERAGE(FILTER(Inventory!G:G,Inventory!J:J=""Closed"",Inventory!D:D>=J47,Inventory!D:D<=K47))"),1.3699999999999999) -> 1.37 | L53: =IFERROR(__xludf.DUMMYFUNCTION("AVERAGE(FILTER(Inventory!G:G,Inventory!J:J=""Closed"",Inventory!D:D>=L47,Inventory!D:D<=M47))"),4.966681415929201) -> 4.9666814 | N53: =IFERROR(__xludf.DUMMYFUNCTION("AVERAGE(FILTER(Inventory!G:G,Inventory!J:J=""Closed"",Inventory!D:D>=N47,Inventory!D:D<=O47))"),4.294450549450549) -> 4.2944505 | P53: =IFERROR(__xludf.DUMMYFUNCTION("AVERAGE(FILTER(Inventory!G:G,Inventory!J:J=""Closed"",Inventory!D:D>=P47,Inventory!D:D<=Q47))"),4.9783006535947685) -> 4.9783007 | R53: =IFERROR(__xludf.DUMMYFUNCTION("AVERAGE(FILTER(Inventory!G:G,Inventory!J:J=""Closed"",Inventory!D:D>=R47,Inventory!D:D<=S47))"),4.653691158021059) -> 4.6536912 | T53: =IFERROR(__xludf.DUMMYFUNCTION("AVERAGE(FILTER(Inventory!G:G,Inventory!J:J=""Closed"",Inventory!D:D>=T47,Inventory!D:D<=U47))"),3.1557241379310352) -> 3.1557241 | V53: =IFERROR(__xludf.DUMMYFUNCTION("AVERAGE(FILTER(Inventory!G:G,Inventory!J:J=""Closed"",Inventory!D:D>=V47,Inventory!D:D<=W47))"),3.153194444444443) -> 3.1531944 | X53: =IFERROR(__xludf.DUMMYFUNCTION("AVERAGE(FILTER(Inventory!G:G,Inventory!J:J=""Closed"",Inventory!D:D>=X47,Inventory!D:D<=Y47))"),5.003485714285712) -> 5.0034857
A54: ~Margin % | B54: =(B50/B48)*100 -> 21.123069 | D54: =(D50/D48)*100 -> 19.424133 | F54: =(F50/F48)*100 -> 18.84935 | H54: =(H50/H48)*100 -> 16.268018 | J54: =(J50/J48)*100 -> 8.5658708 | L54: =(L50/L48)*100 -> 21.211216 | N54: =(N50/N48)*100 -> 22.523104 | P54: =(P50/P48)*100 -> 22.974901 | R54: =(R50/R48)*100 -> 23.549185 | T54: =(T50/T48)*100 -> 18.576724 | V54: =(V50/V48)*100 -> 16.608994 | X54: =(X50/X48)*100 -> 21.825673
A55: ~Duration | B55: =IFERROR(__xludf.DUMMYFUNCTION("AVERAGE(FILTER(Inventory!K:K,Inventory!J:J=""Closed"",Inventory!D:D>=B47,Inventory!D:D<=C47))"),11.56501182033097) -> 11.565012 | D55: =IFERROR(__xludf.DUMMYFUNCTION("AVERAGE(FILTER(Inventory!K:K,Inventory!J:J=""Closed"",Inventory!D:D>=D47,Inventory!D:D<=E47))"),8.439102564102564) -> 8.4391026 | F55: =IFERROR(__xludf.DUMMYFUNCTION("AVERAGE(FILTER(Inventory!K:K,Inventory!J:J=""Closed"",Inventory!D:D>=F47,Inventory!D:D<=G47))"),28.48701298701299) -> 28.487013 | H55: =IFERROR(__xludf.DUMMYFUNCTION("AVERAGE(FILTER(Inventory!K:K,Inventory!J:J=""Closed"",Inventory!D:D>=H47,Inventory!D:D<=I47))"),50.61194029850746) -> 50.61194 | J55: =IFERROR(__xludf.DUMMYFUNCTION("AVERAGE(FILTER(Inventory!K:K,Inventory!J:J=""Closed"",Inventory!D:D>=J47,Inventory!D:D<=K47))"),189.37037037037038) -> 189.37037 | L55: =IFERROR(__xludf.DUMMYFUNCTION("AVERAGE(FILTER(Inventory!K:K,Inventory!J:J=""Closed"",Inventory!D:D>=L47,Inventory!D:D<=M47))"),21.486725663716815) -> 21.486726 | N55: =IFERROR(__xludf.DUMMYFUNCTION("AVERAGE(FILTER(Inventory!K:K,Inventory!J:J=""Closed"",Inventory!D:D>=N47,Inventory!D:D<=O47))"),26.115384615384617) -> 26.115385 | P55: =IFERROR(__xludf.DUMMYFUNCTION("AVERAGE(FILTER(Inventory!K:K,Inventory!J:J=""Closed"",Inventory!D:D>=P47,Inventory!D:D<=Q47))"),15.718954248366012) -> 15.718954 | R55: =IFERROR(__xludf.DUMMYFUNCTION("AVERAGE(FILTER(Inventory!K:K,Inventory!J:J=""Closed"",Inventory!D:D>=R47,Inventory!D:D<=S47))"),14.199312714776632) -> 14.199313 | T55: =IFERROR(__xludf.DUMMYFUNCTION("AVERAGE(FILTER(Inventory!K:K,Inventory!J:J=""Closed"",Inventory!D:D>=T47,Inventory!D:D<=U47))"),31.310344827586206) -> 31.310345 | V55: =IFERROR(__xludf.DUMMYFUNCTION("AVERAGE(FILTER(Inventory!K:K,Inventory!J:J=""Closed"",Inventory!D:D>=V47,Inventory!D:D<=W47))"),34.604166666666664) -> 34.604167 | X55: =IFERROR(__xludf.DUMMYFUNCTION("AVERAGE(FILTER(Inventory!K:K,Inventory!J:J=""Closed"",Inventory!D:D>=X47,Inventory!D:D<=Y47))"),36.042857142857144) -> 36.042857
A56: Payouts | B56: 52.45 | D56: 103.78 | F56: 23.68 | H56: 69.37 | J56: 0 | L56: 90.1 | N56: 40.18 | P56: 40.49 | R56: 102.26 | T56: 21.15 | V56: 42.88 | X56: 49.77
A57: Sheets | B57: 237 | C57: 3695.44 | D57: 261 | E57: 3824.61 | F57: 251 | G57: 3746.19 | H57: 235 | I57: 3570.42 | J57: 231 | K57: 3572.07 | L57: 242 | M57: 3754.6 | N57: 248 | O57: 4020.62 | P57: 259 | Q57: 4212.25 | R57: 246 | S57: 4092.02 | T57: 254 | U57: 4213.18 | V57: 235 | W57: 3983.02 | X57: 226 | Y57: 3876,32
B59: 45748 | C59: 45777 | D59: 45778 | E59: 45808 | F59: 45809 | G59: 45838 | H59: 45839 | I59: 45869 | J59: 45870 | K59: 45900 | L59: 45901 | M59: 45930 | N59: 45931 | O59: 45961 | P59: 45962 | Q59: 45991 | R59: 45992 | S59: 46022 | T59: 46023 | U59: 46053 | V59: 46054 | W59: 46081 | X59: 46082 | Y59: 46112
A60: Revenue | B60: =IFERROR(__xludf.DUMMYFUNCTION("SUM(FILTER(Inventory!F:F,Inventory!J:J=""Closed"",Inventory!D:D>=B59,Inventory!D:D<=C59))"),1373.75) -> 1373.75 | D60: =IFERROR(__xludf.DUMMYFUNCTION("SUM(FILTER(Inventory!F:F,Inventory!J:J=""Closed"",Inventory!D:D>=D59,Inventory!D:D<=E59))"),5046.869999999992) -> 5046.87 | F60: =IFERROR(__xludf.DUMMYFUNCTION("SUM(FILTER(Inventory!F:F,Inventory!J:J=""Closed"",Inventory!D:D>=F59,Inventory!D:D<=G59))"),1212.2299999999996) -> 1212.23 | H60: =IFERROR(__xludf.DUMMYFUNCTION("SUM(FILTER(Inventory!F:F,Inventory!J:J=""Closed"",Inventory!D:D>=H59,Inventory!D:D<=I59))"),642.4799999999999) -> 642.48 | J60: =IFERROR(__xludf.DUMMYFUNCTION("SUM(FILTER(Inventory!F:F,Inventory!J:J=""Closed"",Inventory!D:D>=J59,Inventory!D:D<=K59))"),1326.95) -> 1326.95 | L60: =IFERROR(__xludf.DUMMYFUNCTION("SUM(FILTER(Inventory!F:F,Inventory!J:J=""Closed"",Inventory!D:D>=L59,Inventory!D:D<=M59))"),1412.3299999999997) -> 1412.33 | N60: =IFERROR(__xludf.DUMMYFUNCTION("SUM(FILTER(Inventory!F:F,Inventory!J:J=""Closed"",Inventory!D:D>=N59,Inventory!D:D<=O59))"),1588.6099999999994) -> 1588.61 | P60: =IFERROR(__xludf.DUMMYFUNCTION("SUM(FILTER(Inventory!F:F,Inventory!J:J=""Closed"",Inventory!D:D>=P59,Inventory!D:D<=Q59))"),2314.2900000000004) -> 2314.29 | R60: =IFERROR(__xludf.DUMMYFUNCTION("SUM(FILTER(Inventory!F:F,Inventory!J:J=""Closed"",Inventory!D:D>=R59,Inventory!D:D<=S59))"),1444.97) -> 1444.97 | T60: =IFERROR(__xludf.DUMMYFUNCTION("SUM(FILTER(Inventory!F:F,Inventory!J:J=""Closed"",Inventory!D:D>=T59,Inventory!D:D<=U59))"),2705.8399999999992) -> 2705.84 | V60: =IFERROR(__xludf.DUMMYFUNCTION("SUM(FILTER(Inventory!F:F,Inventory!J:J=""Closed"",Inventory!D:D>=V59,Inventory!D:D<=W59))"),1262.12) -> 1262.12 | X60: =IFERROR(__xludf.DUMMYFUNCTION("SUM(FILTER(Inventory!F:F,Inventory!J:J=""Closed"",Inventory!D:D>=X59,Inventory!D:D<=Y59))"),1297.75) -> 1297.75
A61: Expenses | B61: =IFERROR(__xludf.DUMMYFUNCTION("SUM(FILTER(Inventory!E:E,Inventory!J:J=""Closed"",Inventory!D:D>=B59,Inventory!D:D<=C59))"),1078.1599999999999) -> 1078.16 | D61: =IFERROR(__xludf.DUMMYFUNCTION("SUM(FILTER(Inventory!E:E,Inventory!J:J=""Closed"",Inventory!D:D>=D59,Inventory!D:D<=E59))"),4242.940000000001) -> 4242.94 | F61: =IFERROR(__xludf.DUMMYFUNCTION("SUM(FILTER(Inventory!E:E,Inventory!J:J=""Closed"",Inventory!D:D>=F59,Inventory!D:D<=G59))"),1061.8500000000001) -> 1061.85 | H61: =IFERROR(__xludf.DUMMYFUNCTION("SUM(FILTER(Inventory!E:E,Inventory!J:J=""Closed"",Inventory!D:D>=H59,Inventory!D:D<=I59))"),504.66000000000014) -> 504.66 | J61: =IFERROR(__xludf.DUMMYFUNCTION("SUM(FILTER(Inventory!E:E,Inventory!J:J=""Closed"",Inventory!D:D>=J59,Inventory!D:D<=K59))"),1136.3299999999997) -> 1136.33 | L61: =IFERROR(__xludf.DUMMYFUNCTION("SUM(FILTER(Inventory!E:E,Inventory!J:J=""Closed"",Inventory!D:D>=L59,Inventory!D:D<=M59))"),1151.3700000000001) -> 1151.37 | N61: =IFERROR(__xludf.DUMMYFUNCTION("SUM(FILTER(Inventory!E:E,Inventory!J:J=""Closed"",Inventory!D:D>=N59,Inventory!D:D<=O59))"),1217.889999999999) -> 1217.89 | P61: =IFERROR(__xludf.DUMMYFUNCTION("SUM(FILTER(Inventory!E:E,Inventory!J:J=""Closed"",Inventory!D:D>=P59,Inventory!D:D<=Q59))"),1819.4699999999993) -> 1819.47 | R61: =IFERROR(__xludf.DUMMYFUNCTION("SUM(FILTER(Inventory!E:E,Inventory!J:J=""Closed"",Inventory!D:D>=R59,Inventory!D:D<=S59))"),1109.4399999999991) -> 1109.44 | T61: =IFERROR(__xludf.DUMMYFUNCTION("SUM(FILTER(Inventory!E:E,Inventory!J:J=""Closed"",Inventory!D:D>=T59,Inventory!D:D<=U59))"),2130.2299999999977) -> 2130.23 | V61: =IFERROR(__xludf.DUMMYFUNCTION("SUM(FILTER(Inventory!E:E,Inventory!J:J=""Closed"",Inventory!D:D>=V59,Inventory!D:D<=W59))"),992.2600000000006) -> 992.26 | X61: =IFERROR(__xludf.DUMMYFUNCTION("SUM(FILTER(Inventory!E:E,Inventory!J:J=""Closed"",Inventory!D:D>=X59,Inventory!D:D<=Y59))"),1051.5499999999997) -> 1051.55
A62: Profit | B62: =IFERROR(__xludf.DUMMYFUNCTION("SUM(FILTER(Inventory!G:G,Inventory!J:J=""Closed"",Inventory!D:D>=B59,Inventory!D:D<=C59))"),295.59000000000003) -> 295.59 | D62: =IFERROR(__xludf.DUMMYFUNCTION("SUM(FILTER(Inventory!G:G,Inventory!J:J=""Closed"",Inventory!D:D>=D59,Inventory!D:D<=E59))"),803.9299999999998) -> 803.93 | F62: =IFERROR(__xludf.DUMMYFUNCTION("SUM(FILTER(Inventory!G:G,Inventory!J:J=""Closed"",Inventory!D:D>=F59,Inventory!D:D<=G59))"),150.37999999999997) -> 150.38 | H62: =IFERROR(__xludf.DUMMYFUNCTION("SUM(FILTER(Inventory!G:G,Inventory!J:J=""Closed"",Inventory!D:D>=H59,Inventory!D:D<=I59))"),137.82000000000002) -> 137.82 | J62: =IFERROR(__xludf.DUMMYFUNCTION("SUM(FILTER(Inventory!G:G,Inventory!J:J=""Closed"",Inventory!D:D>=J59,Inventory!D:D<=K59))"),197.40000000000003) -> 197.4 | L62: =IFERROR(__xludf.DUMMYFUNCTION("SUM(FILTER(Inventory!G:G,Inventory!J:J=""Closed"",Inventory!D:D>=L59,Inventory!D:D<=M59))"),260.96) -> 260.96 | N62: =IFERROR(__xludf.DUMMYFUNCTION("SUM(FILTER(Inventory!G:G,Inventory!J:J=""Closed"",Inventory!D:D>=N59,Inventory!D:D<=O59))"),370.71999999999986) -> 370.72 | P62: =IFERROR(__xludf.DUMMYFUNCTION("SUM(FILTER(Inventory!G:G,Inventory!J:J=""Closed"",Inventory!D:D>=P59,Inventory!D:D<=Q59))"),494.8199999999999) -> 494.82 | R62: =IFERROR(__xludf.DUMMYFUNCTION("SUM(FILTER(Inventory!G:G,Inventory!J:J=""Closed"",Inventory!D:D>=R59,Inventory!D:D<=S59))"),335.53) -> 335.53 | T62: =IFERROR(__xludf.DUMMYFUNCTION("SUM(FILTER(Inventory!G:G,Inventory!J:J=""Closed"",Inventory!D:D>=T59,Inventory!D:D<=U59))"),575.6099999999999) -> 575.61 | V62: =IFERROR(__xludf.DUMMYFUNCTION("SUM(FILTER(Inventory!G:G,Inventory!J:J=""Closed"",Inventory!D:D>=V59,Inventory!D:D<=W59))"),269.86) -> 269.86 | X62: =IFERROR(__xludf.DUMMYFUNCTION("SUM(FILTER(Inventory!G:G,Inventory!J:J=""Closed"",Inventory!D:D>=X59,Inventory!D:D<=Y59))"),246.2) -> 246.2
A63: Sold Items | B63: =COUNTIFS(Inventory!J:J,"Closed", Inventory!D:D,">="&B59,Inventory!D:D,"<="&C59) -> 56 | D63: =COUNTIFS(Inventory!J:J,"Closed", Inventory!D:D,">="&D59,Inventory!D:D,"<="&E59) -> 182 | F63: =COUNTIFS(Inventory!J:J,"Closed", Inventory!D:D,">="&F59,Inventory!D:D,"<="&G59) -> 57 | H63: =COUNTIFS(Inventory!J:J,"Closed", Inventory!D:D,">="&H59,Inventory!D:D,"<="&I59) -> 32 | J63: =COUNTIFS(Inventory!J:J,"Closed", Inventory!D:D,">="&J59,Inventory!D:D,"<="&K59) -> 44 | L63: =COUNTIFS(Inventory!J:J,"Closed", Inventory!D:D,">="&L59,Inventory!D:D,"<="&M59) -> 53 | N63: =COUNTIFS(Inventory!J:J,"Closed", Inventory!D:D,">="&N59,Inventory!D:D,"<="&O59) -> 96 | P63: =COUNTIFS(Inventory!J:J,"Closed", Inventory!D:D,">="&P59,Inventory!D:D,"<="&Q59) -> 128 | R63: =COUNTIFS(Inventory!J:J,"Closed", Inventory!D:D,">="&R59,Inventory!D:D,"<="&S59) -> 64 | T63: =COUNTIFS(Inventory!J:J,"Closed", Inventory!D:D,">="&T59,Inventory!D:D,"<="&U59) -> 121 | V63: =COUNTIFS(Inventory!J:J,"Closed", Inventory!D:D,">="&V59,Inventory!D:D,"<="&W59) -> 49 | X63: =COUNTIFS(Inventory!J:J,"Closed", Inventory!D:D,">="&X59,Inventory!D:D,"<="&Y59) -> 72
A64: ~Sold Price | B64: =IFERROR(__xludf.DUMMYFUNCTION("AVERAGE(FILTER(Inventory!F:F,Inventory!J:J=""Closed"",Inventory!D:D>=B59,Inventory!D:D<=C59))"),24.53125) -> 24.53125 | D64: =IFERROR(__xludf.DUMMYFUNCTION("AVERAGE(FILTER(Inventory!F:F,Inventory!J:J=""Closed"",Inventory!D:D>=D59,Inventory!D:D<=E59))"),27.7300549450549) -> 27.730055 | F64: =IFERROR(__xludf.DUMMYFUNCTION("AVERAGE(FILTER(Inventory!F:F,Inventory!J:J=""Closed"",Inventory!D:D>=F59,Inventory!D:D<=G59))"),21.267192982456134) -> 21.267193 | H64: =IFERROR(__xludf.DUMMYFUNCTION("AVERAGE(FILTER(Inventory!F:F,Inventory!J:J=""Closed"",Inventory!D:D>=H59,Inventory!D:D<=I59))"),20.077499999999997) -> 20.0775 | J64: =IFERROR(__xludf.DUMMYFUNCTION("AVERAGE(FILTER(Inventory!F:F,Inventory!J:J=""Closed"",Inventory!D:D>=J59,Inventory!D:D<=K59))"),30.157954545454547) -> 30.157955 | L64: =IFERROR(__xludf.DUMMYFUNCTION("AVERAGE(FILTER(Inventory!F:F,Inventory!J:J=""Closed"",Inventory!D:D>=L59,Inventory!D:D<=M59))"),26.6477358490566) -> 26.647736 | N64: =IFERROR(__xludf.DUMMYFUNCTION("AVERAGE(FILTER(Inventory!F:F,Inventory!J:J=""Closed"",Inventory!D:D>=N59,Inventory!D:D<=O59))"),16.54802083333333) -> 16.548021 | P64: =IFERROR(__xludf.DUMMYFUNCTION("AVERAGE(FILTER(Inventory!F:F,Inventory!J:J=""Closed"",Inventory!D:D>=P59,Inventory!D:D<=Q59))"),18.080390625000003) -> 18.080391 | R64: =IFERROR(__xludf.DUMMYFUNCTION("AVERAGE(FILTER(Inventory!F:F,Inventory!J:J=""Closed"",Inventory!D:D>=R59,Inventory!D:D<=S59))"),22.57765625) -> 22.577656 | T64: =IFERROR(__xludf.DUMMYFUNCTION("AVERAGE(FILTER(Inventory!F:F,Inventory!J:J=""Closed"",Inventory!D:D>=T59,Inventory!D:D<=U59))"),22.36231404958677) -> 22.362314 | V64: =IFERROR(__xludf.DUMMYFUNCTION("AVERAGE(FILTER(Inventory!F:F,Inventory!J:J=""Closed"",Inventory!D:D>=V59,Inventory!D:D<=W59))"),25.75755102040816) -> 25.757551 | X64: =IFERROR(__xludf.DUMMYFUNCTION("AVERAGE(FILTER(Inventory!F:F,Inventory!J:J=""Closed"",Inventory!D:D>=X59,Inventory!D:D<=Y59))"),18.024305555555557) -> 18.024306
A65: ~Profit | B65: =IFERROR(__xludf.DUMMYFUNCTION("AVERAGE(FILTER(Inventory!G:G,Inventory!J:J=""Closed"",Inventory!D:D>=B59,Inventory!D:D<=C59))"),5.278392857142857) -> 5.2783929 | D65: =IFERROR(__xludf.DUMMYFUNCTION("AVERAGE(FILTER(Inventory!G:G,Inventory!J:J=""Closed"",Inventory!D:D>=D59,Inventory!D:D<=E59))"),4.417197802197801) -> 4.4171978 | F65: =IFERROR(__xludf.DUMMYFUNCTION("AVERAGE(FILTER(Inventory!G:G,Inventory!J:J=""Closed"",Inventory!D:D>=F59,Inventory!D:D<=G59))"),2.638245614035087) -> 2.6382456 | H65: =IFERROR(__xludf.DUMMYFUNCTION("AVERAGE(FILTER(Inventory!G:G,Inventory!J:J=""Closed"",Inventory!D:D>=H59,Inventory!D:D<=I59))"),4.306875000000001) -> 4.306875 | J65: =IFERROR(__xludf.DUMMYFUNCTION("AVERAGE(FILTER(Inventory!G:G,Inventory!J:J=""Closed"",Inventory!D:D>=J59,Inventory!D:D<=K59))"),4.486363636363637) -> 4.4863636 | L65: =IFERROR(__xludf.DUMMYFUNCTION("AVERAGE(FILTER(Inventory!G:G,Inventory!J:J=""Closed"",Inventory!D:D>=L59,Inventory!D:D<=M59))"),4.92377358490566) -> 4.9237736 | N65: =IFERROR(__xludf.DUMMYFUNCTION("AVERAGE(FILTER(Inventory!G:G,Inventory!J:J=""Closed"",Inventory!D:D>=N59,Inventory!D:D<=O59))"),3.861666666666665) -> 3.8616667 | P65: =IFERROR(__xludf.DUMMYFUNCTION("AVERAGE(FILTER(Inventory!G:G,Inventory!J:J=""Closed"",Inventory!D:D>=P59,Inventory!D:D<=Q59))"),3.865781249999999) -> 3.8657812 | R65: =IFERROR(__xludf.DUMMYFUNCTION("AVERAGE(FILTER(Inventory!G:G,Inventory!J:J=""Closed"",Inventory!D:D>=R59,Inventory!D:D<=S59))"),5.24265625) -> 5.2426562 | T65: =IFERROR(__xludf.DUMMYFUNCTION("AVERAGE(FILTER(Inventory!G:G,Inventory!J:J=""Closed"",Inventory!D:D>=T59,Inventory!D:D<=U59))"),4.757107438016528) -> 4.7571074 | V65: =IFERROR(__xludf.DUMMYFUNCTION("AVERAGE(FILTER(Inventory!G:G,Inventory!J:J=""Closed"",Inventory!D:D>=V59,Inventory!D:D<=W59))"),5.507346938775511) -> 5.5073469 | X65: =IFERROR(__xludf.DUMMYFUNCTION("AVERAGE(FILTER(Inventory!G:G,Inventory!J:J=""Closed"",Inventory!D:D>=X59,Inventory!D:D<=Y59))"),3.4194444444444443) -> 3.4194444
A66: ~Margin % | B66: =(B62/B60)*100 -> 21.517015 | D66: =(D62/D60)*100 -> 15.929279 | F66: =(F62/F60)*100 -> 12.405237 | H66: =(H62/H60)*100 -> 21.451251 | J66: =(J62/J60)*100 -> 14.87622 | L66: =(L62/L60)*100 -> 18.477268 | N66: =(N62/N60)*100 -> 23.336124 | P66: =(P62/P60)*100 -> 21.381072 | R66: =(R62/R60)*100 -> 23.220551 | T66: =(T62/T60)*100 -> 21.272876 | V66: =(V62/V60)*100 -> 21.381485 | X66: =(X62/X60)*100 -> 18.971296
A67: ~Duration | B67: =IFERROR(__xludf.DUMMYFUNCTION("AVERAGE(FILTER(Inventory!K:K,Inventory!J:J=""Closed"",Inventory!D:D>=B59,Inventory!D:D<=C59))"),45.035714285714285) -> 45.035714 | D67: =IFERROR(__xludf.DUMMYFUNCTION("AVERAGE(FILTER(Inventory!K:K,Inventory!J:J=""Closed"",Inventory!D:D>=D59,Inventory!D:D<=E59))"),43.175824175824175) -> 43.175824 | F67: =IFERROR(__xludf.DUMMYFUNCTION("AVERAGE(FILTER(Inventory!K:K,Inventory!J:J=""Closed"",Inventory!D:D>=F59,Inventory!D:D<=G59))"),158.33333333333334) -> 158.33333 | H67: =IFERROR(__xludf.DUMMYFUNCTION("AVERAGE(FILTER(Inventory!K:K,Inventory!J:J=""Closed"",Inventory!D:D>=H59,Inventory!D:D<=I59))"),26.125) -> 26.125 | J67: =IFERROR(__xludf.DUMMYFUNCTION("AVERAGE(FILTER(Inventory!K:K,Inventory!J:J=""Closed"",Inventory!D:D>=J59,Inventory!D:D<=K59))"),28.59090909090909) -> 28.590909 | L67: =IFERROR(__xludf.DUMMYFUNCTION("AVERAGE(FILTER(Inventory!K:K,Inventory!J:J=""Closed"",Inventory!D:D>=L59,Inventory!D:D<=M59))"),64.22641509433963) -> 64.226415 | N67: =IFERROR(__xludf.DUMMYFUNCTION("AVERAGE(FILTER(Inventory!K:K,Inventory!J:J=""Closed"",Inventory!D:D>=N59,Inventory!D:D<=O59))"),20.645833333333332) -> 20.645833 | P67: =IFERROR(__xludf.DUMMYFUNCTION("AVERAGE(FILTER(Inventory!K:K,Inventory!J:J=""Closed"",Inventory!D:D>=P59,Inventory!D:D<=Q59))"),51.4140625) -> 51.414062 | R67: =IFERROR(__xludf.DUMMYFUNCTION("AVERAGE(FILTER(Inventory!K:K,Inventory!J:J=""Closed"",Inventory!D:D>=R59,Inventory!D:D<=S59))"),43.0625) -> 43.0625 | T67: =IFERROR(__xludf.DUMMYFUNCTION("AVERAGE(FILTER(Inventory!K:K,Inventory!J:J=""Closed"",Inventory!D:D>=T59,Inventory!D:D<=U59))"),34.082644628099175) -> 34.082645 | V67: =IFERROR(__xludf.DUMMYFUNCTION("AVERAGE(FILTER(Inventory!K:K,Inventory!J:J=""Closed"",Inventory!D:D>=V59,Inventory!D:D<=W59))"),43.97959183673469) -> 43.979592 | X67: =IFERROR(__xludf.DUMMYFUNCTION("AVERAGE(FILTER(Inventory!K:K,Inventory!J:J=""Closed"",Inventory!D:D>=X59,Inventory!D:D<=Y59))"),77.86111111111111) -> 77.861111
A68: Payouts | B68: 37.75 | D68: 37.87 | F68: 48.45 | H68: 35.5 | J68: 0 | L68: 34.94 | N68: 34.68 | P68: 35.25 | R68: 0.5 | T68: 35.75 | V68: 34.2 | X68: 35.94
A69: Sheets | B69: 235 | C69: 4196.02 | D69: 230 | E69: 4043.5 | F69: 219 | G69: 3936.1 | H69: 216 | I69: 3772.83 | J69: 212 | K69: 3692.22 | L69: 208 | M69: 3630.85 | N69: 226 | O69: 3914.29 | P69: 220 | Q69: 3869.82 | R69: 210 | S69: 3694.63 | T69: 219 | U69: 3710.58 | V69: 225 | W69: 3866.06 | X69: 224 | Y69: 3893.2
B71: 46113 | C71: 46142 | D71: 46143 | E71: 46173 | F71: 46174 | G71: 46203 | H71: 46204 | I71: 46234
A72: Revenue | B72: =IFERROR(__xludf.DUMMYFUNCTION("SUM(FILTER(Inventory!F:F,Inventory!J:J=""Closed"",Inventory!D:D>=B71,Inventory!D:D<=C71))"),1997.5799999999997) -> 1997.58 | D72: =IFERROR(__xludf.DUMMYFUNCTION("SUM(FILTER(Inventory!F:F,Inventory!J:J=""Closed"",Inventory!D:D>=D71,Inventory!D:D<=E71))"),3445.9500000000007) -> 3445.95 | F72: =IFERROR(__xludf.DUMMYFUNCTION("SUM(FILTER(Inventory!F:F,Inventory!J:J=""Closed"",Inventory!D:D>=F71,Inventory!D:D<=G71))"),2313.9000000000005) -> 2313.9 | H72: =IFERROR(__xludf.DUMMYFUNCTION("SUM(FILTER(Inventory!F:F,Inventory!J:J=""Closed"",Inventory!D:D>=H71,Inventory!D:D<=I71))"),30.89) -> 30.89
A73: Expenses | B73: =IFERROR(__xludf.DUMMYFUNCTION("SUM(FILTER(Inventory!E:E,Inventory!J:J=""Closed"",Inventory!D:D>=B71,Inventory!D:D<=C71))"),1554.1099999999994) -> 1554.11 | D73: =IFERROR(__xludf.DUMMYFUNCTION("SUM(FILTER(Inventory!E:E,Inventory!J:J=""Closed"",Inventory!D:D>=D71,Inventory!D:D<=E71))"),2766.889999999999) -> 2766.89 | F73: =IFERROR(__xludf.DUMMYFUNCTION("SUM(FILTER(Inventory!E:E,Inventory!J:J=""Closed"",Inventory!D:D>=F71,Inventory!D:D<=G71))"),1901.180000000001) -> 1901.18 | H73: =IFERROR(__xludf.DUMMYFUNCTION("SUM(FILTER(Inventory!E:E,Inventory!J:J=""Closed"",Inventory!D:D>=H71,Inventory!D:D<=I71))"),19.39) -> 19.39
A74: Profit | B74: =IFERROR(__xludf.DUMMYFUNCTION("SUM(FILTER(Inventory!G:G,Inventory!J:J=""Closed"",Inventory!D:D>=B71,Inventory!D:D<=C71))"),443.4699999999999) -> 443.47 | D74: =IFERROR(__xludf.DUMMYFUNCTION("SUM(FILTER(Inventory!G:G,Inventory!J:J=""Closed"",Inventory!D:D>=D71,Inventory!D:D<=E71))"),679.0599999999998) -> 679.06 | F74: =IFERROR(__xludf.DUMMYFUNCTION("SUM(FILTER(Inventory!G:G,Inventory!J:J=""Closed"",Inventory!D:D>=F71,Inventory!D:D<=G71))"),412.7200000000001) -> 412.72 | H74: =IFERROR(__xludf.DUMMYFUNCTION("SUM(FILTER(Inventory!G:G,Inventory!J:J=""Closed"",Inventory!D:D>=H71,Inventory!D:D<=I71))"),11.5) -> 11.5
A75: Sold Items | B75: =COUNTIFS(Inventory!J:J,"Closed", Inventory!D:D,">="&B71,Inventory!D:D,"<="&C71) -> 90 | D75: =COUNTIFS(Inventory!J:J,"Closed", Inventory!D:D,">="&D71,Inventory!D:D,"<="&E71) -> 133 | F75: =COUNTIFS(Inventory!J:J,"Closed", Inventory!D:D,">="&F71,Inventory!D:D,"<="&G71) -> 93 | H75: =COUNTIFS(Inventory!J:J,"Closed", Inventory!D:D,">="&H71,Inventory!D:D,"<="&I71) -> 3
A76: ~Sold Price | B76: =IFERROR(__xludf.DUMMYFUNCTION("AVERAGE(FILTER(Inventory!F:F,Inventory!J:J=""Closed"",Inventory!D:D>=B71,Inventory!D:D<=C71))"),22.19533333333333) -> 22.195333 | D76: =IFERROR(__xludf.DUMMYFUNCTION("AVERAGE(FILTER(Inventory!F:F,Inventory!J:J=""Closed"",Inventory!D:D>=D71,Inventory!D:D<=E71))"),25.909398496240605) -> 25.909399 | F76: =IFERROR(__xludf.DUMMYFUNCTION("AVERAGE(FILTER(Inventory!F:F,Inventory!J:J=""Closed"",Inventory!D:D>=F71,Inventory!D:D<=G71))"),24.880645161290328) -> 24.880645 | H76: =IFERROR(__xludf.DUMMYFUNCTION("AVERAGE(FILTER(Inventory!F:F,Inventory!J:J=""Closed"",Inventory!D:D>=H71,Inventory!D:D<=I71))"),10.296666666666667) -> 10.296667
A77: ~Profit | B77: =IFERROR(__xludf.DUMMYFUNCTION("AVERAGE(FILTER(Inventory!G:G,Inventory!J:J=""Closed"",Inventory!D:D>=B71,Inventory!D:D<=C71))"),4.927444444444443) -> 4.9274444 | D77: =IFERROR(__xludf.DUMMYFUNCTION("AVERAGE(FILTER(Inventory!G:G,Inventory!J:J=""Closed"",Inventory!D:D>=D71,Inventory!D:D<=E71))"),5.105714285714284) -> 5.1057143 | F77: =IFERROR(__xludf.DUMMYFUNCTION("AVERAGE(FILTER(Inventory!G:G,Inventory!J:J=""Closed"",Inventory!D:D>=F71,Inventory!D:D<=G71))"),4.437849462365592) -> 4.4378495 | H77: =IFERROR(__xludf.DUMMYFUNCTION("AVERAGE(FILTER(Inventory!G:G,Inventory!J:J=""Closed"",Inventory!D:D>=H71,Inventory!D:D<=I71))"),3.8333333333333335) -> 3.8333333
A78: ~Margin % | B78: =(B74/B72)*100 -> 22.200362 | D78: =(D74/D72)*100 -> 19.706032 | F78: =(F74/F72)*100 -> 17.836553 | H78: =(H74/H72)*100 -> 37.228877
A79: ~Duration | B79: =IFERROR(__xludf.DUMMYFUNCTION("AVERAGE(FILTER(Inventory!K:K,Inventory!J:J=""Closed"",Inventory!D:D>=B71,Inventory!D:D<=C71))"),43.266666666666666) -> 43.266667 | D79: =IFERROR(__xludf.DUMMYFUNCTION("AVERAGE(FILTER(Inventory!K:K,Inventory!J:J=""Closed"",Inventory!D:D>=D71,Inventory!D:D<=E71))"),67.95488721804512) -> 67.954887 | F79: =IFERROR(__xludf.DUMMYFUNCTION("AVERAGE(FILTER(Inventory!K:K,Inventory!J:J=""Closed"",Inventory!D:D>=F71,Inventory!D:D<=G71))"),36.935483870967744) -> 36.935484 | H79: =IFERROR(__xludf.DUMMYFUNCTION("AVERAGE(FILTER(Inventory!K:K,Inventory!J:J=""Closed"",Inventory!D:D>=H71,Inventory!D:D<=I71))"),7.333333333333333) -> 7.3333333
A80: Payouts | B80: 33.16 | D80: 27.56 | F80: 58.79 | H80: 35.5
A81: Sheets | B81: 253 | C81: 4017.94 | D81: 257 | E81: 4074.84 | F81: 264 | G81: 4278.53
B83: Final 2020 | D83: Final 2021 | F83: Final 2022 | H83: Final 2023 | J83: Final 2024 | L83: Final 2025 | N83: Final 2026 | P83: Total
A84: Revenue | B84: =SUM(B3:Y3) -> 3615.65 | D84: =SUM(B13:Y13) -> 8528.04 | F84: =SUM(B24:Y24) -> 16569.57 | H84: =SUM(B36:Y36) -> 32530.071 | J84: =SUM(B48:Y48) -> 41494.898 | L84: =SUM(B60:Y60) -> 21628.19 | N84: =SUM(B72:Y72) -> 7788.32 | P84: =SUM(B84:L84) -> 124366.42
A85: ~Revenue | B85: =AVERAGE(B3:Y3) -> 301.30417 | D85: =AVERAGE(B13:Y13) -> 710.67 | F85: =AVERAGE(B24:Y24) -> 1380.7975 | H85: =AVERAGE(B36:Y36) -> 2710.8392 | J85: =AVERAGE(B48:Y48) -> 3457.9082 | L85: =AVERAGE(B60:Y60) -> 1802.3492 | N85: =AVERAGE(B72:Y72) -> 1947.08 | P85: =AVERAGE(B85:L85) -> 1727.3114
A86: Expenses | B86: =SUM(B4:Y4) -> 2562.94 | D86: =SUM(B14:Y14) -> 6505.64 | F86: =SUM(B25:Y25) -> 12693.23 | H86: =SUM(B37:Y37) -> 25968.62 | J86: =SUM(B49:Y49) -> 32896.216 | L86: =SUM(B61:Y61) -> 17496.15 | N86: =SUM(B73:Y73) -> 6241.57 | P86: =SUM(B86:L86) -> 98122.796
A87: ~Expenses | B87: =AVERAGE(B4:Y4) -> 213.57833 | D87: =AVERAGE(B14:Y14) -> 542.13667 | F87: =AVERAGE(B25:Y25) -> 1057.7692 | H87: =AVERAGE(B37:Y37) -> 2164.0517 | J87: =AVERAGE(B49:Y49) -> 2741.3513 | L87: =AVERAGE(B61:Y61) -> 1458.0125 | N87: =AVERAGE(B73:Y73) -> 1560.3925 | P87: =AVERAGE(B87:L87) -> 1362.8166
A88: Profit | B88: =SUM(B5:Y5) -> 1052.71 | D88: =SUM(B15:Y15) -> 2022.4 | F88: =SUM(B26:Y26) -> 3876.34 | H88: =SUM(B38:Y38) -> 6561.451 | J88: =SUM(B50:Y50) -> 8598.6821 | L88: =SUM(B62:Y62) -> 4138.82 | N88: =SUM(B74:Y74) -> 1546.75 | P88: =SUM(B88:L88) -> 26250.403
A89: ~Profit | B89: =AVERAGE(B5:Y5) -> 87.725833 | D89: =AVERAGE(B15:Y15) -> 168.53333 | F89: =AVERAGE(B26:Y26) -> 323.02833 | H89: =AVERAGE(B38:Y38) -> 546.78758 | J89: =AVERAGE(B50:Y50) -> 716.55684 | L89: =AVERAGE(B62:Y62) -> 344.90167 | N89: =AVERAGE(B74:Y74) -> 386.6875 | P89: =AVERAGE(B89:L89) -> 364.58893
A90: Sold Items | B90: =SUM(B6:Y6) -> 624 | D90: =SUM(B16:Y16) -> 980 | F90: =SUM(B27:Y27) -> 1322 | H90: =SUM(B39:Y39) -> 2246 | J90: =SUM(B51:Y51) -> 2264 | L90: =SUM(B63:Y63) -> 954 | N90: =SUM(B75:Y75) -> 319 | P90: =SUM(B90:L90) -> 8390
A91: ~Sold Items | B91: =AVERAGE(B6:Y6) -> 52 | D91: =AVERAGE(B16:Y16) -> 81.666667 | F91: =AVERAGE(B27:Y27) -> 110.16667 | H91: =AVERAGE(B39:Y39) -> 187.16667 | J91: =AVERAGE(B51:Y51) -> 188.66667 | L91: =AVERAGE(B63:Y63) -> 79.5 | N91: =AVERAGE(B75:Y75) -> 79.75 | P91: =AVERAGE(B91:L91) -> 116.52778
A92: ~Sold Price | B92: =AVERAGE(B7:Y7) -> 6.9794103 | D92: =AVERAGE(B17:Y17) -> 8.5737806 | F92: =AVERAGE(B28:Y28) -> 13.619629 | H92: =AVERAGE(B40:Y40) -> 14.82753 | J92: =AVERAGE(B52:Y52) -> 18.882285 | L92: =AVERAGE(B64:Y64) -> 22.813494 | P92: =AVERAGE(B92:L92) -> 14.282688
A93: Profit | B93: =AVERAGE(B8:Y8) -> 1.8311134 | D93: =AVERAGE(B18:Y18) -> 2.1259743 | F93: =AVERAGE(B29:Y29) -> 3.2965482 | H93: =AVERAGE(B41:Y41) -> 3.0107083 | J93: =AVERAGE(B53:Y53) -> 3.6915497 | L93: =AVERAGE(B65:Y65) -> 4.392071 | P93: =AVERAGE(B93:L93) -> 3.0579941
A94: ~Margin | B94: =B88/B84 -> 0.29115373 | D94: =D88/D84 -> 0.23714711 | F94: =F88/F84 -> 0.23394331 | H94: =H88/H84 -> 0.20170417 | J94: =J88/J84 -> 0.20722264 | L94: =L88/L84 -> 0.19136229 | P94: =P88/P84 -> 0.21107308
A95: ~Duration | B95: =AVERAGE(B10:Y10) -> 26.703805 | D95: =AVERAGE(B20:Y20) -> 30.507269 | F95: =AVERAGE(B31:Y31) -> 36.045238 | H95: =AVERAGE(B43:Y43) -> 22.597644 | J95: =AVERAGE(B55:Y55) -> 38.995932 | L95: =AVERAGE(B67:Y67) -> 53.044412 | P95: =AVERAGE(B95:L95) -> 34.64905
A96: Payout | D96: =SUM(B21:Y21) -> 81.9 | F96: =SUM(B32:Y32) -> 158.4 | H96: =SUM(B44:Y44) -> 521.35 | J96: =SUM(B56:Y56) -> 636.11 | L96: =SUM(B68:Y68) -> 370.83 | P96: =SUM(D96:L96) -> 1768.59

Sheet Search
B2: Search for Games... | H2: SUBTOTALS
B3: 🔍 | C3: tempest
C4: Name | D4: Vendor | E4: Sold Price | F4: Profit | G4: Duration
B5: {=SEQUENCE(H11,1)} -> 1 | C5: =IFERROR(__xludf.DUMMYFUNCTION("FILTER({Inventory!A2:B8916,Inventory!F2:F8916,Inventory!G2:G8916,Inventory!K2:K8916},ISNUMBER(SEARCH(C3,Inventory!A2:A8916)), Inventory!J2:J8916=""Closed"")"),"Tempest Rising") -> Tempest Rising | D5: =IFERROR(__xludf.DUMMYFUNCTION("""COMPUTED_VALUE"""),"CDKeys") -> CDKeys | E5: =IFERROR(__xludf.DUMMYFUNCTION("""COMPUTED_VALUE"""),9.4) -> 9.4 | F5: =IFERROR(__xludf.DUMMYFUNCTION("""COMPUTED_VALUE"""),1.5100000000000007) -> 1.51 | G5: =IFERROR(__xludf.DUMMYFUNCTION("""COMPUTED_VALUE"""),5.0) -> 5
B6: 2 | C6: =IFERROR(__xludf.DUMMYFUNCTION("""COMPUTED_VALUE"""),"Tempest Rising") -> Tempest Rising | D6: =IFERROR(__xludf.DUMMYFUNCTION("""COMPUTED_VALUE"""),"CDKeys") -> CDKeys | E6: =IFERROR(__xludf.DUMMYFUNCTION("""COMPUTED_VALUE"""),13.76) -> 13.76 | F6: =IFERROR(__xludf.DUMMYFUNCTION("""COMPUTED_VALUE"""),5.87) -> 5.87 | G6: =IFERROR(__xludf.DUMMYFUNCTION("""COMPUTED_VALUE"""),1.0) -> 1 | H6: Total Profit
B7: 3 | C7: =IFERROR(__xludf.DUMMYFUNCTION("""COMPUTED_VALUE"""),"Tempest Rising") -> Tempest Rising | D7: =IFERROR(__xludf.DUMMYFUNCTION("""COMPUTED_VALUE"""),"CDKeys") -> CDKeys | E7: =IFERROR(__xludf.DUMMYFUNCTION("""COMPUTED_VALUE"""),13.76) -> 13.76 | F7: =IFERROR(__xludf.DUMMYFUNCTION("""COMPUTED_VALUE"""),5.87) -> 5.87 | G7: =IFERROR(__xludf.DUMMYFUNCTION("""COMPUTED_VALUE"""),0.0) -> 0 | H7: =SUBTOTAL(9,F:F) -> 97.52
B8: 4 | C8: =IFERROR(__xludf.DUMMYFUNCTION("""COMPUTED_VALUE"""),"Tempest Rising") -> Tempest Rising | D8: =IFERROR(__xludf.DUMMYFUNCTION("""COMPUTED_VALUE"""),"Other") -> Other | E8: =IFERROR(__xludf.DUMMYFUNCTION("""COMPUTED_VALUE"""),9.7) -> 9.7 | F8: =IFERROR(__xludf.DUMMYFUNCTION("""COMPUTED_VALUE"""),3.079999999999999) -> 3.08 | G8: =IFERROR(__xludf.DUMMYFUNCTION("""COMPUTED_VALUE"""),0.0) -> 0 | H8: Revenue
B9: 5 | C9: =IFERROR(__xludf.DUMMYFUNCTION("""COMPUTED_VALUE"""),"Tempest Rising") -> Tempest Rising | D9: =IFERROR(__xludf.DUMMYFUNCTION("""COMPUTED_VALUE"""),"King") -> King | E9: =IFERROR(__xludf.DUMMYFUNCTION("""COMPUTED_VALUE"""),9.06) -> 9.06 | F9: =IFERROR(__xludf.DUMMYFUNCTION("""COMPUTED_VALUE"""),3.0300000000000002) -> 3.03 | G9: =IFERROR(__xludf.DUMMYFUNCTION("""COMPUTED_VALUE"""),1.0) -> 1 | H9: =SUBTOTAL(9,E:E) -> 240.99
B10: 6 | C10: =IFERROR(__xludf.DUMMYFUNCTION("""COMPUTED_VALUE"""),"Tempest Rising") -> Tempest Rising | D10: =IFERROR(__xludf.DUMMYFUNCTION("""COMPUTED_VALUE"""),"King") -> King | E10: =IFERROR(__xludf.DUMMYFUNCTION("""COMPUTED_VALUE"""),13.29) -> 13.29 | F10: =IFERROR(__xludf.DUMMYFUNCTION("""COMPUTED_VALUE"""),7.1899999999999995) -> 7.19 | G10: =IFERROR(__xludf.DUMMYFUNCTION("""COMPUTED_VALUE"""),42.0) -> 42 | H10: Sold Items
B11: 7 | C11: =IFERROR(__xludf.DUMMYFUNCTION("""COMPUTED_VALUE"""),"Tempest Rising") -> Tempest Rising | D11: =IFERROR(__xludf.DUMMYFUNCTION("""COMPUTED_VALUE"""),"King") -> King | E11: =IFERROR(__xludf.DUMMYFUNCTION("""COMPUTED_VALUE"""),13.29) -> 13.29 | F11: =IFERROR(__xludf.DUMMYFUNCTION("""COMPUTED_VALUE"""),5.829999999999999) -> 5.83 | G11: =IFERROR(__xludf.DUMMYFUNCTION("""COMPUTED_VALUE"""),38.0) -> 38 | H11: =SUBTOTAL(3,C5:C8795) -> 22
B12: 8 | C12: =IFERROR(__xludf.DUMMYFUNCTION("""COMPUTED_VALUE"""),"Tempest Rising") -> Tempest Rising | D12: =IFERROR(__xludf.DUMMYFUNCTION("""COMPUTED_VALUE"""),"King") -> King | E12: =IFERROR(__xludf.DUMMYFUNCTION("""COMPUTED_VALUE"""),11.46) -> 11.46 | F12: =IFERROR(__xludf.DUMMYFUNCTION("""COMPUTED_VALUE"""),4.000000000000001) -> 4 | G12: =IFERROR(__xludf.DUMMYFUNCTION("""COMPUTED_VALUE"""),41.0) -> 41 | H12: Duration
B13: 9 | C13: =IFERROR(__xludf.DUMMYFUNCTION("""COMPUTED_VALUE"""),"Tempest Rising") -> Tempest Rising | D13: =IFERROR(__xludf.DUMMYFUNCTION("""COMPUTED_VALUE"""),"King") -> King | E13: =IFERROR(__xludf.DUMMYFUNCTION("""COMPUTED_VALUE"""),11.46) -> 11.46 | F13: =IFERROR(__xludf.DUMMYFUNCTION("""COMPUTED_VALUE"""),4.000000000000001) -> 4 | G13: =IFERROR(__xludf.DUMMYFUNCTION("""COMPUTED_VALUE"""),41.0) -> 41 | H13: =SUBTOTAL(1,G:G) -> 25.045455
B14: 10 | C14: =IFERROR(__xludf.DUMMYFUNCTION("""COMPUTED_VALUE"""),"Tempest Rising") -> Tempest Rising | D14: =IFERROR(__xludf.DUMMYFUNCTION("""COMPUTED_VALUE"""),"King") -> King | E14: =IFERROR(__xludf.DUMMYFUNCTION("""COMPUTED_VALUE"""),11.46) -> 11.46 | F14: =IFERROR(__xludf.DUMMYFUNCTION("""COMPUTED_VALUE"""),4.000000000000001) -> 4 | G14: =IFERROR(__xludf.DUMMYFUNCTION("""COMPUTED_VALUE"""),42.0) -> 42 | H14: Min
B15: 11 | C15: =IFERROR(__xludf.DUMMYFUNCTION("""COMPUTED_VALUE"""),"Tempest Rising") -> Tempest Rising | D15: =IFERROR(__xludf.DUMMYFUNCTION("""COMPUTED_VALUE"""),"King") -> King | E15: =IFERROR(__xludf.DUMMYFUNCTION("""COMPUTED_VALUE"""),11.46) -> 11.46 | F15: =IFERROR(__xludf.DUMMYFUNCTION("""COMPUTED_VALUE"""),4.000000000000001) -> 4 | G15: =IFERROR(__xludf.DUMMYFUNCTION("""COMPUTED_VALUE"""),42.0) -> 42 | H15: =MIN(F5:F8795) -> 1.51
B16: 12 | C16: =IFERROR(__xludf.DUMMYFUNCTION("""COMPUTED_VALUE"""),"Tempest Rising") -> Tempest Rising | D16: =IFERROR(__xludf.DUMMYFUNCTION("""COMPUTED_VALUE"""),"King") -> King | E16: =IFERROR(__xludf.DUMMYFUNCTION("""COMPUTED_VALUE"""),11.46) -> 11.46 | F16: =IFERROR(__xludf.DUMMYFUNCTION("""COMPUTED_VALUE"""),4.000000000000001) -> 4 | G16: =IFERROR(__xludf.DUMMYFUNCTION("""COMPUTED_VALUE"""),42.0) -> 42 | H16: High
B17: 13 | C17: =IFERROR(__xludf.DUMMYFUNCTION("""COMPUTED_VALUE"""),"Tempest Rising") -> Tempest Rising | D17: =IFERROR(__xludf.DUMMYFUNCTION("""COMPUTED_VALUE"""),"King") -> King | E17: =IFERROR(__xludf.DUMMYFUNCTION("""COMPUTED_VALUE"""),10.14) -> 10.14 | F17: =IFERROR(__xludf.DUMMYFUNCTION("""COMPUTED_VALUE"""),2.6800000000000006) -> 2.68 | G17: =IFERROR(__xludf.DUMMYFUNCTION("""COMPUTED_VALUE"""),51.0) -> 51 | H17: =MAX(F5:F8795) -> 7.19
B18: 14 | C18: =IFERROR(__xludf.DUMMYFUNCTION("""COMPUTED_VALUE"""),"Tempest Rising") -> Tempest Rising | D18: =IFERROR(__xludf.DUMMYFUNCTION("""COMPUTED_VALUE"""),"King") -> King | E18: =IFERROR(__xludf.DUMMYFUNCTION("""COMPUTED_VALUE"""),10.14) -> 10.14 | F18: =IFERROR(__xludf.DUMMYFUNCTION("""COMPUTED_VALUE"""),2.6800000000000006) -> 2.68 | G18: =IFERROR(__xludf.DUMMYFUNCTION("""COMPUTED_VALUE"""),52.0) -> 52 | H18: Average
B19: 15 | C19: =IFERROR(__xludf.DUMMYFUNCTION("""COMPUTED_VALUE"""),"Tempest Rising") -> Tempest Rising | D19: =IFERROR(__xludf.DUMMYFUNCTION("""COMPUTED_VALUE"""),"King") -> King | E19: =IFERROR(__xludf.DUMMYFUNCTION("""COMPUTED_VALUE"""),10.14) -> 10.14 | F19: =IFERROR(__xludf.DUMMYFUNCTION("""COMPUTED_VALUE"""),2.6800000000000006) -> 2.68 | G19: =IFERROR(__xludf.DUMMYFUNCTION("""COMPUTED_VALUE"""),55.0) -> 55 | H19: =SUBTOTAL(1,F:F) -> 4.4327273
B20: 16 | C20: =IFERROR(__xludf.DUMMYFUNCTION("""COMPUTED_VALUE"""),"Tempest Rising") -> Tempest Rising | D20: =IFERROR(__xludf.DUMMYFUNCTION("""COMPUTED_VALUE"""),"King") -> King | E20: =IFERROR(__xludf.DUMMYFUNCTION("""COMPUTED_VALUE"""),10.14) -> 10.14 | F20: =IFERROR(__xludf.DUMMYFUNCTION("""COMPUTED_VALUE"""),3.16) -> 3.16 | G20: =IFERROR(__xludf.DUMMYFUNCTION("""COMPUTED_VALUE"""),11.0) -> 11 | H20: Difference
B21: 17 | C21: =IFERROR(__xludf.DUMMYFUNCTION("""COMPUTED_VALUE"""),"Tempest Rising") -> Tempest Rising | D21: =IFERROR(__xludf.DUMMYFUNCTION("""COMPUTED_VALUE"""),"King") -> King | E21: =IFERROR(__xludf.DUMMYFUNCTION("""COMPUTED_VALUE"""),10.14) -> 10.14 | F21: =IFERROR(__xludf.DUMMYFUNCTION("""COMPUTED_VALUE"""),3.16) -> 3.16 | G21: =IFERROR(__xludf.DUMMYFUNCTION("""COMPUTED_VALUE"""),13.0) -> 13 | H21: =H17-H15 -> 5.68
B22: 18 | C22: =IFERROR(__xludf.DUMMYFUNCTION("""COMPUTED_VALUE"""),"Tempest Rising") -> Tempest Rising | D22: =IFERROR(__xludf.DUMMYFUNCTION("""COMPUTED_VALUE"""),"King") -> King | E22: =IFERROR(__xludf.DUMMYFUNCTION("""COMPUTED_VALUE"""),10.14) -> 10.14 | F22: =IFERROR(__xludf.DUMMYFUNCTION("""COMPUTED_VALUE"""),6.15) -> 6.15 | G22: =IFERROR(__xludf.DUMMYFUNCTION("""COMPUTED_VALUE"""),13.0) -> 13 | H22: Reference AVG
B23: 19 | C23: =IFERROR(__xludf.DUMMYFUNCTION("""COMPUTED_VALUE"""),"Tempest Rising") -> Tempest Rising | D23: =IFERROR(__xludf.DUMMYFUNCTION("""COMPUTED_VALUE"""),"King") -> King | E23: =IFERROR(__xludf.DUMMYFUNCTION("""COMPUTED_VALUE"""),10.14) -> 10.14 | F23: =IFERROR(__xludf.DUMMYFUNCTION("""COMPUTED_VALUE"""),6.15) -> 6.15 | G23: =IFERROR(__xludf.DUMMYFUNCTION("""COMPUTED_VALUE"""),13.0) -> 13 | H23: =IF(F5<>"", AVERAGE(F$5:F$1000), "") -> 4.4327273
B24: 20 | C24: =IFERROR(__xludf.DUMMYFUNCTION("""COMPUTED_VALUE"""),"Tempest Rising") -> Tempest Rising | D24: =IFERROR(__xludf.DUMMYFUNCTION("""COMPUTED_VALUE"""),"King") -> King | E24: =IFERROR(__xludf.DUMMYFUNCTION("""COMPUTED_VALUE"""),10.15) -> 10.15 | F24: =IFERROR(__xludf.DUMMYFUNCTION("""COMPUTED_VALUE"""),6.16) -> 6.16 | G24: =IFERROR(__xludf.DUMMYFUNCTION("""COMPUTED_VALUE"""),15.0) -> 15
B25: 21 | C25: =IFERROR(__xludf.DUMMYFUNCTION("""COMPUTED_VALUE"""),"Tempest Rising") -> Tempest Rising | D25: =IFERROR(__xludf.DUMMYFUNCTION("""COMPUTED_VALUE"""),"King") -> King | E25: =IFERROR(__xludf.DUMMYFUNCTION("""COMPUTED_VALUE"""),10.15) -> 10.15 | F25: =IFERROR(__xludf.DUMMYFUNCTION("""COMPUTED_VALUE"""),6.16) -> 6.16 | G25: =IFERROR(__xludf.DUMMYFUNCTION("""COMPUTED_VALUE"""),16.0) -> 16
B26: 22 | C26: =IFERROR(__xludf.DUMMYFUNCTION("""COMPUTED_VALUE"""),"Tempest Rising") -> Tempest Rising | D26: =IFERROR(__xludf.DUMMYFUNCTION("""COMPUTED_VALUE"""),"King") -> King | E26: =IFERROR(__xludf.DUMMYFUNCTION("""COMPUTED_VALUE"""),10.15) -> 10.15 | F26: =IFERROR(__xludf.DUMMYFUNCTION("""COMPUTED_VALUE"""),6.16) -> 6.16 | G26: =IFERROR(__xludf.DUMMYFUNCTION("""COMPUTED_VALUE"""),17.0) -> 17

Sheet Entries
A1: Games | B1: Publisher | C1: Quantity | D1: Profit Margin | E1: Avg Profit | F1: Total Profit | G1: Duration | H1: Star | I1: LP | L1: STK
A2: 12 is Better Than 6 | B2: =Publishers!A121 -> HypeTrain Digital | C2: =COUNTIF(Inventory!A:A, A2) -> 1 | D2: =IFERROR(__xludf.DUMMYFUNCTION("IFERROR(AVERAGE(FILTER(Inventory!H:H,Inventory!J:J=""Closed"",Inventory!A:A=A2)),"""")"),1.0) -> 1 | E2: =IFERROR(__xludf.DUMMYFUNCTION("IFERROR(AVERAGE(FILTER(Inventory!G:G,Inventory!J:J=""Closed"",Inventory!A:A=A2)),""0"")"),0.21) -> 0.21 | F2: =IFERROR(__xludf.DUMMYFUNCTION("IFERROR(SUM(FILTER(Inventory!G:G,Inventory!J:J=""Closed"",Inventory!A:A=A2)),""0"")"),0.21) -> 0.21 | G2: =IFERROR(__xludf.DUMMYFUNCTION("IFERROR(AVERAGE(FILTER(Inventory!K:K,Inventory!J:J=""Closed"",Inventory!A:A=A2)),""0"")"),31.0) -> 31 | H2: FALSE | J2: =MAXIFS(Inventory!D:D, Inventory!A:A, A:A) -> 45030 | L2: =COUNTIFS(Inventory!A:A,A2,Inventory!J:J,"Open") -> 0
A3: 911 Operator | B3: =Publishers!A107 -> Games Operators | C3: =COUNTIF(Inventory!A:A, A3) -> 2 | D3: =IFERROR(__xludf.DUMMYFUNCTION("IFERROR(AVERAGE(FILTER(Inventory!H:H,Inventory!J:J=""Closed"",Inventory!A:A=A3)),""0"")"),1.0) -> 1 | E3: =IFERROR(__xludf.DUMMYFUNCTION("IFERROR(AVERAGE(FILTER(Inventory!G:G,Inventory!J:J=""Closed"",Inventory!A:A=A3)),""0"")"),0.725) -> 0.725 | F3: =IFERROR(__xludf.DUMMYFUNCTION("IFERROR(SUM(FILTER(Inventory!G:G,Inventory!J:J=""Closed"",Inventory!A:A=A3)),""0"")"),1.45) -> 1.45 | G3: =IFERROR(__xludf.DUMMYFUNCTION("IFERROR(AVERAGE(FILTER(Inventory!K:K,Inventory!J:J=""Closed"",Inventory!A:A=A3)),""0"")"),22.0) -> 22 | H3: FALSE | J3: =MAXIFS(Inventory!D:D, Inventory!A:A, A:A) -> 44010 | L3: =COUNTIFS(Inventory!A:A,A3,Inventory!J:J,"Open") -> 0
A4: A Little To The Left | B4: =Publishers!A220 -> Secret Mode | C4: =COUNTIF(Inventory!A:A, A4) -> 1 | D4: =IFERROR(__xludf.DUMMYFUNCTION("IFERROR(AVERAGE(FILTER(Inventory!H:H,Inventory!J:J=""Closed"",Inventory!A:A=A4)),"""")"),"") | F4: =IFERROR(__xludf.DUMMYFUNCTION("IFERROR(SUM(FILTER(Inventory!G:G,Inventory!J:J=""Closed"",Inventory!A:A=A4)),""0"")"),"0") -> 0 | H4: FALSE | J4: =MAXIFS(Inventory!D:D, Inventory!A:A, A:A) -> 0 | L4: =COUNTIFS(Inventory!A:A,A4,Inventory!J:J,"Open") -> 1
A5: A Plague Tale: Innocence | B5: =Publishers!A99 -> Focus Home Interactive | C5: =COUNTIF(Inventory!A:A, A5) -> 5 | D5: =IFERROR(__xludf.DUMMYFUNCTION("IFERROR(AVERAGE(FILTER(Inventory!H:H,Inventory!J:J=""Closed"",Inventory!A:A=A5)),""0"")"),0.17317231130307326) -> 0.17317231 | E5: =IFERROR(__xludf.DUMMYFUNCTION("IFERROR(AVERAGE(FILTER(Inventory!G:G,Inventory!J:J=""Closed"",Inventory!A:A=A5)),""0"")"),2.0120000000000005) -> 2.012 | F5: =IFERROR(__xludf.DUMMYFUNCTION("IFERROR(SUM(FILTER(Inventory!G:G,Inventory!J:J=""Closed"",Inventory!A:A=A5)),""0"")"),10.060000000000002) -> 10.06 | G5: =IFERROR(__xludf.DUMMYFUNCTION("IFERROR(AVERAGE(FILTER(Inventory!K:K,Inventory!J:J=""Closed"",Inventory!A:A=A5)),""0"")"),32.6) -> 32.6 | H5: FALSE | J5: =MAXIFS(Inventory!D:D, Inventory!A:A, A:A) -> 44887 | L5: =COUNTIFS(Inventory!A:A,A5,Inventory!J:J,"Open") -> 0
A6: A Plague Tale: Requiem | B6: =Publishers!A99 -> Focus Home Interactive | C6: =COUNTIF(Inventory!A:A, A6) -> 1 | D6: =IFERROR(__xludf.DUMMYFUNCTION("IFERROR(AVERAGE(FILTER(Inventory!H:H,Inventory!J:J=""Closed"",Inventory!A:A=A6)),""0"")"),0.057562524811433216) -> 0.057562525 | E6: =IFERROR(__xludf.DUMMYFUNCTION("IFERROR(AVERAGE(FILTER(Inventory!G:G,Inventory!J:J=""Closed"",Inventory!A:A=A6)),""0"")"),1.4500000000000028) -> 1.45 | F6: =IFERROR(__xludf.DUMMYFUNCTION("IFERROR(SUM(FILTER(Inventory!G:G,Inventory!J:J=""Closed"",Inventory!A:A=A6)),""0"")"),1.4500000000000028) -> 1.45 | G6: =IFERROR(__xludf.DUMMYFUNCTION("IFERROR(AVERAGE(FILTER(Inventory!K:K,Inventory!J:J=""Closed"",Inventory!A:A=A6)),""0"")"),9.0) -> 9 | H6: FALSE | J6: =MAXIFS(Inventory!D:D, Inventory!A:A, A:A) -> 45122 | L6: =COUNTIFS(Inventory!A:A,A6,Inventory!J:J,"Open") -> 0
A7: Above Snakes | B7: =Publishers!A62 -> Crytivo | C7: =COUNTIF(Inventory!A:A, A7) -> 2 | D7: =IFERROR(__xludf.DUMMYFUNCTION("IFERROR(AVERAGE(FILTER(Inventory!H:H,Inventory!J:J=""Closed"",Inventory!A:A=A7)),""0"")"),0.06288664089421458) -> 0.062886641 | E7: =IFERROR(__xludf.DUMMYFUNCTION("IFERROR(AVERAGE(FILTER(Inventory!G:G,Inventory!J:J=""Closed"",Inventory!A:A=A7)),""0"")"),0.8549999999999995) -> 0.855 | F7: =IFERROR(__xludf.DUMMYFUNCTION("IFERROR(SUM(FILTER(Inventory!G:G,Inventory!J:J=""Closed"",Inventory!A:A=A7)),""0"")"),1.709999999999999) -> 1.71 | G7: =IFERROR(__xludf.DUMMYFUNCTION("IFERROR(AVERAGE(FILTER(Inventory!K:K,Inventory!J:J=""Closed"",Inventory!A:A=A7)),""0"")"),1.0) -> 1 | H7: FALSE | J7: =MAXIFS(Inventory!D:D, Inventory!A:A, A:A) -> 45077 | L7: =COUNTIFS(Inventory!A:A,A7,Inventory!J:J,"Open") -> 0
A8: ABRISS - build to destroy | B8: =Publishers!A25 -> astragon Entertainment | C8: =COUNTIF(Inventory!A:A, A8) -> 1 | F8: =IFERROR(__xludf.DUMMYFUNCTION("IFERROR(SUM(FILTER(Inventory!G:G,Inventory!J:J=""Closed"",Inventory!A:A=A8)),""0"")"),"0") -> 0 | H8: FALSE | J8: =MAXIFS(Inventory!D:D, Inventory!A:A, A:A) -> 0 | L8: =COUNTIFS(Inventory!A:A,A8,Inventory!J:J,"Open") -> 1
A9: Absolver | B9: =Publishers!A71 -> Devolver Digital | C9: =COUNTIF(Inventory!A:A, A9) -> 2 | D9: =IFERROR(__xludf.DUMMYFUNCTION("IFERROR(AVERAGE(FILTER(Inventory!H:H,Inventory!J:J=""Closed"",Inventory!A:A=A9)),""0"")"),0.18208851086450928) -> 0.18208851 | E9: =IFERROR(__xludf.DUMMYFUNCTION("IFERROR(AVERAGE(FILTER(Inventory!G:G,Inventory!J:J=""Closed"",Inventory!A:A=A9)),""0"")"),1.3450000000000002) -> 1.345 | F9: =IFERROR(__xludf.DUMMYFUNCTION("IFERROR(SUM(FILTER(Inventory!G:G,Inventory!J:J=""Closed"",Inventory!A:A=A9)),""0"")"),2.6900000000000004) -> 2.69 | G9: =IFERROR(__xludf.DUMMYFUNCTION("IFERROR(AVERAGE(FILTER(Inventory!K:K,Inventory!J:J=""Closed"",Inventory!A:A=A9)),""0"")"),40.5) -> 40.5 | H9: FALSE | J9: =MAXIFS(Inventory!D:D, Inventory!A:A, A:A) -> 44591 | L9: =COUNTIFS(Inventory!A:A,A9,Inventory!J:J,"Open") -> 0
A10: Abzu | B10: =Publishers!A8 -> 505 Games | C10: =COUNTIF(Inventory!A:A, A10) -> 17 | D10: =IFERROR(__xludf.DUMMYFUNCTION("IFERROR(AVERAGE(FILTER(Inventory!H:H,Inventory!J:J=""Closed"",Inventory!A:A=A10)),""0"")"),0.2993622928480093) -> 0.29936229 | E10: =IFERROR(__xludf.DUMMYFUNCTION("IFERROR(AVERAGE(FILTER(Inventory!G:G,Inventory!J:J=""Closed"",Inventory!A:A=A10)),""0"")"),2.094705882352941) -> 2.0947059 | F10: =IFERROR(__xludf.DUMMYFUNCTION("IFERROR(SUM(FILTER(Inventory!G:G,Inventory!J:J=""Closed"",Inventory!A:A=A10)),""0"")"),35.61) -> 35.61 | G10: =IFERROR(__xludf.DUMMYFUNCTION("IFERROR(AVERAGE(FILTER(Inventory!K:K,Inventory!J:J=""Closed"",Inventory!A:A=A10)),""0"")"),9.823529411764707) -> 9.8235294 | H10: FALSE | J10: =MAXIFS(Inventory!D:D, Inventory!A:A, A:A) -> 45236 | L10: =COUNTIFS(Inventory!A:A,A10,Inventory!J:J,"Open") -> 0
A11: Across the Obelisk | B11: =Publishers!A188 -> Paradox Interactive | C11: =COUNTIF(Inventory!A:A, A11) -> 4 | D11: =IFERROR(__xludf.DUMMYFUNCTION("IFERROR(AVERAGE(FILTER(Inventory!H:H,Inventory!J:J=""Closed"",Inventory!A:A=A11)),""0"")"),0.20710438811359097) -> 0.20710439 | E11: =IFERROR(__xludf.DUMMYFUNCTION("IFERROR(AVERAGE(FILTER(Inventory!G:G,Inventory!J:J=""Closed"",Inventory!A:A=A11)),""0"")"),2.5600000000000005) -> 2.56 | F11: =IFERROR(__xludf.DUMMYFUNCTION("IFERROR(SUM(FILTER(Inventory!G:G,Inventory!J:J=""Closed"",Inventory!A:A=A11)),""0"")"),10.240000000000002) -> 10.24 | G11: =IFERROR(__xludf.DUMMYFUNCTION("IFERROR(AVERAGE(FILTER(Inventory!K:K,Inventory!J:J=""Closed"",Inventory!A:A=A11)),""0"")"),1.0) -> 1 | H11: FALSE | J11: =MAXIFS(Inventory!D:D, Inventory!A:A, A:A) -> 45019 | L11: =COUNTIFS(Inventory!A:A,A11,Inventory!J:J,"Open") -> 0
A12: Act of Aggression - Reboot Edition | B12: =Publishers!A87 -> Eugen Systems | C12: =COUNTIF(Inventory!A:A, A12) -> 12 | D12: =IFERROR(__xludf.DUMMYFUNCTION("IFERROR(AVERAGE(FILTER(Inventory!H:H,Inventory!J:J=""Closed"",Inventory!A:A=A12)),""0"")"),0.22616858283609234) -> 0.22616858 | E12: =IFERROR(__xludf.DUMMYFUNCTION("IFERROR(AVERAGE(FILTER(Inventory!G:G,Inventory!J:J=""Closed"",Inventory!A:A=A12)),""0"")"),0.24166666666666667) -> 0.24166667 | F12: =IFERROR(__xludf.DUMMYFUNCTION("IFERROR(SUM(FILTER(Inventory!G:G,Inventory!J:J=""Closed"",Inventory!A:A=A12)),""0"")"),2.9) -> 2.9 | G12: =IFERROR(__xludf.DUMMYFUNCTION("IFERROR(AVERAGE(FILTER(Inventory!K:K,Inventory!J:J=""Closed"",Inventory!A:A=A12)),""0"")"),94.0) -> 94 | H12: FALSE | J12: =MAXIFS(Inventory!D:D, Inventory!A:A, A:A) -> 44968 | L12: =COUNTIFS(Inventory!A:A,A12,Inventory!J:J,"Open") -> 0
A13: After Us | B13: =Publishers!A199 -> Private Division | C13: =COUNTIF(Inventory!A:A, A13) -> 1 | D13: =IFERROR(__xludf.DUMMYFUNCTION("IFERROR(AVERAGE(FILTER(Inventory!H:H,Inventory!J:J=""Closed"",Inventory!A:A=A13)),""0"")"),0.18514350028137305) -> 0.1851435 | E13: =IFERROR(__xludf.DUMMYFUNCTION("IFERROR(AVERAGE(FILTER(Inventory!G:G,Inventory!J:J=""Closed"",Inventory!A:A=A13)),""0"")"),3.289999999999999) -> 3.29 | F13: =IFERROR(__xludf.DUMMYFUNCTION("IFERROR(SUM(FILTER(Inventory!G:G,Inventory!J:J=""Closed"",Inventory!A:A=A13)),""0"")"),3.289999999999999) -> 3.29 | G13: =IFERROR(__xludf.DUMMYFUNCTION("IFERROR(AVERAGE(FILTER(Inventory!K:K,Inventory!J:J=""Closed"",Inventory!A:A=A13)),""0"")"),323.0) -> 323 | H13: FALSE | J13: =MAXIFS(Inventory!D:D, Inventory!A:A, A:A) -> 45467 | L13: =COUNTIFS(Inventory!A:A,A13,Inventory!J:J,"Open") -> 0
A14: Against the Storm | B14: =Publishers!A119 -> Hooded Horse | C14: =COUNTIF(Inventory!A:A, A14) -> 1 | F14: =IFERROR(__xludf.DUMMYFUNCTION("IFERROR(SUM(FILTER(Inventory!G:G,Inventory!J:J=""Closed"",Inventory!A:A=A14)),""0"")"),"0") -> 0 | H14: FALSE | J14: =MAXIFS(Inventory!D:D, Inventory!A:A, A:A) -> 0 | L14: =COUNTIFS(Inventory!A:A,A14,Inventory!J:J,"Open") -> 1
A15: Age of Darkness: Final Stand | B15: =Publishers!A253 -> Team17 Digital | C15: =COUNTIF(Inventory!A:A, A15) -> 2 | D15: =IFERROR(__xludf.DUMMYFUNCTION("IFERROR(AVERAGE(FILTER(Inventory!H:H,Inventory!J:J=""Closed"",Inventory!A:A=A15)),"""")"),-0.36520858296079095) -> -0.36520858 | E15: =IFERROR(__xludf.DUMMYFUNCTION("IFERROR(AVERAGE(FILTER(Inventory!G:G,Inventory!J:J=""Closed"",Inventory!A:A=A15)),""0"")"),-2.37) -> -2.37 | F15: =IFERROR(__xludf.DUMMYFUNCTION("IFERROR(SUM(FILTER(Inventory!G:G,Inventory!J:J=""Closed"",Inventory!A:A=A15)),""0"")"),-4.74) -> -4.74 | G15: =IFERROR(__xludf.DUMMYFUNCTION("IFERROR(AVERAGE(FILTER(Inventory!K:K,Inventory!J:J=""Closed"",Inventory!A:A=A15)),"""")"),454.5) -> 454.5 | H15: FALSE | J15: =MAXIFS(Inventory!D:D, Inventory!A:A, A:A) -> 45385 | L15: =COUNTIFS(Inventory!A:A,A15,Inventory!J:J,"Open") -> 0
